{"name":"时尚集团词库","type":"时尚品牌","description":"时尚集团词库","example":"时尚伊人 座驾 华夏地理 奥迪杂志 男士健康 秦勤 ","words":[{"word":"阿迪达斯","pinyin":"a'di'da'si"},{"word":"阿尔法罗密欧","pinyin":"a'er'fa'luo'mi'ou"},{"word":"阿里斯顿","pinyin":"a'li'si'dun"},{"word":"阿曼尼","pinyin":"a'man'ni"},{"word":"阿斯顿马丁","pinyin":"a'si'dun'ma'ding"},{"word":"爱玛仕","pinyin":"ai'ma'shi"},{"word":"爱慕","pinyin":"ai'mu"},{"word":"安利","pinyin":"an'li"},{"word":"安娜苏","pinyin":"an'na'su"},{"word":"奥德臣","pinyin":"ao'de'chen"},{"word":"奥迪","pinyin":"ao'di"},{"word":"奥迪杂志","pinyin":"ao'di'za'zhi"},{"word":"奥林巴斯","pinyin":"ao'lin'ba'si"},{"word":"奥索卡","pinyin":"ao'suo'ka"},{"word":"巴宝莉","pinyin":"ba'bao'li"},{"word":"芭比布朗","pinyin":"ba'bi'bu'lang"},{"word":"百达裴丽","pinyin":"bai'da'pei'li"},{"word":"百年龄","pinyin":"bai'nian'ling"},{"word":"班提酒业","pinyin":"ban'ti'jiu'ye"},{"word":"宝马","pinyin":"bao'ma"},{"word":"保时捷","pinyin":"bao'shi'jie"},{"word":"报喜鸟","pinyin":"bao'xi'niao"},{"word":"宝资","pinyin":"bao'zi"},{"word":"北京现代途胜","pinyin":"bei'jing'xian'dai'tu'sheng"},{"word":"贝令妃","pinyin":"bei'ling'fei"},{"word":"北欧风情","pinyin":"bei'ou'feng'qing"},{"word":"奔驰","pinyin":"ben'chi"},{"word":"本田","pinyin":"ben'tian"},{"word":"本田日产","pinyin":"ben'tian'ri'chan"},{"word":"碧欧泉","pinyin":"bi'ou'quan"},{"word":"彪马","pinyin":"biao'ma"},{"word":"别克","pinyin":"bie'ke"},{"word":"宾利","pinyin":"bin'li"},{"word":"伯爵","pinyin":"bo'jue"},{"word":"博世","pinyin":"bo'shi"},{"word":"蔡瀛","pinyin":"cai'ying"},{"word":"常娟","pinyin":"chang'juan"},{"word":"陈碧松","pinyin":"chen'bi'song"},{"word":"陈谊","pinyin":"chen'yi"},{"word":"宠爱之名","pinyin":"chong'ai'zhi'ming"},{"word":"楚朗","pinyin":"chu'lang"},{"word":"大范宁","pinyin":"da'fan'ning"},{"word":"达芬奇","pinyin":"da'fen'qi"},{"word":"戴姆勒","pinyin":"dai'mu'le"},{"word":"道奇凯领","pinyin":"dao'qi'kai'ling"},{"word":"德红梅","pinyin":"de'hong'mei"},{"word":"邓禄普","pinyin":"deng'lu'pu"},{"word":"登喜路","pinyin":"deng'xi'lu"},{"word":"迪奥","pinyin":"di'ao"},{"word":"蒂芙尼","pinyin":"di'fu'ni"},{"word":"鼎佳国际","pinyin":"ding'jia'guo'ji"},{"word":"杜雷斯","pinyin":"du'lei'si"},{"word":"发朵","pinyin":"fa'duo"},{"word":"法拉利","pinyin":"fa'la'li"},{"word":"梵克雅宝","pinyin":"fan'ke'ya'bao"},{"word":"范思哲","pinyin":"fan'si'zhe"},{"word":"菲拉格慕","pinyin":"fei'la'ge'mu"},{"word":"飞利浦","pinyin":"fei'li'pu"},{"word":"芬迪","pinyin":"fen'di"},{"word":"丰田","pinyin":"feng'tian"},{"word":"芙莱莎","pinyin":"fu'lai'sha"},{"word":"傅琳","pinyin":"fu'lin"},{"word":"富隆酒业","pinyin":"fu'long'jiu'ye"},{"word":"福特","pinyin":"fu'te"},{"word":"高夫","pinyin":"gao'fu"},{"word":"格力普","pinyin":"ge'li'pu"},{"word":"哥伦比尼","pinyin":"ge'lun'bi'ni"},{"word":"古琦","pinyin":"gu'qi"},{"word":"古越龙山黄酒","pinyin":"gu'yue'long'shan'huang'jiu"},{"word":"海尔","pinyin":"hai'er"},{"word":"海蓝之谜","pinyin":"hai'lan'zhi'mi"},{"word":"汉和","pinyin":"han'he"},{"word":"好管家","pinyin":"hao'guan'jia"},{"word":"郝宁","pinyin":"hao'ning"},{"word":"豪雅表","pinyin":"hao'ya'biao"},{"word":"赫莲娜","pinyin":"he'lian'na"},{"word":"花梨","pinyin":"hua'li"},{"word":"华伦天奴","pinyin":"hua'lun'tian'nu"},{"word":"华硕","pinyin":"hua'shuo"},{"word":"华夏地理","pinyin":"hua'xia'di'li"},{"word":"黄辉","pinyin":"huang'hui"},{"word":"汇菱","pinyin":"hui'ling"},{"word":"惠普","pinyin":"hui'pu"},{"word":"汇源果汁","pinyin":"hui'yuan'guo'zhi"},{"word":"纪梵希","pinyin":"ji'fan'xi"},{"word":"吉列","pinyin":"ji'lie"},{"word":"吉普","pinyin":"ji'pu"},{"word":"家美乐","pinyin":"jia'mei'le"},{"word":"佳能","pinyin":"jia'neng"},{"word":"佳泰兴业","pinyin":"jia'tai'xing'ye"},{"word":"蒋雷","pinyin":"jiang'lei"},{"word":"娇兰","pinyin":"jiao'lan"},{"word":"娇韵诗","pinyin":"jiao'yun'shi"},{"word":"捷豹","pinyin":"jie'bao"},{"word":"捷成洋酒","pinyin":"jie'cheng'yang'jiu"},{"word":"杰卡斯葡萄酒","pinyin":"jie'ka'si'pu'tao'jiu"},{"word":"杰尼亚","pinyin":"jie'ni'ya"},{"word":"杰士邦","pinyin":"jie'shi'bang"},{"word":"金利来","pinyin":"jin'li'lai"},{"word":"精工","pinyin":"jing'gong"},{"word":"劲旅","pinyin":"jing'lv"},{"word":"骏德酒业","pinyin":"jun'de'jiu'ye"},{"word":"卡地亚","pinyin":"ka'di'ya"},{"word":"卡尔文克莱恩","pinyin":"ka'er'wen'ke'lai'en"},{"word":"凯迪拉克","pinyin":"kai'di'la'ke"},{"word":"科宝博洛尼","pinyin":"ke'bao'bo'luo'ni"},{"word":"克莱斯勒","pinyin":"ke'lai'si'le"},{"word":"科勒","pinyin":"ke'le"},{"word":"莱珀妮","pinyin":"lai'po'ni"},{"word":"蓝博基尼","pinyin":"lan'bo'ji'ni"},{"word":"兰蔻","pinyin":"lan'kou"},{"word":"兰芝","pinyin":"lan'zhi"},{"word":"浪琴","pinyin":"lang'qin"},{"word":"劳斯莱斯","pinyin":"lao'si'lai'si"},{"word":"雷达","pinyin":"lei'da"},{"word":"雷克萨斯","pinyin":"lei'ke'sa'si"},{"word":"李崇华","pinyin":"li'chong'hua"},{"word":"理肤泉","pinyin":"li'fu'quan"},{"word":"李军","pinyin":"li'jun"},{"word":"李维斯","pinyin":"li'wei'si"},{"word":"李晓娟","pinyin":"li'xiao'juan"},{"word":"李永适","pinyin":"li'yong'shi"},{"word":"联想","pinyin":"lian'xiang"},{"word":"梁朝辉","pinyin":"liang'chao'hui"},{"word":"廖敏","pinyin":"liao'min"},{"word":"林明谦","pinyin":"lin'ming'qian"},{"word":"刘江","pinyin":"liu'jiang"},{"word":"刘蓉","pinyin":"liu'rong"},{"word":"刘勇超","pinyin":"liu'yong'chao"},{"word":"刘阅微","pinyin":"liu'yue'wei"},{"word":"路虎","pinyin":"lu'hu"},{"word":"露华浓","pinyin":"lu'hua'nong"},{"word":"路璐","pinyin":"lu'lu"},{"word":"路易威登","pinyin":"lu'yi'wei'deng"},{"word":"罗博报告","pinyin":"luo'bo'bao'gao"},{"word":"马爹利","pinyin":"ma'die'li"},{"word":"马艳丽","pinyin":"ma'yan'li"},{"word":"迈巴赫","pinyin":"mai'ba'he"},{"word":"美宝莲","pinyin":"mei'bao'lian"},{"word":"美标","pinyin":"mei'biao"},{"word":"美国星座","pinyin":"mei'guo'xing'zuo"},{"word":"美克美家","pinyin":"mei'ke'mei'jia"},{"word":"玫琳凯","pinyin":"mei'lin'kai"},{"word":"梅赛德斯","pinyin":"mei'sai'de'si"},{"word":"美食与美酒","pinyin":"mei'shi'yu'mei'jiu"},{"word":"美夏葡萄酒","pinyin":"mei'xia'pu'tao'jiu"},{"word":"梦特娇","pinyin":"meng'te'jiao"},{"word":"摩托罗拉","pinyin":"mo'tuo'luo'la"},{"word":"耐克","pinyin":"nai'ke"},{"word":"男人装","pinyin":"nan'ren'zhuang"},{"word":"男士健康","pinyin":"nan'shi'jian'kang"},{"word":"尼康","pinyin":"ni'kang"},{"word":"尼太格皮草","pinyin":"ni'tai'ge'pi'cao"},{"word":"妮维雅","pinyin":"ni'wei'ya"},{"word":"诺基亚","pinyin":"nuo'ji'ya"},{"word":"欧宝","pinyin":"ou'bao"},{"word":"讴歌","pinyin":"ou'ge"},{"word":"欧莱雅","pinyin":"ou'lai'ya"},{"word":"欧米茄","pinyin":"ou'mi'jia"},{"word":"欧珀莱","pinyin":"ou'po'lai"},{"word":"欧舒丹","pinyin":"ou'shu'dan"},{"word":"派乐酒业","pinyin":"pai'le'jiu'ye"},{"word":"潘箭","pinyin":"pan'jian"},{"word":"潘婷","pinyin":"pan'ting"},{"word":"彭澎","pinyin":"peng'peng"},{"word":"苹果","pinyin":"ping'guo"},{"word":"普拉达","pinyin":"pu'la'da"},{"word":"葡萄酒","pinyin":"pu'tao'jiu"},{"word":"七彩小鱼","pinyin":"qi'cai'xiao'yu"},{"word":"齐唯","pinyin":"qi'wei"},{"word":"倩碧","pinyin":"qian'bi"},{"word":"乾祥","pinyin":"qian'xiang"},{"word":"乾祥服饰","pinyin":"qian'xiang'fu'shi"},{"word":"乾祥服饰旗舰店","pinyin":"qian'xiang'fu'shi'qi'jian'dian"},{"word":"强生","pinyin":"qiang'sheng"},{"word":"壳牌","pinyin":"qiao'pai"},{"word":"乔治阿玛尼","pinyin":"qiao'zhi'a'ma'ni"},{"word":"乔治百龄坛","pinyin":"qiao'zhi'bai'ling'tan"},{"word":"秦勤","pinyin":"qin'qin"},{"word":"雀巢","pinyin":"que'chao"},{"word":"人头马","pinyin":"ren'tou'ma"},{"word":"人头马干邑","pinyin":"ren'tou'ma'gan'yi"},{"word":"三星","pinyin":"san'xing"},{"word":"神露酒业","pinyin":"shen'lu'jiu'ye"},{"word":"圣罗兰","pinyin":"sheng'luo'lan"},{"word":"施华洛世奇","pinyin":"shi'hua'luo'shi'qi"},{"word":"石静柯","pinyin":"shi'jing'ke"},{"word":"时尚芭莎","pinyin":"shi'shang'ba'sha"},{"word":"时尚家居","pinyin":"shi'shang'jia'ju"},{"word":"时尚健康","pinyin":"shi'shang'jian'kang"},{"word":"时尚旅游","pinyin":"shi'shang'lv'you"},{"word":"时尚时间","pinyin":"shi'shang'shi'jian"},{"word":"时尚先生","pinyin":"shi'shang'xian'sheng"},{"word":"时尚伊人","pinyin":"shi'shang'yi'ren"},{"word":"瘦马","pinyin":"shou'ma"},{"word":"斯巴鲁森林人","pinyin":"si'ba'lu'sen'lin'ren"},{"word":"丝芙兰","pinyin":"si'fu'lan"},{"word":"思魅欧泊莱","pinyin":"si'mei'ou'bo'lai"},{"word":"斯沃琪","pinyin":"si'wo'qi"},{"word":"苏芒","pinyin":"su'mang"},{"word":"孙福强","pinyin":"sun'fu'qiang"},{"word":"孙雅君","pinyin":"sun'ya'jun"},{"word":"索尼","pinyin":"suo'ni"},{"word":"索尼爱立信","pinyin":"suo'ni'ai'li'xin"},{"word":"索亚特","pinyin":"suo'ya'te"},{"word":"泰诺健","pinyin":"tai'nuo'jian"},{"word":"唐正一","pinyin":"tang'zheng'yi"},{"word":"桃乐丝","pinyin":"tao'le'si"},{"word":"天梭","pinyin":"tian'suo"},{"word":"通用","pinyin":"tong'yong"},{"word":"万宝龙","pinyin":"wan'bao'long"},{"word":"王锋","pinyin":"wang'feng"},{"word":"王海波","pinyin":"wang'hai'bo"},{"word":"王抒今","pinyin":"wang'shu'jin"},{"word":"王晓枫","pinyin":"wang'xiao'feng"},{"word":"汪洋","pinyin":"wang'yang"},{"word":"王媛","pinyin":"wang'yuan"},{"word":"王月","pinyin":"wang'yue"},{"word":"威娜","pinyin":"wei'na"},{"word":"薇姿","pinyin":"wei'zi"},{"word":"文洁","pinyin":"wen'jie"},{"word":"沃尔沃","pinyin":"wo'er'wo"},{"word":"五彩石","pinyin":"wu'cai'shi"},{"word":"吴泓","pinyin":"wu'hong"},{"word":"西门子","pinyin":"xi'men'zi"},{"word":"席梦思","pinyin":"xi'meng'si"},{"word":"希思黎","pinyin":"xi'si'li"},{"word":"西亚特","pinyin":"xi'ya'te"},{"word":"暇步士","pinyin":"xia'bu'shi"},{"word":"夏图","pinyin":"xia'tu"},{"word":"香奈儿","pinyin":"xiang'nai'er"},{"word":"萧邦","pinyin":"xiao'bang"},{"word":"小狗儿","pinyin":"xiao'gou'er"},{"word":"小黄鱼","pinyin":"xiao'huang'yu"},{"word":"小鱼儿","pinyin":"xiao'yu'er"},{"word":"写意空间","pinyin":"xie'yi'kong'jian"},{"word":"新潮电子酒窖","pinyin":"xin'chao'dian'zi'jiu'jiao"},{"word":"徐聪","pinyin":"xu'cong"},{"word":"徐广宇","pinyin":"xu'guang'yu"},{"word":"徐洁民","pinyin":"xu'jie'min"},{"word":"徐巍","pinyin":"xu'wei"},{"word":"轩尼诗","pinyin":"xuan'ni'shi"},{"word":"雪佛兰","pinyin":"xue'fo'lan"},{"word":"雪花啤酒","pinyin":"xue'hua'pi'jiu"},{"word":"薛嵛","pinyin":"xue'yu"},{"word":"寻范","pinyin":"xun'fan"},{"word":"雅诗兰黛","pinyin":"ya'shi'lan'dai"},{"word":"殷红","pinyin":"yan'hong"},{"word":"炎焱妖","pinyin":"yan'yan'yao"},{"word":"炎焱妖服饰","pinyin":"yan'yan'yao'fu'shi"},{"word":"炎焱妖服饰旗舰店","pinyin":"yan'yan'yao'fu'shi'qi'jian'dian"},{"word":"炎焱妖旗舰店","pinyin":"yan'yan'yao'qi'jian'dian"},{"word":"宜家","pinyin":"yi'jia"},{"word":"伊利","pinyin":"yi'li"},{"word":"伊丽莎白雅顿","pinyin":"yi'li'sha'bai'ya'dun"},{"word":"依诺维绅","pinyin":"yi'nuo'wei'shen"},{"word":"一汽大众","pinyin":"yi'qi'da'zhong"},{"word":"一汽丰田","pinyin":"yi'qi'feng'tian"},{"word":"逸鼠顿","pinyin":"yi'shu'dun"},{"word":"殷智贤","pinyin":"yin'zhi'xian"},{"word":"英菲尼迪","pinyin":"ying'fei'ni'di"},{"word":"英翔宇","pinyin":"ying'xiang'yu"},{"word":"由东往西","pinyin":"you'dong'wang'xi"},{"word":"雨花石","pinyin":"yu'hua'shi"},{"word":"余辉","pinyin":"yu'hui"},{"word":"玉兰油","pinyin":"yu'lan'you"},{"word":"羽西","pinyin":"yu'xi"},{"word":"张琳","pinyin":"zhang'lin"},{"word":"张米","pinyin":"zhang'mi"},{"word":"张念军","pinyin":"zhang'nian'jun"},{"word":"张晓冬","pinyin":"zhang'xiao'dong"},{"word":"张媛","pinyin":"zhang'yuan"},{"word":"张稚玉","pinyin":"zhang'zhi'yu"},{"word":"植村秀","pinyin":"zhi'cun'xiu"},{"word":"钟宁","pinyin":"zhong'ning"},{"word":"中堂","pinyin":"zhong'tang"},{"word":"中意葡萄酒展","pinyin":"zhong'yi'pu'tao'jiu'zhan"},{"word":"周大福","pinyin":"zhou'da'fu"},{"word":"朱航","pinyin":"zhu'hang"},{"word":"资生堂","pinyin":"zi'sheng'tang"},{"word":"座驾","pinyin":"zuo'jia"}]}