{"name":"焊接工艺人员词库2","type":"材料科学","description":"焊接专业词汇，水轮发电机组焊接结构词汇","example":"按图纸技术要求 按线 半割 半自动气保焊机 半自动气割机 薄涂料焊条 ","words":[{"word":"阿海","pinyin":"a'hai"},{"word":"按图纸技术要求","pinyin":"an'tu'zhi'ji'shu'yao'qiu"},{"word":"按图纸及相关标准要求","pinyin":"an'tu'zhi'ji'xiang'guan'biao'zhun'yao'qiu"},{"word":"按线","pinyin":"an'xian"},{"word":"安装高程","pinyin":"an'zhuang'gao'cheng"},{"word":"把合工艺螺栓","pinyin":"ba'he'gong'yi'luo'shuan"},{"word":"把合牢固","pinyin":"ba'he'lao'gu"},{"word":"把合螺栓","pinyin":"ba'he'luo'shuan"},{"word":"巴基斯坦","pinyin":"ba'ji'si'tan"},{"word":"半割","pinyin":"ban'ge"},{"word":"半割坡口","pinyin":"ban'ge'po'kou"},{"word":"半自动气保焊机","pinyin":"ban'zi'dong'qi'bao'han'ji"},{"word":"半自动气割机","pinyin":"ban'zi'dong'qi'ge'ji"},{"word":"背面","pinyin":"bei'mian"},{"word":"背面气体","pinyin":"bei'mian'qi'ti"},{"word":"背面清根","pinyin":"bei'mian'qing'gen"},{"word":"鼻端固定导叶","pinyin":"bi'duan'gu'ding'dao'ye"},{"word":"比能","pinyin":"bi'neng"},{"word":"比转速","pinyin":"bi'zhuan'su"},{"word":"表计压力","pinyin":"biao'ji'ya'li"},{"word":"表面硬质堆焊","pinyin":"biao'mian'ying'zhi'dui'han"},{"word":"波浪变形","pinyin":"bo'lang'bian'xing"},{"word":"波浪度","pinyin":"bo'lang'du"},{"word":"薄涂料焊条","pinyin":"bo'tu'liao'han'tiao"},{"word":"补偿节","pinyin":"bu'chang'jie"},{"word":"部件","pinyin":"bu'jian"},{"word":"不可调式水利机械","pinyin":"bu'ke'tiao'shi'shui'li'ji'xie"},{"word":"布鲁桥","pinyin":"bu'lu'qiao"},{"word":"补气试验","pinyin":"bu'qi'shi'yan"},{"word":"藏木","pinyin":"cang'mu"},{"word":"操作架","pinyin":"cao'zuo'jia"},{"word":"层间温度","pinyin":"ceng'jian'wen'du"},{"word":"叉管","pinyin":"cha'guan"},{"word":"插装","pinyin":"cha'zhuang"},{"word":"产品成套办公室","pinyin":"chan'pin'cheng'tao'ban'gong'shi"},{"word":"产品金属零部件涂漆","pinyin":"chan'pin'jin'shu'ling'bu'jian'tu'qi"},{"word":"长甸","pinyin":"chang'dian"},{"word":"长河坝","pinyin":"chang'he'ba"},{"word":"超负荷非正常运行区","pinyin":"chao'fu'he'fei'zheng'chang'yun'xing'qu"},{"word":"衬板","pinyin":"chen'ban"},{"word":"衬垫","pinyin":"chen'dian"},{"word":"陈明","pinyin":"chen'ming"},{"word":"陈志磊","pinyin":"chen'zhi'lei"},{"word":"成套办","pinyin":"cheng'tao'ban"},{"word":"成型","pinyin":"cheng'xing"},{"word":"成形余量","pinyin":"cheng'xing'yu'liang"},{"word":"冲击式水轮机","pinyin":"chong'ji'shi'shui'lun'ji"},{"word":"冲击式转轮公称直径","pinyin":"chong'ji'shi'zhuan'lun'gong'cheng'zhi'jing"},{"word":"楚卡斯","pinyin":"chu'ka'si"},{"word":"出口角度","pinyin":"chu'kou'jiao'du"},{"word":"初生空化系数","pinyin":"chu'sheng'kong'hua'xi'shu"},{"word":"初始压力","pinyin":"chu'shi'ya'li"},{"word":"初始转速","pinyin":"chu'shi'zhuan'su"},{"word":"出线盒","pinyin":"chu'xian'he"},{"word":"传输导叶","pinyin":"chuan'shu'dao'ye"},{"word":"传输室","pinyin":"chuan'shu'shi"},{"word":"锤击","pinyin":"chui'ji"},{"word":"垂直度","pinyin":"chui'zhi'du"},{"word":"磁轭圈","pinyin":"ci'e'quan"},{"word":"凑合节","pinyin":"cou'he'jie"},{"word":"搭板","pinyin":"da'ban"},{"word":"搭焊牢固","pinyin":"da'han'lao'gu"},{"word":"搭焊顺序","pinyin":"da'han'shun'xu"},{"word":"大件厂","pinyin":"da'jian'chang"},{"word":"大脚角焊缝","pinyin":"da'jiao'jiao'han'feng"},{"word":"搭接接头","pinyin":"da'jie'jie'tou"},{"word":"大面坡口","pinyin":"da'mian'po'kou"},{"word":"打磨","pinyin":"da'mo"},{"word":"大坡口","pinyin":"da'po'kou"},{"word":"大坡口侧","pinyin":"da'po'kou'ce"},{"word":"大气压","pinyin":"da'qi'ya"},{"word":"打压工具","pinyin":"da'ya'gong'ju"},{"word":"大中型水轮机","pinyin":"da'zhong'xing'shui'lun'ji"},{"word":"单导叶接力器","pinyin":"dan'dao'ye'jie'li'qi"},{"word":"单幅板转子支架","pinyin":"dan'fu'ban'zhuan'zi'zhi'jia"},{"word":"单级水泵水轮机","pinyin":"dan'ji'shui'beng'shui'lun'ji"},{"word":"单位飞逸转速","pinyin":"dan'wei'fei'yi'zhuan'su"},{"word":"单位功率","pinyin":"dan'wei'gong'lv"},{"word":"单位量","pinyin":"dan'wei'liang"},{"word":"单位流量","pinyin":"dan'wei'liu'liang"},{"word":"单位水力矩","pinyin":"dan'wei'shui'li'ju"},{"word":"单位水推力","pinyin":"dan'wei'shui'tui'li"},{"word":"单位转速","pinyin":"dan'wei'zhuan'su"},{"word":"导电管","pinyin":"dao'dian'guan"},{"word":"导水机构","pinyin":"dao'shui'ji'gou"},{"word":"导水机构部分","pinyin":"dao'shui'ji'gou'bu'fen"},{"word":"导水机构中心线","pinyin":"dao'shui'ji'gou'zhong'xin'xian"},{"word":"导叶","pinyin":"dao'ye"},{"word":"导叶臂","pinyin":"dao'ye'bi"},{"word":"导叶端面密封","pinyin":"dao'ye'duan'mian'mi'feng"},{"word":"导叶分布圆","pinyin":"dao'ye'fen'bu'yuan"},{"word":"导叶高度","pinyin":"dao'ye'gao'du"},{"word":"导叶过载保护","pinyin":"dao'ye'guo'zai'bao'hu"},{"word":"导叶过载保护装置","pinyin":"dao'ye'guo'zai'bao'hu'zhuang'zhi"},{"word":"导叶接力器","pinyin":"dao'ye'jie'li'qi"},{"word":"导叶开口","pinyin":"dao'ye'kai'kou"},{"word":"导叶立面密封","pinyin":"dao'ye'li'mian'mi'feng"},{"word":"导叶力特性","pinyin":"dao'ye'li'te'xing"},{"word":"导叶连杆","pinyin":"dao'ye'lian'gan"},{"word":"导叶调节装置","pinyin":"dao'ye'tiao'jie'zhuang'zhi"},{"word":"导叶限位","pinyin":"dao'ye'xian'wei"},{"word":"导叶限位块","pinyin":"dao'ye'xian'wei'kuai"},{"word":"导叶止推轴承","pinyin":"dao'ye'zhi'tui'zhou'cheng"},{"word":"导叶止推装置","pinyin":"dao'ye'zhi'tui'zhuang'zhi"},{"word":"导叶轴","pinyin":"dao'ye'zhou"},{"word":"导叶轴承","pinyin":"dao'ye'zhou'cheng"},{"word":"导叶轴密封","pinyin":"dao'ye'zhou'mi'feng"},{"word":"导轴承","pinyin":"dao'zhou'cheng"},{"word":"导轴承中心线","pinyin":"dao'zhou'cheng'zhong'xin'xian"},{"word":"等离子切割机","pinyin":"deng'li'zi'qie'ge'ji"},{"word":"灯泡式水轮机","pinyin":"deng'pao'shi'shui'lun'ji"},{"word":"灯泡体","pinyin":"deng'pao'ti"},{"word":"灯泡体支柱","pinyin":"deng'pao'ti'zhi'zhu"},{"word":"低负荷非正常运行区","pinyin":"di'fu'he'fei'zheng'chang'yun'xing'qu"},{"word":"底环","pinyin":"di'huan"},{"word":"底角板","pinyin":"di'jiao'ban"},{"word":"低压测量断面","pinyin":"di'ya'ce'liang'duan'mian"},{"word":"第一部分附录","pinyin":"di'yi'bu'fen'fu'lu"},{"word":"垫板","pinyin":"dian'ban"},{"word":"点焊","pinyin":"dian'han"},{"word":"电焊件","pinyin":"dian'han'jian"},{"word":"电焊件退火工艺守则","pinyin":"dian'han'jian'tui'huo'gong'yi'shou'ze"},{"word":"电弧点焊","pinyin":"dian'hu'dian'han"},{"word":"电弧缝焊","pinyin":"dian'hu'feng'han"},{"word":"电弧焊","pinyin":"dian'hu'han"},{"word":"电极","pinyin":"dian'ji"},{"word":"垫片","pinyin":"dian'pian"},{"word":"垫平","pinyin":"dian'ping"},{"word":"电气焊","pinyin":"dian'qi'han"},{"word":"垫条","pinyin":"dian'tiao"},{"word":"垫稳","pinyin":"dian'wen"},{"word":"电渣焊","pinyin":"dian'zha'han"},{"word":"电渣焊电极","pinyin":"dian'zha'han'dian'ji"},{"word":"电站空化系数","pinyin":"dian'zhan'kong'hua'xi'shu"},{"word":"电站水头","pinyin":"dian'zhan'shui'tou"},{"word":"电站最大水头","pinyin":"dian'zhan'zui'da'shui'tou"},{"word":"电站最小水头","pinyin":"dian'zhan'zui'xiao'shui'tou"},{"word":"电子设备厂","pinyin":"dian'zi'she'bei'chang"},{"word":"电子束焊","pinyin":"dian'zi'shu'han"},{"word":"电阻焊电极","pinyin":"dian'zu'han'dian'ji"},{"word":"吊耳","pinyin":"diao'er"},{"word":"刁丽英","pinyin":"diao'li'ying"},{"word":"吊攀","pinyin":"diao'pan"},{"word":"吊装","pinyin":"diao'zhuang"},{"word":"吊装中心体","pinyin":"diao'zhuang'zhong'xin'ti"},{"word":"顶盖","pinyin":"ding'gai"},{"word":"顶环板","pinyin":"ding'huan'ban"},{"word":"顶油管","pinyin":"ding'you'guan"},{"word":"定子机座","pinyin":"ding'zi'ji'zuo"},{"word":"定子铁芯","pinyin":"ding'zi'tie'xin"},{"word":"端板","pinyin":"duan'ban"},{"word":"端盖","pinyin":"duan'gai"},{"word":"锻件","pinyin":"duan'jian"},{"word":"短路焊","pinyin":"duan'lu'han"},{"word":"堆焊层","pinyin":"dui'han'ceng"},{"word":"堆焊缓冲层","pinyin":"dui'han'huan'chong'ceng"},{"word":"对接接头","pinyin":"dui'jie'jie'tou"},{"word":"对正","pinyin":"dui'zheng"},{"word":"多股电极","pinyin":"duo'gu'dian'ji"},{"word":"多级式蓄能泵","pinyin":"duo'ji'shi'xu'neng'beng"},{"word":"多级水泵水轮机","pinyin":"duo'ji'shui'beng'shui'lun'ji"},{"word":"额定比转速","pinyin":"e'ding'bi'zhuan'su"},{"word":"额定功率","pinyin":"e'ding'gong'lv"},{"word":"额定流量","pinyin":"e'ding'liu'liang"},{"word":"额定水头","pinyin":"e'ding'shui'tou"},{"word":"额定值","pinyin":"e'ding'zhi"},{"word":"额定转速","pinyin":"e'ding'zhuan'su"},{"word":"发出最大功率的流量","pinyin":"fa'chu'zui'da'gong'lv'de'liu'liang"},{"word":"发出最大功率的水头","pinyin":"fa'chu'zui'da'gong'lv'de'shui'tou"},{"word":"法兰板","pinyin":"fa'lan'ban"},{"word":"发射涂料焊条","pinyin":"fa'she'tu'liao'han'tiao"},{"word":"反击式水轮机","pinyin":"fan'ji'shi'shui'lun'ji"},{"word":"反击式水轮机空蚀评定","pinyin":"fan'ji'shi'shui'lun'ji'kong'shi'ping'ding"},{"word":"翻身架","pinyin":"fan'shen'jia"},{"word":"反向止推轴承","pinyin":"fan'xiang'zhi'tui'zhou'cheng"},{"word":"方钢","pinyin":"fang'gang"},{"word":"方钢拉筋","pinyin":"fang'gang'la'jin"},{"word":"放样","pinyin":"fang'yang"},{"word":"放样线","pinyin":"fang'yang'xian"},{"word":"防止变形","pinyin":"fang'zhi'bian'xing"},{"word":"飞逸工况","pinyin":"fei'yi'gong'kuang"},{"word":"飞逸试验","pinyin":"fei'yi'shi'yan"},{"word":"飞逸特性曲线","pinyin":"fei'yi'te'xing'qu'xian"},{"word":"飞逸转速","pinyin":"fei'yi'zhuan'su"},{"word":"非正常运行的功率上限","pinyin":"fei'zheng'chang'yun'xing'de'gong'lv'shang'xian"},{"word":"非正常运行的功率下限","pinyin":"fei'zheng'chang'yun'xing'de'gong'lv'xia'xian"},{"word":"分半键","pinyin":"fen'ban'jian"},{"word":"分瓣式中间环","pinyin":"fen'ban'shi'zhong'jian'huan"},{"word":"分瓣数","pinyin":"fen'ban'shu"},{"word":"分厂","pinyin":"fen'chang"},{"word":"分段退步焊接","pinyin":"fen'duan'tui'bu'han'jie"},{"word":"分流管","pinyin":"fen'liu'guan"},{"word":"风铲","pinyin":"feng'chan"},{"word":"封底","pinyin":"feng'di"},{"word":"枫树坝","pinyin":"feng'shu'ba"},{"word":"凤滩","pinyin":"feng'tan"},{"word":"腹板","pinyin":"fu'ban"},{"word":"付康","pinyin":"fu'kang"},{"word":"附录","pinyin":"fu'lu"},{"word":"负载试验","pinyin":"fu'zai'shi'yan"},{"word":"副轴","pinyin":"fu'zhou"},{"word":"盖板","pinyin":"gai'ban"},{"word":"甘洪丰","pinyin":"gan'hong'feng"},{"word":"感应焊","pinyin":"gan'ying'han"},{"word":"钢板","pinyin":"gang'ban"},{"word":"钢板热成型工艺守则","pinyin":"gang'ban're'cheng'xing'gong'yi'shou'ze"},{"word":"钢琴线","pinyin":"gang'qin'xian"},{"word":"高程","pinyin":"gao'cheng"},{"word":"高压测量断面","pinyin":"gao'ya'ce'liang'duan'mian"},{"word":"高压顶油管","pinyin":"gao'ya'ding'you'guan"},{"word":"高压油顶起","pinyin":"gao'ya'you'ding'qi"},{"word":"各层","pinyin":"ge'ceng"},{"word":"割出坡口","pinyin":"ge'chu'po'kou"},{"word":"葛为民","pinyin":"ge'wei'min"},{"word":"割渣","pinyin":"ge'zha"},{"word":"公称型线","pinyin":"gong'cheng'xing'xian"},{"word":"工具螺钉","pinyin":"gong'ju'luo'ding"},{"word":"工况","pinyin":"gong'kuang"},{"word":"功率","pinyin":"gong'lv"},{"word":"工艺部","pinyin":"gong'yi'bu"},{"word":"工艺守则","pinyin":"gong'yi'shou'ze"},{"word":"固定导叶","pinyin":"gu'ding'dao'ye"},{"word":"固定抗磨止漏环","pinyin":"gu'ding'kang'mo'zhi'lou'huan"},{"word":"固定可拆卸构件","pinyin":"gu'ding'ke'chai'xie'gou'jian"},{"word":"固定止漏环","pinyin":"gu'ding'zhi'lou'huan"},{"word":"官地","pinyin":"guan'di"},{"word":"关富雷","pinyin":"guan'fu'lei"},{"word":"灌江砂后加热弯形","pinyin":"guan'jiang'sha'hou'jia're'wan'xing"},{"word":"贯流式","pinyin":"guan'liu'shi"},{"word":"贯流式水轮机","pinyin":"guan'liu'shi'shui'lun'ji"},{"word":"管形座","pinyin":"guan'xing'zuo"},{"word":"管形座内壳","pinyin":"guan'xing'zuo'nei'ke"},{"word":"观音岩","pinyin":"guan'yin'yan"},{"word":"滚板机","pinyin":"gun'ban'ji"},{"word":"滚压成形","pinyin":"gun'ya'cheng'xing"},{"word":"过渡过程","pinyin":"guo'du'guo'cheng"},{"word":"过流面","pinyin":"guo'liu'mian"},{"word":"过流面积","pinyin":"guo'liu'mian'ji"},{"word":"焊缝","pinyin":"han'feng"},{"word":"焊缝搭焊点","pinyin":"han'feng'da'han'dian"},{"word":"焊剂","pinyin":"han'ji"},{"word":"焊机","pinyin":"han'ji"},{"word":"焊角尺寸","pinyin":"han'jiao'chi'cun"},{"word":"焊接工艺规范","pinyin":"han'jie'gong'yi'gui'fan"},{"word":"焊接工艺规范参照","pinyin":"han'jie'gong'yi'gui'fan'can'zhao"},{"word":"焊接规范","pinyin":"han'jie'gui'fan"},{"word":"焊接滚轮架","pinyin":"han'jie'gun'lun'jia"},{"word":"焊接结构","pinyin":"han'jie'jie'gou"},{"word":"焊接结构自由公差标准","pinyin":"han'jie'jie'gou'zi'you'gong'cha'biao'zhun"},{"word":"焊接面","pinyin":"han'jie'mian"},{"word":"焊接顺序","pinyin":"han'jie'shun'xu"},{"word":"焊接位置","pinyin":"han'jie'wei'zhi"},{"word":"焊瘤","pinyin":"han'liu"},{"word":"焊前预热","pinyin":"han'qian'yu're"},{"word":"焊丝","pinyin":"han'si"},{"word":"焊态","pinyin":"han'tai"},{"word":"焊透","pinyin":"han'tou"},{"word":"焊至图纸尺寸","pinyin":"han'zhi'tu'zhi'chi'cun"},{"word":"合缝错牙","pinyin":"he'feng'cuo'ya"},{"word":"合缝面","pinyin":"he'feng'mian"},{"word":"合缝面法兰","pinyin":"he'feng'mian'fa'lan"},{"word":"合格后转加工","pinyin":"he'ge'hou'zhuan'jia'gong"},{"word":"盒型筋","pinyin":"he'xing'jin"},{"word":"横焊","pinyin":"heng'han"},{"word":"洪都拉斯","pinyin":"hong'du'la'si"},{"word":"后焊法","pinyin":"hou'han'fa"},{"word":"蝴蝶阀","pinyin":"hu'die'fa"},{"word":"弧焊电极","pinyin":"hu'han'dian'ji"},{"word":"弧伤","pinyin":"hu'shang"},{"word":"划通风孔位置线","pinyin":"hua'tong'feng'kong'wei'zhi'xian"},{"word":"划线割掉成型余量","pinyin":"hua'xian'ge'diao'cheng'xing'yu'liang"},{"word":"环板","pinyin":"huan'ban"},{"word":"环板半径","pinyin":"huan'ban'ban'jing"},{"word":"环缝","pinyin":"huan'feng"},{"word":"环焊缝","pinyin":"huan'han'feng"},{"word":"环筋","pinyin":"huan'jin"},{"word":"环境压力","pinyin":"huan'jing'ya'li"},{"word":"换算的空蚀保证量","pinyin":"huan'suan'de'kong'shi'bao'zheng'liang"},{"word":"回送导叶","pinyin":"hui'song'dao'ye"},{"word":"回送环","pinyin":"hui'song'huan"},{"word":"混合气体保护焊","pinyin":"hun'he'qi'ti'bao'hu'han"},{"word":"混流式","pinyin":"hun'liu'shi"},{"word":"混流式水轮机","pinyin":"hun'liu'shi'shui'lun'ji"},{"word":"混流式蓄能泵","pinyin":"hun'liu'shi'xu'neng'beng"},{"word":"混流式转轮公称直径","pinyin":"hun'liu'shi'zhuan'lun'gong'cheng'zhi'jing"},{"word":"活动导叶","pinyin":"huo'dong'dao'ye"},{"word":"活性焊剂","pinyin":"huo'xing'han'ji"},{"word":"基础环","pinyin":"ji'chu'huan"},{"word":"机动焊","pinyin":"ji'dong'han"},{"word":"积分平均效率","pinyin":"ji'fen'ping'jun'xiao'lv"},{"word":"机壳","pinyin":"ji'ke"},{"word":"机壳盖","pinyin":"ji'ke'gai"},{"word":"机坑","pinyin":"ji'keng"},{"word":"机坑里衬","pinyin":"ji'keng'li'chen"},{"word":"基准运行时间","pinyin":"ji'zhun'yun'xing'shi'jian"},{"word":"机组","pinyin":"ji'zu"},{"word":"加强筋板","pinyin":"jia'qiang'jin'ban"},{"word":"加强圈","pinyin":"jia'qiang'quan"},{"word":"加权平均水头","pinyin":"jia'quan'ping'jun'shui'tou"},{"word":"加权平均效率","pinyin":"jia'quan'ping'jun'xiao'lv"},{"word":"贾瑞燕","pinyin":"jia'rui'yan"},{"word":"夹渣","pinyin":"jia'zha"},{"word":"检查涂漆质量","pinyin":"jian'cha'tu'qi'zhi'liang"},{"word":"检查样板","pinyin":"jian'cha'yang'ban"},{"word":"检查样板架","pinyin":"jian'cha'yang'ban'jia"},{"word":"剪床","pinyin":"jian'chuang"},{"word":"剪断销","pinyin":"jian'duan'xiao"},{"word":"检修密封","pinyin":"jian'xiu'mi'feng"},{"word":"检修平台","pinyin":"jian'xiu'ping'tai"},{"word":"江砂","pinyin":"jiang'sha"},{"word":"江砂使用前烘干","pinyin":"jiang'sha'shi'yong'qian'hong'gan"},{"word":"角钢","pinyin":"jiao'gang"},{"word":"角焊缝","pinyin":"jiao'han'feng"},{"word":"角接接头","pinyin":"jiao'jie'jie'tou"},{"word":"角向","pinyin":"jiao'xiang"},{"word":"角向砂轮机","pinyin":"jiao'xiang'sha'lun'ji"},{"word":"结构部件","pinyin":"jie'gou'bu'jian"},{"word":"接合","pinyin":"jie'he"},{"word":"解体","pinyin":"jie'ti"},{"word":"接头","pinyin":"jie'tou"},{"word":"接头熔深","pinyin":"jie'tou'rong'shen"},{"word":"节圆直径","pinyin":"jie'yuan'zhi'jing"},{"word":"进出水室","pinyin":"jin'chu'shui'shi"},{"word":"进口角度","pinyin":"jin'kou'jiao'du"},{"word":"进口流道","pinyin":"jin'kou'liu'dao"},{"word":"锦屏","pinyin":"jin'ping"},{"word":"金属极","pinyin":"jin'shu'ji"},{"word":"金属芯焊丝","pinyin":"jin'shu'xin'han'si"},{"word":"进水阀门公称直径","pinyin":"jin'shui'fa'men'gong'cheng'zhi'jing"},{"word":"进水阀门基本技术条件","pinyin":"jin'shui'fa'men'ji'ben'ji'shu'tiao'jian"},{"word":"净水头","pinyin":"jing'shui'tou"},{"word":"径向力","pinyin":"jing'xiang'li"},{"word":"井字梁","pinyin":"jing'zi'liang"},{"word":"锯床","pinyin":"ju'chuang"},{"word":"绝对压力","pinyin":"jue'dui'ya'li"},{"word":"均压管","pinyin":"jun'ya'guan"},{"word":"卡基娃","pinyin":"ka'ji'wa"},{"word":"卡里巴","pinyin":"ka'li'ba"},{"word":"开口","pinyin":"kai'kou"},{"word":"看线","pinyin":"kan'xian"},{"word":"抗磨板","pinyin":"kang'mo'ban"},{"word":"可更换导叶","pinyin":"ke'geng'huan'dao'ye"},{"word":"科卡科多辛克雷","pinyin":"ke'ka'ke'duo'xin'ke'lei"},{"word":"可逆式水轮机","pinyin":"ke'ni'shi'shui'lun'ji"},{"word":"可调式水利机械","pinyin":"ke'tiao'shi'shui'li'ji'xie"},{"word":"空化","pinyin":"kong'hua"},{"word":"空化和空蚀","pinyin":"kong'hua'he'kong'shi"},{"word":"空化试验","pinyin":"kong'hua'shi'yan"},{"word":"空化裕量","pinyin":"kong'hua'yu'liang"},{"word":"空蚀","pinyin":"kong'shi"},{"word":"空蚀保证量","pinyin":"kong'shi'bao'zheng'liang"},{"word":"空蚀保证期","pinyin":"kong'shi'bao'zheng'qi"},{"word":"空蚀量","pinyin":"kong'shi'liang"},{"word":"空蚀面积","pinyin":"kong'shi'mian'ji"},{"word":"空蚀面积保证系数","pinyin":"kong'shi'mian'ji'bao'zheng'xi'shu"},{"word":"空蚀深度","pinyin":"kong'shi'shen'du"},{"word":"空蚀深度保证系数","pinyin":"kong'shi'shen'du'bao'zheng'xi'shu"},{"word":"空蚀体积","pinyin":"kong'shi'ti'ji"},{"word":"空蚀质量","pinyin":"kong'shi'zhi'liang"},{"word":"空蚀质量保证系数","pinyin":"kong'shi'zhi'liang'bao'zheng'xi'shu"},{"word":"空载工况","pinyin":"kong'zai'gong'kuang"},{"word":"控制环","pinyin":"kong'zhi'huan"},{"word":"控制设备事业部","pinyin":"kong'zhi'she'bei'shi'ye'bu"},{"word":"空中翻身","pinyin":"kong'zhong'fan'shen"},{"word":"扩散管","pinyin":"kuo'san'guan"},{"word":"扩散环","pinyin":"kuo'san'huan"},{"word":"扩散室","pinyin":"kuo'san'shi"},{"word":"廊道","pinyin":"lang'dao"},{"word":"乐昌峡","pinyin":"le'chang'xia"},{"word":"肋板","pinyin":"lei'ban"},{"word":"类型","pinyin":"lei'xing"},{"word":"冷作","pinyin":"leng'zuo"},{"word":"立焊","pinyin":"li'han"},{"word":"立焊缝","pinyin":"li'han'feng"},{"word":"立筋","pinyin":"li'jin"},{"word":"立圈","pinyin":"li'quan"},{"word":"李荣生","pinyin":"li'rong'sheng"},{"word":"立式机组","pinyin":"li'shi'ji'zu"},{"word":"力特性","pinyin":"li'te'xing"},{"word":"力特性试验","pinyin":"li'te'xing'shi'yan"},{"word":"溧阳","pinyin":"li'yang"},{"word":"联动机构","pinyin":"lian'dong'ji'gou"},{"word":"连杆","pinyin":"lian'gan"},{"word":"连接板","pinyin":"lian'jie'ban"},{"word":"联轴螺钉","pinyin":"lian'zhou'luo'ding"},{"word":"联轴螺栓","pinyin":"lian'zhou'luo'shuan"},{"word":"两瓣","pinyin":"liang'ban"},{"word":"梁旭阳","pinyin":"liang'xu'yang"},{"word":"裂纹","pinyin":"lie'wen"},{"word":"临界空化系数","pinyin":"lin'jie'kong'hua'xi'shu"},{"word":"临界气蚀系数","pinyin":"lin'jie'qi'shi'xi'shu"},{"word":"林磊","pinyin":"lin'lei"},{"word":"流道参数","pinyin":"liu'dao'can'shu"},{"word":"流量","pinyin":"liu'liang"},{"word":"柳树沟","pinyin":"liu'shu'gou"},{"word":"刘玉兰","pinyin":"liu'yu'lan"},{"word":"龙开口","pinyin":"long'kai'kou"},{"word":"卢昌福","pinyin":"lu'chang'fu"},{"word":"轮毂","pinyin":"lun'gu"},{"word":"轮盘","pinyin":"lun'pan"},{"word":"轮叶","pinyin":"lun'ye"},{"word":"裸电极","pinyin":"luo'dian'ji"},{"word":"螺孔","pinyin":"luo'kong"},{"word":"螺纹孔","pinyin":"luo'wen'kong"},{"word":"螺旋拉紧器","pinyin":"luo'xuan'la'jin'qi"},{"word":"吕胜海","pinyin":"lv'sheng'hai"},{"word":"马里费鲁","pinyin":"ma'li'fei'lu"},{"word":"马丘比丘","pinyin":"ma'qiu'bi'qiu"},{"word":"脉冲焊","pinyin":"mai'chong'han"},{"word":"埋弧焊","pinyin":"mai'hu'han"},{"word":"埋弧焊机","pinyin":"mai'hu'han'ji"},{"word":"埋入部件","pinyin":"mai'ru'bu'jian"},{"word":"毛水头","pinyin":"mao'shui'tou"},{"word":"米尺","pinyin":"mi'chi"},{"word":"名称","pinyin":"ming'cheng"},{"word":"名义尺寸","pinyin":"ming'yi'chi'cun"},{"word":"摩擦焊","pinyin":"mo'ca'han"},{"word":"摩擦装置","pinyin":"mo'ca'zhuang'zhi"},{"word":"磨蚀","pinyin":"mo'shi"},{"word":"磨损","pinyin":"mo'sun"},{"word":"模型","pinyin":"mo'xing"},{"word":"模型机","pinyin":"mo'xing'ji"},{"word":"模型试验","pinyin":"mo'xing'shi'yan"},{"word":"模型验收试验","pinyin":"mo'xing'yan'shou'shi'yan"},{"word":"模型验收试验规程","pinyin":"mo'xing'yan'shou'shi'yan'gui'cheng"},{"word":"母材","pinyin":"mu'cai"},{"word":"沐若","pinyin":"mu'ruo"},{"word":"沐若生态小机","pinyin":"mu'ruo'sheng'tai'xiao'ji"},{"word":"耐压试验","pinyin":"nai'ya'shi'yan"},{"word":"内导环","pinyin":"nei'dao'huan"},{"word":"内导水环","pinyin":"nei'dao'shui'huan"},{"word":"内顶盖","pinyin":"nei'ding'gai"},{"word":"内径千分尺","pinyin":"nei'jing'qian'fen'chi"},{"word":"内配水环","pinyin":"nei'pei'shui'huan"},{"word":"内圆","pinyin":"nei'yuan"},{"word":"内藏式喷针接力器","pinyin":"nei'zang'shi'pen'zhen'jie'li'qi"},{"word":"内罩","pinyin":"nei'zhao"},{"word":"糯扎渡","pinyin":"nuo'zha'du"},{"word":"爬焊","pinyin":"pa'han"},{"word":"排出高度","pinyin":"pai'chu'gao'du"},{"word":"排水管","pinyin":"pai'shui'guan"},{"word":"盘形阀","pinyin":"pan'xing'fa"},{"word":"旁通阀","pinyin":"pang'tong'fa"},{"word":"泡头","pinyin":"pao'tou"},{"word":"泡头球壁","pinyin":"pao'tou'qiu'bi"},{"word":"泡头球壁压模","pinyin":"pao'tou'qiu'bi'ya'mu"},{"word":"配割","pinyin":"pei'ge"},{"word":"配割余量","pinyin":"pei'ge'yu'liang"},{"word":"喷丸室","pinyin":"pen'wan'shi"},{"word":"喷针","pinyin":"pen'zhen"},{"word":"喷针杆","pinyin":"pen'zhen'gan"},{"word":"喷针接力器","pinyin":"pen'zhen'jie'li'qi"},{"word":"喷针头","pinyin":"pen'zhen'tou"},{"word":"喷针折向器反馈器","pinyin":"pen'zhen'zhe'xiang'qi'fan'kui'qi"},{"word":"喷嘴","pinyin":"pen'zui"},{"word":"喷嘴口","pinyin":"pen'zui'kou"},{"word":"喷嘴体","pinyin":"pen'zui'ti"},{"word":"喷嘴罩","pinyin":"pen'zui'zhao"},{"word":"喷嘴支管","pinyin":"pen'zui'zhi'guan"},{"word":"喷嘴装配","pinyin":"pen'zui'zhuang'pei"},{"word":"偏流器","pinyin":"pian'liu'qi"},{"word":"拼焊缝","pinyin":"pin'han'feng"},{"word":"拼焊坡口朝上","pinyin":"pin'han'po'kou'chao'shang"},{"word":"频率","pinyin":"pin'lv"},{"word":"平板蝶阀","pinyin":"ping'ban'die'fa"},{"word":"平焊","pinyin":"ping'han"},{"word":"平均流速","pinyin":"ping'jun'liu'su"},{"word":"平行度","pinyin":"ping'xing'du"},{"word":"坡口","pinyin":"po'kou"},{"word":"坡口焊缝","pinyin":"po'kou'han'feng"},{"word":"坡口线","pinyin":"po'kou'xian"},{"word":"起吊管","pinyin":"qi'diao'guan"},{"word":"汽发","pinyin":"qi'fa"},{"word":"气割面","pinyin":"qi'ge'mian"},{"word":"气割枪","pinyin":"qi'ge'qiang"},{"word":"汽化压力","pinyin":"qi'hua'ya'li"},{"word":"气蚀","pinyin":"qi'shi"},{"word":"气蚀磨损","pinyin":"qi'shi'mo'sun"},{"word":"气蚀损坏","pinyin":"qi'shi'sun'huai"},{"word":"其它部件","pinyin":"qi'ta'bu'jian"},{"word":"气体垫","pinyin":"qi'ti'dian"},{"word":"千斤顶","pinyin":"qian'jin'ding"},{"word":"铅坠","pinyin":"qian'zhui"},{"word":"乔宏来","pinyin":"qiao'hong'lai"},{"word":"切割机辅助工具","pinyin":"qie'ge'ji'fu'zhu'gong'ju"},{"word":"秦坤涛","pinyin":"qin'kun'tao"},{"word":"清根","pinyin":"qing'gen"},{"word":"清理","pinyin":"qing'li"},{"word":"清理修整部分及割渣","pinyin":"qing'li'xiu'zheng'bu'fen'ji'ge'zha"},{"word":"球阀","pinyin":"qiu'fa"},{"word":"球缺形壁","pinyin":"qiu'que'xing'bi"},{"word":"全贯流式水轮机","pinyin":"quan'guan'liu'shi'shui'lun'ji"},{"word":"缺陷","pinyin":"que'xian"},{"word":"燃料气体","pinyin":"ran'liao'qi'ti"},{"word":"热滚校圆","pinyin":"re'gun'xiao'yuan"},{"word":"热影响区","pinyin":"re'ying'xiang'qu"},{"word":"熔滴过渡","pinyin":"rong'di'guo'du"},{"word":"熔合","pinyin":"rong'he"},{"word":"熔合线","pinyin":"rong'he'xian"},{"word":"熔化极气体保护焊","pinyin":"rong'hua'ji'qi'ti'bao'hu'han"},{"word":"熔化喷焊","pinyin":"rong'hua'pen'han"},{"word":"熔化性填塞","pinyin":"rong'hua'xing'tian'sai"},{"word":"熔宽","pinyin":"rong'kuan"},{"word":"熔深","pinyin":"rong'shen"},{"word":"熔嘴电渣焊","pinyin":"rong'zui'dian'zha'han"},{"word":"砂轮机","pinyin":"sha'lun'ji"},{"word":"砂轮机打磨光滑","pinyin":"sha'lun'ji'da'mo'guang'hua"},{"word":"筛紧","pinyin":"shai'jin"},{"word":"扇形球壁","pinyin":"shan'xing'qiu'bi"},{"word":"上阿特巴拉","pinyin":"shang'a'te'ba'la"},{"word":"上齿压板","pinyin":"shang'chi'ya'ban"},{"word":"上齿压板装焊胎具","pinyin":"shang'chi'ya'ban'zhuang'han'tai'ju"},{"word":"上导轴承","pinyin":"shang'dao'zhou'cheng"},{"word":"上导轴承座","pinyin":"shang'dao'zhou'cheng'zuo"},{"word":"上冠","pinyin":"shang'guan"},{"word":"上环板","pinyin":"shang'huan'ban"},{"word":"上机架","pinyin":"shang'ji'jia"},{"word":"上机壳","pinyin":"shang'ji'ke"},{"word":"上筋板","pinyin":"shang'jin'ban"},{"word":"上下环板","pinyin":"shang'xia'huan'ban"},{"word":"上翼板","pinyin":"shang'yi'ban"},{"word":"上圆板","pinyin":"shang'yuan'ban"},{"word":"舌板","pinyin":"she'ban"},{"word":"设计比转速","pinyin":"she'ji'bi'zhuan'su"},{"word":"设计部","pinyin":"she'ji'bu"},{"word":"设计洪水位","pinyin":"she'ji'hong'shui'wei"},{"word":"设计名义尺寸","pinyin":"she'ji'ming'yi'chi'cun"},{"word":"设计水头","pinyin":"she'ji'shui'tou"},{"word":"设计尾水位","pinyin":"she'ji'wei'shui'wei"},{"word":"射流入射角","pinyin":"she'liu'ru'she'jiao"},{"word":"射流椭圆","pinyin":"she'liu'tuo'yuan"},{"word":"射流直径","pinyin":"she'liu'zhi'jing"},{"word":"射流直径比","pinyin":"she'liu'zhi'jing'bi"},{"word":"施焊","pinyin":"shi'han"},{"word":"实际尺寸","pinyin":"shi'ji'chi'cun"},{"word":"实际运行时间","pinyin":"shi'ji'yun'xing'shi'jian"},{"word":"试件","pinyin":"shi'jian"},{"word":"石棉绳","pinyin":"shi'mian'sheng"},{"word":"实体","pinyin":"shi'ti"},{"word":"试验方面","pinyin":"shi'yan'fang'mian"},{"word":"试验类型","pinyin":"shi'yan'lei'xing"},{"word":"十字型","pinyin":"shi'zi'xing"},{"word":"手工焊","pinyin":"shou'gong'han"},{"word":"手工开坡口","pinyin":"shou'gong'kai'po'kou"},{"word":"手拉葫芦","pinyin":"shou'la'hu'lu"},{"word":"受油器","pinyin":"shou'you'qi"},{"word":"竖筋","pinyin":"shu'jin"},{"word":"竖井贯流式水轮机","pinyin":"shu'jing'guan'liu'shi'shui'lun'ji"},{"word":"竖井头","pinyin":"shu'jing'tou"},{"word":"数控气割机","pinyin":"shu'kong'qi'ge'ji"},{"word":"数控气割下料","pinyin":"shu'kong'qi'ge'xia'liao"},{"word":"甩负荷试验","pinyin":"shuai'fu'he'shi'yan"},{"word":"双幅板转子支架","pinyin":"shuang'fu'ban'zhuan'zi'zhi'jia"},{"word":"双击式水轮机","pinyin":"shuang'ji'shi'shui'lun'ji"},{"word":"双面焊搭接接头","pinyin":"shuang'mian'han'da'jie'jie'tou"},{"word":"双面焊对接接头","pinyin":"shuang'mian'han'dui'jie'jie'tou"},{"word":"水泵水轮机","pinyin":"shui'beng'shui'lun'ji"},{"word":"水泵水轮机全特性","pinyin":"shui'beng'shui'lun'ji'quan'te'xing"},{"word":"水锤","pinyin":"shui'chui"},{"word":"水的重度","pinyin":"shui'de'zhong'du"},{"word":"水电","pinyin":"shui'dian"},{"word":"水电加工","pinyin":"shui'dian'jia'gong"},{"word":"水斗","pinyin":"shui'dou"},{"word":"水斗式水轮机","pinyin":"shui'dou'shi'shui'lun'ji"},{"word":"水利机械","pinyin":"shui'li'ji'xie"},{"word":"水轮机","pinyin":"shui'lun'ji"},{"word":"水轮机比转速","pinyin":"shui'lun'ji'bi'zhuan'su"},{"word":"水轮机出口测量断面","pinyin":"shui'lun'ji'chu'kou'ce'liang'duan'mian"},{"word":"水轮机出口面积","pinyin":"shui'lun'ji'chu'kou'mian'ji"},{"word":"水轮机出口压强","pinyin":"shui'lun'ji'chu'kou'ya'qiang"},{"word":"水轮机的比转速","pinyin":"shui'lun'ji'de'bi'zhuan'su"},{"word":"水轮机额定输出功率","pinyin":"shui'lun'ji'e'ding'shu'chu'gong'lv"},{"word":"水轮机飞逸转速","pinyin":"shui'lun'ji'fei'yi'zhuan'su"},{"word":"水轮机功率","pinyin":"shui'lun'ji'gong'lv"},{"word":"水轮机功率试验","pinyin":"shui'lun'ji'gong'lv'shi'yan"},{"word":"水轮机基本技术条件","pinyin":"shui'lun'ji'ji'ben'ji'shu'tiao'jian"},{"word":"水轮机技术保证","pinyin":"shui'lun'ji'ji'shu'bao'zheng"},{"word":"水轮机机械效率","pinyin":"shui'lun'ji'ji'xie'xiao'lv"},{"word":"水轮机加权平均效率","pinyin":"shui'lun'ji'jia'quan'ping'jun'xiao'lv"},{"word":"水轮机进口测量断面","pinyin":"shui'lun'ji'jin'kou'ce'liang'duan'mian"},{"word":"水轮机进口面积","pinyin":"shui'lun'ji'jin'kou'mian'ji"},{"word":"水轮机进口压强","pinyin":"shui'lun'ji'jin'kou'ya'qiang"},{"word":"水轮机空化系数","pinyin":"shui'lun'ji'kong'hua'xi'shu"},{"word":"水轮机空载流量","pinyin":"shui'lun'ji'kong'zai'liu'liang"},{"word":"水轮机流量","pinyin":"shui'lun'ji'liu'liang"},{"word":"水轮机试验","pinyin":"shui'lun'ji'shi'yan"},{"word":"水轮机输出功率","pinyin":"shui'lun'ji'shu'chu'gong'lv"},{"word":"水轮机输入功率","pinyin":"shui'lun'ji'shu'ru'gong'lv"},{"word":"水轮机水力效率","pinyin":"shui'lun'ji'shui'li'xiao'lv"},{"word":"水轮机水头","pinyin":"shui'lun'ji'shui'tou"},{"word":"水轮机效率","pinyin":"shui'lun'ji'xiao'lv"},{"word":"水轮机正常运行区","pinyin":"shui'lun'ji'zheng'chang'yun'xing'qu"},{"word":"水轮机转轮公称直径","pinyin":"shui'lun'ji'zhuan'lun'gong'cheng'zhi'jing"},{"word":"水轮机转速","pinyin":"shui'lun'ji'zhuan'su"},{"word":"水轮机最大瞬态压力","pinyin":"shui'lun'ji'zui'da'shun'tai'ya'li"},{"word":"水轮机最大瞬态转速","pinyin":"shui'lun'ji'zui'da'shun'tai'zhuan'su"},{"word":"水头","pinyin":"shui'tou"},{"word":"水推力","pinyin":"shui'tui'li"},{"word":"水位","pinyin":"shui'wei"},{"word":"水准仪","pinyin":"shui'zhun'yi"},{"word":"瞬态压力变化率","pinyin":"shun'tai'ya'li'bian'hua'lv"},{"word":"瞬态转速变化率","pinyin":"shun'tai'zhuan'su'bian'hua'lv"},{"word":"死水位","pinyin":"si'shui'wei"},{"word":"速度比能","pinyin":"su'du'bi'neng"},{"word":"速度水头","pinyin":"su'du'shui'tou"},{"word":"胎具","pinyin":"tai'ju"},{"word":"碳电极","pinyin":"tan'dian'ji"},{"word":"碳弧气刨机","pinyin":"tan'hu'qi'bao'ji"},{"word":"探伤","pinyin":"tan'shang"},{"word":"套材","pinyin":"tao'cai"},{"word":"陶瓷衬垫","pinyin":"tao'ci'chen'dian"},{"word":"套料","pinyin":"tao'liao"},{"word":"特性曲线","pinyin":"te'xing'qu'xian"},{"word":"特性试验","pinyin":"te'xing'shi'yan"},{"word":"填充金属","pinyin":"tian'chong'jin'shu"},{"word":"调节保证","pinyin":"tiao'jie'bao'zheng"},{"word":"调节装置","pinyin":"tiao'jie'zhuang'zhi"},{"word":"调平","pinyin":"tiao'ping"},{"word":"调速轴","pinyin":"tiao'su'zhou"},{"word":"铁素体数值","pinyin":"tie'su'ti'shu'zhi"},{"word":"铁丸","pinyin":"tie'wan"},{"word":"通风孔","pinyin":"tong'feng'kong"},{"word":"通风孔位置线","pinyin":"tong'feng'kong'wei'zhi'xian"},{"word":"通流部件技术条件","pinyin":"tong'liu'bu'jian'ji'shu'tiao'jian"},{"word":"投影线","pinyin":"tou'ying'xian"},{"word":"凸凹缺陷","pinyin":"tu'ao'que'xian"},{"word":"涂料焊条","pinyin":"tu'liao'han'tiao"},{"word":"涂漆","pinyin":"tu'qi"},{"word":"退火","pinyin":"tui'huo"},{"word":"退火炉","pinyin":"tui'huo'lu"},{"word":"推拉杆","pinyin":"tui'la'gan"},{"word":"托口","pinyin":"tuo'kou"},{"word":"椭圆筒","pinyin":"tuo'yuan'tong"},{"word":"外壁","pinyin":"wai'bi"},{"word":"外导环","pinyin":"wai'dao'huan"},{"word":"外导水环","pinyin":"wai'dao'shui'huan"},{"word":"外径千分尺","pinyin":"wai'jing'qian'fen'chi"},{"word":"外壳","pinyin":"wai'ke"},{"word":"外伸式喷针接力器","pinyin":"wai'shen'shi'pen'zhen'jie'li'qi"},{"word":"完全熔合","pinyin":"wan'quan'rong'he"},{"word":"王江","pinyin":"wang'jiang"},{"word":"围板","pinyin":"wei'ban"},{"word":"魏方锴","pinyin":"wei'fang'kai"},{"word":"未焊透","pinyin":"wei'han'tou"},{"word":"未熔合","pinyin":"wei'rong'he"},{"word":"尾水管","pinyin":"wei'shui'guan"},{"word":"尾水管补气系统","pinyin":"wei'shui'guan'bu'qi'xi'tong"},{"word":"尾水管补气装置","pinyin":"wei'shui'guan'bu'qi'zhuang'zhi"},{"word":"尾水管进口段","pinyin":"wei'shui'guan'jin'kou'duan"},{"word":"尾水管扩散段","pinyin":"wei'shui'guan'kuo'san'duan"},{"word":"尾水管廊道","pinyin":"wei'shui'guan'lang'dao"},{"word":"尾水管里衬","pinyin":"wei'shui'guan'li'chen"},{"word":"尾水管弯管","pinyin":"wei'shui'guan'wan'guan"},{"word":"尾水管支墩","pinyin":"wei'shui'guan'zhi'dun"},{"word":"尾水管支墩里衬","pinyin":"wei'shui'guan'zhi'dun'li'chen"},{"word":"尾水管肘管","pinyin":"wei'shui'guan'zhou'guan"},{"word":"尾水管锥管","pinyin":"wei'shui'guan'zhui'guan"},{"word":"尾水廊道","pinyin":"wei'shui'lang'dao"},{"word":"位置比能","pinyin":"wei'zhi'bi'neng"},{"word":"位置水头","pinyin":"wei'zhi'shui'tou"},{"word":"位置线","pinyin":"wei'zhi'xian"},{"word":"温控柜","pinyin":"wen'kong'gui"},{"word":"蜗壳","pinyin":"wo'ke"},{"word":"蜗壳包角","pinyin":"wo'ke'bao'jiao"},{"word":"蜗壳鼻端","pinyin":"wo'ke'bi'duan"},{"word":"蜗室","pinyin":"wo'shi"},{"word":"钨极","pinyin":"wu'ji"},{"word":"钨极气体保护焊","pinyin":"wu'ji'qi'ti'bao'hu'han"},{"word":"吸出高度","pinyin":"xi'chu'gao'du"},{"word":"溪洛渡","pinyin":"xi'luo'du"},{"word":"吸入高度","pinyin":"xi'ru'gao'du"},{"word":"吸水管","pinyin":"xi'shui'guan"},{"word":"吸水管进口段","pinyin":"xi'shui'guan'jin'kou'duan"},{"word":"吸水管扩散段","pinyin":"xi'shui'guan'kuo'san'duan"},{"word":"吸水管里衬","pinyin":"xi'shui'guan'li'chen"},{"word":"吸水管弯管","pinyin":"xi'shui'guan'wan'guan"},{"word":"吸水管支墩","pinyin":"xi'shui'guan'zhi'dun"},{"word":"吸水管支墩里衬","pinyin":"xi'shui'guan'zhi'dun'li'chen"},{"word":"吸水管肘管","pinyin":"xi'shui'guan'zhou'guan"},{"word":"吸水管锥管","pinyin":"xi'shui'guan'zhui'guan"},{"word":"下齿压板","pinyin":"xia'chi'ya'ban"},{"word":"下齿压板装焊胎具","pinyin":"xia'chi'ya'ban'zhuang'han'tai'ju"},{"word":"下环","pinyin":"xia'huan"},{"word":"下环板","pinyin":"xia'huan'ban"},{"word":"下机架","pinyin":"xia'ji'jia"},{"word":"下机坑","pinyin":"xia'ji'keng"},{"word":"下筋板","pinyin":"xia'jin'ban"},{"word":"下序","pinyin":"xia'xu"},{"word":"下序工作","pinyin":"xia'xu'gong'zuo"},{"word":"下圆板","pinyin":"xia'yuan'ban"},{"word":"下转变温度","pinyin":"xia'zhuan'bian'wen'du"},{"word":"弦距","pinyin":"xian'ju"},{"word":"线圈","pinyin":"xian'quan"},{"word":"相对效率","pinyin":"xiang'dui'xiao'lv"},{"word":"相贯线","pinyin":"xiang'guan'xian"},{"word":"向家坝左岸","pinyin":"xiang'jia'ba'zuo'an"},{"word":"响水涧","pinyin":"xiang'shui'jian"},{"word":"相似工况","pinyin":"xiang'si'gong'kuang"},{"word":"小孔焊接术","pinyin":"xiao'kong'han'jie'shu"},{"word":"效率","pinyin":"xiao'lv"},{"word":"效率试验","pinyin":"xiao'lv'shi'yan"},{"word":"消泡箱","pinyin":"xiao'pao'xiang"},{"word":"校圆","pinyin":"xiao'yuan"},{"word":"校直","pinyin":"xiao'zhi"},{"word":"斜击式水轮机","pinyin":"xie'ji'shi'shui'lun'ji"},{"word":"协联工况","pinyin":"xie'lian'gong'kuang"},{"word":"协联装置","pinyin":"xie'lian'zhuang'zhi"},{"word":"斜流定桨式水轮机","pinyin":"xie'liu'ding'jiang'shi'shui'lun'ji"},{"word":"斜流式水轮机","pinyin":"xie'liu'shi'shui'lun'ji"},{"word":"斜流式蓄能泵","pinyin":"xie'liu'shi'xu'neng'beng"},{"word":"斜流转桨式水轮机","pinyin":"xie'liu'zhuan'jiang'shi'shui'lun'ji"},{"word":"泄水锥","pinyin":"xie'shui'zhui"},{"word":"性能参数","pinyin":"xing'neng'can'shu"},{"word":"性能试验","pinyin":"xing'neng'shi'yan"},{"word":"型线偏差","pinyin":"xing'xian'pian'cha"},{"word":"修割","pinyin":"xiu'ge"},{"word":"修整部分","pinyin":"xiu'zheng'bu'fen"},{"word":"修整切割过程","pinyin":"xiu'zheng'qie'ge'guo'cheng"},{"word":"蓄能泵","pinyin":"xu'neng'beng"},{"word":"蓄能泵出口测量断面","pinyin":"xu'neng'beng'chu'kou'ce'liang'duan'mian"},{"word":"蓄能泵的流量比转速","pinyin":"xu'neng'beng'de'liu'liang'bi'zhuan'su"},{"word":"蓄能泵的输出功率","pinyin":"xu'neng'beng'de'shu'chu'gong'lv"},{"word":"蓄能泵的输入功率","pinyin":"xu'neng'beng'de'shu'ru'gong'lv"},{"word":"蓄能泵反向飞逸转速","pinyin":"xu'neng'beng'fan'xiang'fei'yi'zhuan'su"},{"word":"蓄能泵机械效率","pinyin":"xu'neng'beng'ji'xie'xiao'lv"},{"word":"蓄能泵进口测量断面","pinyin":"xu'neng'beng'jin'kou'ce'liang'duan'mian"},{"word":"蓄能泵净吸上扬程","pinyin":"xu'neng'beng'jing'xi'shang'yang'cheng"},{"word":"蓄能泵空化系数","pinyin":"xu'neng'beng'kong'hua'xi'shu"},{"word":"蓄能泵空化余量","pinyin":"xu'neng'beng'kong'hua'yu'liang"},{"word":"蓄能泵零流量功率","pinyin":"xu'neng'beng'ling'liu'liang'gong'lv"},{"word":"蓄能泵零流量扬程","pinyin":"xu'neng'beng'ling'liu'liang'yang'cheng"},{"word":"蓄能泵流量","pinyin":"xu'neng'beng'liu'liang"},{"word":"蓄能泵水力效率","pinyin":"xu'neng'beng'shui'li'xiao'lv"},{"word":"蓄能泵吸入扬程损失","pinyin":"xu'neng'beng'xi'ru'yang'cheng'sun'shi"},{"word":"蓄能泵扬程","pinyin":"xu'neng'beng'yang'cheng"},{"word":"蓄能泵最大流量","pinyin":"xu'neng'beng'zui'da'liu'liang"},{"word":"蓄能泵最大输入功率","pinyin":"xu'neng'beng'zui'da'shu'ru'gong'lv"},{"word":"蓄能泵最大扬程","pinyin":"xu'neng'beng'zui'da'yang'cheng"},{"word":"蓄能泵最小输入功率","pinyin":"xu'neng'beng'zui'xiao'shu'ru'gong'lv"},{"word":"旋转方向","pinyin":"xuan'zhuan'fang'xiang"},{"word":"氩弧焊","pinyin":"ya'hu'han"},{"word":"压力","pinyin":"ya'li"},{"word":"压力比能","pinyin":"ya'li'bi'neng"},{"word":"压力钢管","pinyin":"ya'li'gang'guan"},{"word":"压力脉动","pinyin":"ya'li'mai'dong"},{"word":"压力脉动试验","pinyin":"ya'li'mai'dong'shi'yan"},{"word":"压力水头","pinyin":"ya'li'shui'tou"},{"word":"压平","pinyin":"ya'ping"},{"word":"压强","pinyin":"ya'qiang"},{"word":"压胎","pinyin":"ya'tai"},{"word":"闫海滨","pinyin":"yan'hai'bin"},{"word":"阎海滨","pinyin":"yan'hai'bin"},{"word":"研究所","pinyin":"yan'jiu'suo"},{"word":"验收试验","pinyin":"yan'shou'shi'yan"},{"word":"岩滩扩机","pinyin":"yan'tan'kuo'ji"},{"word":"样冲","pinyin":"yang'chong"},{"word":"样冲打上标记","pinyin":"yang'chong'da'shang'biao'ji"},{"word":"样冲眼","pinyin":"yang'chong'yan"},{"word":"仰焊","pinyin":"yang'han"},{"word":"仰焊缝","pinyin":"yang'han'feng"},{"word":"羊曲","pinyin":"yang'qu"},{"word":"氧燃料气割","pinyin":"yang'ran'liao'qi'ge"},{"word":"羊头铺","pinyin":"yang'tou'pu"},{"word":"摇臂钻床","pinyin":"yao'bi'zuan'chuang"},{"word":"咬边","pinyin":"yao'bian"},{"word":"药芯焊丝","pinyin":"yao'xin'han'si"},{"word":"药芯焊丝弧焊","pinyin":"yao'xin'han'si'hu'han"},{"word":"叶轮","pinyin":"ye'lun"},{"word":"叶轮公称直径","pinyin":"ye'lun'gong'cheng'zhi'jing"},{"word":"叶轮后盖","pinyin":"ye'lun'hou'gai"},{"word":"叶轮前盖","pinyin":"ye'lun'qian'gai"},{"word":"叶轮上冠","pinyin":"ye'lun'shang'guan"},{"word":"叶轮上冠密封","pinyin":"ye'lun'shang'guan'mi'feng"},{"word":"叶轮上冠腔","pinyin":"ye'lun'shang'guan'qiang"},{"word":"叶轮输出功率","pinyin":"ye'lun'shu'chu'gong'lv"},{"word":"叶轮输入功率","pinyin":"ye'lun'shu'ru'gong'lv"},{"word":"叶轮体","pinyin":"ye'lun'ti"},{"word":"叶轮下环","pinyin":"ye'lun'xia'huan"},{"word":"叶轮下环密封","pinyin":"ye'lun'xia'huan'mi'feng"},{"word":"叶轮下环腔","pinyin":"ye'lun'xia'huan'qiang"},{"word":"叶轮叶片","pinyin":"ye'lun'ye'pian"},{"word":"叶片","pinyin":"ye'pian"},{"word":"叶片安放角","pinyin":"ye'pian'an'fang'jiao"},{"word":"叶片背面","pinyin":"ye'pian'bei'mian"},{"word":"叶片出水边","pinyin":"ye'pian'chu'shui'bian"},{"word":"叶片接力器装配","pinyin":"ye'pian'jie'li'qi'zhuang'pei"},{"word":"叶片进水边","pinyin":"ye'pian'jin'shui'bian"},{"word":"叶片开口","pinyin":"ye'pian'kai'kou"},{"word":"叶片力特性","pinyin":"ye'pian'li'te'xing"},{"word":"叶片连杆","pinyin":"ye'pian'lian'gan"},{"word":"叶片密封","pinyin":"ye'pian'mi'feng"},{"word":"叶片倾角","pinyin":"ye'pian'qing'jiao"},{"word":"叶片枢轴","pinyin":"ye'pian'shu'zhou"},{"word":"叶片正面","pinyin":"ye'pian'zheng'mian"},{"word":"叶片转臂","pinyin":"ye'pian'zhuan'bi"},{"word":"叶片转角","pinyin":"ye'pian'zhuan'jiao"},{"word":"翼板","pinyin":"yi'ban"},{"word":"一般术语","pinyin":"yi'ban'shu'yu"},{"word":"依次分段","pinyin":"yi'ci'fen'duan"},{"word":"伊朗","pinyin":"yi'lang"},{"word":"以上工序完成后","pinyin":"yi'shang'gong'xu'wan'cheng'hou"},{"word":"溢油","pinyin":"yi'you"},{"word":"引水室","pinyin":"yin'shui'shi"},{"word":"油槽","pinyin":"you'cao"},{"word":"油槽壁","pinyin":"you'cao'bi"},{"word":"油钢管","pinyin":"you'gang'guan"},{"word":"油管路","pinyin":"you'guan'lu"},{"word":"油腔","pinyin":"you'qiang"},{"word":"油箱","pinyin":"you'xiang"},{"word":"油压机","pinyin":"you'ya'ji"},{"word":"油压千斤顶","pinyin":"you'ya'qian'jin'ding"},{"word":"余高","pinyin":"yu'gao"},{"word":"余量线","pinyin":"yu'liang'xian"},{"word":"预先放好","pinyin":"yu'xian'fang'hao"},{"word":"圆盘","pinyin":"yuan'pan"},{"word":"圆筒阀","pinyin":"yuan'tong'fa"},{"word":"圆筒筋","pinyin":"yuan'tong'jin"},{"word":"原型","pinyin":"yuan'xing"},{"word":"运行工况","pinyin":"yun'xing'gong'kuang"},{"word":"运行特性曲线","pinyin":"yun'xing'te'xing'qu'xian"},{"word":"运转特性曲线","pinyin":"yun'zhuan'te'xing'qu'xian"},{"word":"斩态过程","pinyin":"zhan'tai'guo'cheng"},{"word":"张淮","pinyin":"zhang'huai"},{"word":"张伟华","pinyin":"zhang'wei'hua"},{"word":"张艳军","pinyin":"zhang'yan'jun"},{"word":"赵永胜","pinyin":"zhao'yong'sheng"},{"word":"找正","pinyin":"zhao'zheng"},{"word":"柘溪","pinyin":"zhe'xi"},{"word":"折向器","pinyin":"zhe'xiang'qi"},{"word":"折向器接力器","pinyin":"zhe'xiang'qi'jie'li'qi"},{"word":"折向器轴","pinyin":"zhe'xiang'qi'zhou"},{"word":"真空破坏阀","pinyin":"zhen'kong'po'huai'fa"},{"word":"针形阀","pinyin":"zhen'xing'fa"},{"word":"正常蓄水位","pinyin":"zheng'chang'xu'shui'wei"},{"word":"正面","pinyin":"zheng'mian"},{"word":"质保部","pinyin":"zhi'bao'bu"},{"word":"支臂","pinyin":"zhi'bi"},{"word":"支持盖","pinyin":"zhi'chi'gai"},{"word":"制动喷嘴","pinyin":"zhi'dong'pen'zui"},{"word":"支墩","pinyin":"zhi'dun"},{"word":"质量保证部","pinyin":"zhi'liang'bao'zheng'bu"},{"word":"直流电极接负","pinyin":"zhi'liu'dian'ji'jie'fu"},{"word":"直流电极接正","pinyin":"zhi'liu'dian'ji'jie'zheng"},{"word":"止漏环","pinyin":"zhi'lou'huan"},{"word":"直坡口焊缝","pinyin":"zhi'po'kou'han'feng"},{"word":"止推轴承","pinyin":"zhi'tui'zhou'cheng"},{"word":"制造工艺部","pinyin":"zhi'zao'gong'yi'bu"},{"word":"中环板","pinyin":"zhong'huan'ban"},{"word":"中间轴","pinyin":"zhong'jian'zhou"},{"word":"中心体","pinyin":"zhong'xin'ti"},{"word":"中心筒","pinyin":"zhong'xin'tong"},{"word":"中心柱","pinyin":"zhong'xin'zhu"},{"word":"中性焊剂","pinyin":"zhong'xing'han'ji"},{"word":"轴承体","pinyin":"zhou'cheng'ti"},{"word":"轴承支架","pinyin":"zhou'cheng'zhi'jia"},{"word":"轴领","pinyin":"zhou'ling"},{"word":"轴流定桨式水轮机","pinyin":"zhou'liu'ding'jiang'shi'shui'lun'ji"},{"word":"轴流式水轮机","pinyin":"zhou'liu'shi'shui'lun'ji"},{"word":"轴流式蓄能泵","pinyin":"zhou'liu'shi'xu'neng'beng"},{"word":"轴流式转轮公称直径","pinyin":"zhou'liu'shi'zhuan'lun'gong'cheng'zhi'jing"},{"word":"轴流调桨式水轮机","pinyin":"zhou'liu'tiao'jiang'shi'shui'lun'ji"},{"word":"轴流转桨式水轮机","pinyin":"zhou'liu'zhuan'jiang'shi'shui'lun'ji"},{"word":"轴密封","pinyin":"zhou'mi'feng"},{"word":"轴伸贯流式水轮机","pinyin":"zhou'shen'guan'liu'shi'shui'lun'ji"},{"word":"轴瓦","pinyin":"zhou'wa"},{"word":"轴向支撑","pinyin":"zhou'xiang'zhi'cheng"},{"word":"肘形尾水管","pinyin":"zhou'xing'wei'shui'guan"},{"word":"肘形尾水管长度","pinyin":"zhou'xing'wei'shui'guan'chang'du"},{"word":"肘形尾水管深度","pinyin":"zhou'xing'wei'shui'guan'shen'du"},{"word":"主阀","pinyin":"zhu'fa"},{"word":"主阀与阀门","pinyin":"zhu'fa'yu'fa'men"},{"word":"主立筋","pinyin":"zhu'li'jin"},{"word":"驻留","pinyin":"zhu'liu"},{"word":"主轴","pinyin":"zhu'zhou"},{"word":"主轴密封","pinyin":"zhu'zhou'mi'feng"},{"word":"主轴密封装置","pinyin":"zhu'zhou'mi'feng'zhuang'zhi"},{"word":"转臂","pinyin":"zhuan'bi"},{"word":"转动部分","pinyin":"zhuan'dong'bu'fen"},{"word":"转动部件","pinyin":"zhuan'dong'bu'jian"},{"word":"转轮","pinyin":"zhuan'lun"},{"word":"转轮公称直径","pinyin":"zhuan'lun'gong'cheng'zhi'jing"},{"word":"转轮减压板","pinyin":"zhuan'lun'jian'ya'ban"},{"word":"转轮抗磨环","pinyin":"zhuan'lun'kang'mo'huan"},{"word":"转轮密封装置","pinyin":"zhuan'lun'mi'feng'zhuang'zhi"},{"word":"转轮上冠","pinyin":"zhuan'lun'shang'guan"},{"word":"转轮上冠密封","pinyin":"zhuan'lun'shang'guan'mi'feng"},{"word":"转轮上冠腔","pinyin":"zhuan'lun'shang'guan'qiang"},{"word":"转轮室","pinyin":"zhuan'lun'shi"},{"word":"转轮室上环","pinyin":"zhuan'lun'shi'shang'huan"},{"word":"转轮室下环","pinyin":"zhuan'lun'shi'xia'huan"},{"word":"转轮输出功率","pinyin":"zhuan'lun'shu'chu'gong'lv"},{"word":"转轮输入功率","pinyin":"zhuan'lun'shu'ru'gong'lv"},{"word":"转轮体","pinyin":"zhuan'lun'ti"},{"word":"转轮下环","pinyin":"zhuan'lun'xia'huan"},{"word":"转轮下环密封","pinyin":"zhuan'lun'xia'huan'mi'feng"},{"word":"转轮下环腔","pinyin":"zhuan'lun'xia'huan'qiang"},{"word":"转轮叶片","pinyin":"zhuan'lun'ye'pian"},{"word":"转轮叶片接力器","pinyin":"zhuan'lun'ye'pian'jie'li'qi"},{"word":"转轮运输车","pinyin":"zhuan'lun'yun'shu'che"},{"word":"转轮运输门","pinyin":"zhuan'lun'yun'shu'men"},{"word":"转轮直径","pinyin":"zhuan'lun'zhi'jing"},{"word":"转轮止漏环","pinyin":"zhuan'lun'zhi'lou'huan"},{"word":"转速","pinyin":"zhuan'su"},{"word":"转下序","pinyin":"zhuan'xia'xu"},{"word":"转叶机构","pinyin":"zhuan'ye'ji'gou"},{"word":"转油压机压平","pinyin":"zhuan'you'ya'ji'ya'ping"},{"word":"转子","pinyin":"zhuan'zi"},{"word":"转子支架","pinyin":"zhuan'zi'zhi'jia"},{"word":"装焊","pinyin":"zhuang'han"},{"word":"装配","pinyin":"zhuang'pei"},{"word":"装配试验","pinyin":"zhuang'pei'shi'yan"},{"word":"装配位置线","pinyin":"zhuang'pei'wei'zhi'xian"},{"word":"装置气蚀系数","pinyin":"zhuang'zhi'qi'shi'xi'shu"},{"word":"锥板","pinyin":"zhui'ban"},{"word":"锥形尾水管","pinyin":"zhui'xing'wei'shui'guan"},{"word":"自动焊","pinyin":"zi'dong'han"},{"word":"自检装配尺寸","pinyin":"zi'jian'zhuang'pei'chi'cun"},{"word":"自下而上","pinyin":"zi'xia'er'shang"},{"word":"自由公差标准","pinyin":"zi'you'gong'cha'biao'zhun"},{"word":"纵缝","pinyin":"zong'feng"},{"word":"综合特性曲线","pinyin":"zong'he'te'xing'qu'xian"},{"word":"总水头","pinyin":"zong'shui'tou"},{"word":"组合电极","pinyin":"zu'he'dian'ji"},{"word":"钻床","pinyin":"zuan'chuang"},{"word":"钻孔","pinyin":"zuan'kong"},{"word":"最大静水压","pinyin":"zui'da'jing'shui'ya"},{"word":"最大水头","pinyin":"zui'da'shui'tou"},{"word":"最低尾水位","pinyin":"zui'di'wei'shui'wei"},{"word":"最高静水头","pinyin":"zui'gao'jing'shui'tou"},{"word":"最高尾水位","pinyin":"zui'gao'wei'shui'wei"},{"word":"最小水头","pinyin":"zui'xiao'shui'tou"},{"word":"最优比转速","pinyin":"zui'you'bi'zhuan'su"},{"word":"最优工况","pinyin":"zui'you'gong'kuang"},{"word":"最优工况功率","pinyin":"zui'you'gong'kuang'gong'lv"},{"word":"最优效率","pinyin":"zui'you'xiao'lv"},{"word":"坐标线","pinyin":"zuo'biao'xian"},{"word":"左焊法","pinyin":"zuo'han'fa"},{"word":"座环","pinyin":"zuo'huan"},{"word":"座环环板","pinyin":"zuo'huan'huan'ban"},{"word":"座环扩散段","pinyin":"zuo'huan'kuo'san'duan"}]}