{"name":"不良反应-子谦","type":"医疗","description":"药品不良反应","example":"白内障 白细胞减少 白细胞增多 背部疾病 臂动脉血栓形成 鼻衄 ","words":[{"word":"嗳气","pinyin":"ai'qi"},{"word":"艾滋病","pinyin":"ai'zi'bing"},{"word":"白斑","pinyin":"bai'ban"},{"word":"白带","pinyin":"bai'dai"},{"word":"白内障","pinyin":"bai'nei'zhang"},{"word":"白内障摘除术","pinyin":"bai'nei'zhang'zhai'chu'shu"},{"word":"白细胞减少","pinyin":"bai'xi'bao'jian'shao"},{"word":"白细胞增多","pinyin":"bai'xi'bao'zeng'duo"},{"word":"白血病","pinyin":"bai'xue'bing"},{"word":"白血病样反应","pinyin":"bai'xue'bing'yang'fan'ying"},{"word":"斑丘疹","pinyin":"ban'qiu'zhen"},{"word":"背部疾病","pinyin":"bei'bu'ji'bing"},{"word":"苯丙酮尿","pinyin":"ben'bing'tong'niao"},{"word":"贲门驰缓不能","pinyin":"ben'men'chi'huan'bu'neng"},{"word":"臂动脉血栓形成","pinyin":"bi'dong'mai'xue'shuan'xing'cheng"},{"word":"闭经","pinyin":"bi'jing"},{"word":"臂静脉血栓形成","pinyin":"bi'jing'mai'xue'shuan'xing'cheng"},{"word":"鼻衄","pinyin":"bi'nv"},{"word":"鼻浅血栓性静脉炎","pinyin":"bi'qian'xue'shuan'xing'jing'mai'yan"},{"word":"臂深血栓性静脉炎","pinyin":"bi'shen'xue'shuan'xing'jing'mai'yan"},{"word":"鼻息肉","pinyin":"bi'xi'rou"},{"word":"臂血栓性静脉炎","pinyin":"bi'xue'shuan'xing'jing'mai'yan"},{"word":"鼻炎","pinyin":"bi'yan"},{"word":"鼻中隔穿孔","pinyin":"bi'zhong'ge'chuan'kong"},{"word":"鼻中隔溃疡","pinyin":"bi'zhong'ge'kui'yang"},{"word":"便秘","pinyin":"bian'mi"},{"word":"变态反应","pinyin":"bian'tai'fan'ying"},{"word":"变态反应加重","pinyin":"bian'tai'fan'ying'jia'zhong"},{"word":"变态反应性皮炎","pinyin":"bian'tai'fan'ying'xing'pi'yan"},{"word":"变应性肺泡炎","pinyin":"bian'ying'xing'fei'pao'yan"},{"word":"变应性脉管炎","pinyin":"bian'ying'xing'mai'guan'yan"},{"word":"表皮坏死","pinyin":"biao'pi'huai'si"},{"word":"憋气","pinyin":"bie'qi"},{"word":"病毒感染","pinyin":"bing'du'gan'ran"},{"word":"病理性骨折","pinyin":"bing'li'xing'gu'zhe"},{"word":"并指症","pinyin":"bing'zhi'zheng"},{"word":"玻璃体脱离","pinyin":"bo'li'ti'tuo'li"},{"word":"勃起功能障碍","pinyin":"bo'qi'gong'neng'zhang'ai"},{"word":"剥脱性皮炎","pinyin":"bo'tuo'xing'pi'yan"},{"word":"卟啉症","pinyin":"bu'lin'zheng"},{"word":"不耐乳糖","pinyin":"bu'nai'ru'tang"},{"word":"不适","pinyin":"bu'shi"},{"word":"步态异常","pinyin":"bu'tai'yi'chang"},{"word":"补体因子异常","pinyin":"bu'ti'yin'zi'yi'chang"},{"word":"不孕不育","pinyin":"bu'yun'bu'yu"},{"word":"苍白","pinyin":"cang'bai"},{"word":"藏毛囊肿","pinyin":"cang'mao'nang'zhong"},{"word":"产程延长","pinyin":"chan'cheng'yan'chang"},{"word":"产后泌乳减少","pinyin":"chan'hou'mi'ru'jian'shao"},{"word":"产后泌乳增加","pinyin":"chan'hou'mi'ru'zeng'jia"},{"word":"产伤","pinyin":"chan'shang"},{"word":"肠穿孔","pinyin":"chang'chuan'kong"},{"word":"肠动力疾病","pinyin":"chang'dong'li'ji'bing"},{"word":"肠梗阻","pinyin":"chang'geng'zu"},{"word":"肠坏死","pinyin":"chang'huai'si"},{"word":"肠溃疡","pinyin":"chang'kui'yang"},{"word":"肠溃疡穿孔","pinyin":"chang'kui'yang'chuan'kong"},{"word":"肠麻痹","pinyin":"chang'ma'bi"},{"word":"肠鸣音异常","pinyin":"chang'ming'yin'yi'chang"},{"word":"肠系膜静脉血栓性静脉炎","pinyin":"chang'xi'mo'jing'mai'xue'shuan'xing'jing'mai'yan"},{"word":"肠系膜栓塞","pinyin":"chang'xi'mo'shuan'se"},{"word":"肠系膜血管血栓形成","pinyin":"chang'xi'mo'xue'guan'xue'shuan'xing'cheng"},{"word":"肠狭窄","pinyin":"chang'xia'zhai"},{"word":"肠炎","pinyin":"chang'yan"},{"word":"肠炎加重","pinyin":"chang'yan'jia'zhong"},{"word":"潮红","pinyin":"chao'hong"},{"word":"超声心动图异常","pinyin":"chao'sheng'xin'dong'tu'yi'chang"},{"word":"潮式呼吸","pinyin":"chao'shi'hu'xi"},{"word":"撤药性抽搐","pinyin":"che'yao'xing'chou'chu"},{"word":"撤药性出血","pinyin":"che'yao'xing'chu'xie"},{"word":"撤药性头痛","pinyin":"che'yao'xing'tou'tong"},{"word":"撤药性心律失常","pinyin":"che'yao'xing'xin'lv'shi'chang"},{"word":"撤药性综合征","pinyin":"che'yao'xing'zong'he'zheng"},{"word":"痴呆","pinyin":"chi'dai"},{"word":"迟发性运动障碍","pinyin":"chi'fa'xing'yun'dong'zhang'ai"},{"word":"耻骨联合松懈","pinyin":"chi'gu'lian'he'song'xie"},{"word":"驰缓性麻痹","pinyin":"chi'huan'xing'ma'bi"},{"word":"齿周损害","pinyin":"chi'zhou'sun'hai"},{"word":"抽搐","pinyin":"chou'chu"},{"word":"抽动秽语综合征","pinyin":"chou'dong'hui'yu'zong'he'zheng"},{"word":"出汗减少","pinyin":"chu'han'jian'shao"},{"word":"搐搦","pinyin":"chu'nuo"},{"word":"出血时间延长","pinyin":"chu'xie'shi'jian'yan'chang"},{"word":"出血性皮炎","pinyin":"chu'xie'xing'pi'yan"},{"word":"出血性结肠炎","pinyin":"chu'xue'xing'jie'chang'yan"},{"word":"出血性膀胱炎","pinyin":"chu'xue'xing'pang'guang'yan"},{"word":"出血性胃炎","pinyin":"chu'xue'xing'wei'yan"},{"word":"喘鸣","pinyin":"chuan'ming"},{"word":"传染性肝炎","pinyin":"chuan'ran'xing'gan'yan"},{"word":"垂体病","pinyin":"chui'ti'bing"},{"word":"垂体功能不全","pinyin":"chui'ti'gong'neng'bu'quan"},{"word":"唇病","pinyin":"chun'bing"},{"word":"唇干","pinyin":"chun'gan"},{"word":"唇溃疡形成","pinyin":"chun'kui'yang'xing'cheng"},{"word":"唇裂","pinyin":"chun'lie"},{"word":"唇炎","pinyin":"chun'yan"},{"word":"雌激素增加","pinyin":"ci'ji'su'zeng'jia"},{"word":"猝死","pinyin":"cu'si"},{"word":"促性腺激素减少","pinyin":"cu'xing'xian'ji'su'jian'shao"},{"word":"促性腺激素增多","pinyin":"cu'xing'xian'ji'su'zeng'duo"},{"word":"卒中出血","pinyin":"cu'zhong'chu'xie"},{"word":"痤疮","pinyin":"cuo'chuang"},{"word":"错觉","pinyin":"cuo'jue"},{"word":"大便变色","pinyin":"da'bian'bian'se"},{"word":"大便急迫性增多","pinyin":"da'bian'ji'po'xing'zeng'duo"},{"word":"大便频率增多","pinyin":"da'bian'pin'lv'zeng'duo"},{"word":"大便失禁","pinyin":"da'bian'shi'jin"},{"word":"大脑病","pinyin":"da'nao'bing"},{"word":"大脑缺血","pinyin":"da'nao'que'xie"},{"word":"大脑血管障碍","pinyin":"da'nao'xue'guan'zhang'ai"},{"word":"大疱性疹","pinyin":"da'pao'xing'zhen"},{"word":"大血管移位","pinyin":"da'xue'guan'yi'wei"},{"word":"大叶性肺炎","pinyin":"da'ye'xing'fei'yan"},{"word":"代谢性碱中毒","pinyin":"dai'xie'xing'jian'zhong'du"},{"word":"代谢性酸中毒","pinyin":"dai'xie'xing'suan'zhong'du"},{"word":"带状疱疹","pinyin":"dai'zhuang'pao'zhen"},{"word":"蛋白尿","pinyin":"dan'bai'niao"},{"word":"单纯性疱疹","pinyin":"dan'chun'xing'pao'zhen"},{"word":"胆道闭锁","pinyin":"dan'dao'bi'suo"},{"word":"胆道病","pinyin":"dan'dao'bing"},{"word":"胆固醇结晶栓子","pinyin":"dan'gu'chun'jie'jing'shuan'zi"},{"word":"单核细胞白血病","pinyin":"dan'he'xi'bao'bai'xue'bing"},{"word":"单核细胞减少","pinyin":"dan'he'xi'bao'jian'shao"},{"word":"单核细胞增多","pinyin":"dan'he'xi'bao'zeng'duo"},{"word":"胆红素尿","pinyin":"dan'hong'su'niao"},{"word":"胆红素血症","pinyin":"dan'hong'su'xue'zheng"},{"word":"胆红素血症加重","pinyin":"dan'hong'su'xue'zheng'jia'zhong"},{"word":"胆碱能综合征","pinyin":"dan'jian'neng'zong'he'zheng"},{"word":"胆碱酯酶减少","pinyin":"dan'jian'zhi'mei'jian'shao"},{"word":"胆碱酯酶增加","pinyin":"dan'jian'zhi'mei'zeng'jia"},{"word":"淡漠","pinyin":"dan'mo"},{"word":"胆囊病","pinyin":"dan'nang'bing"},{"word":"胆囊痛","pinyin":"dan'nang'tong"},{"word":"胆囊炎","pinyin":"dan'nang'yan"},{"word":"单神经炎","pinyin":"dan'shen'jing'yan"},{"word":"单瘫","pinyin":"dan'tan"},{"word":"胆小管癌","pinyin":"dan'xiao'guan'ai"},{"word":"胆小管狭窄","pinyin":"dan'xiao'guan'xia'zhai"},{"word":"胆汁尿","pinyin":"dan'zhi'niao"},{"word":"胆汁性肝硬化","pinyin":"dan'zhi'xing'gan'ying'hua"},{"word":"胆汁淤积型肝炎","pinyin":"dan'zhi'yu'ji'xing'gan'yan"},{"word":"盗汗","pinyin":"dao'han"},{"word":"倒睫","pinyin":"dao'jie"},{"word":"导致耐药性或依赖性的药物","pinyin":"dao'zhi'nai'yao'xing'huo'yi'lai'xing'de'yao'wu"},{"word":"低蛋白血症","pinyin":"di'dan'bai'xue'zheng"},{"word":"低胆固醇血症","pinyin":"di'dan'gu'chun'xue'zheng"},{"word":"低钙血症","pinyin":"di'gai'xue'zheng"},{"word":"低钾血症","pinyin":"di'jia'xue'zheng"},{"word":"低磷酸盐血症","pinyin":"di'lin'suan'yan'xue'zheng"},{"word":"低氯血症","pinyin":"di'lv'xue'zheng"},{"word":"低镁血症","pinyin":"di'mei'xue'zheng"},{"word":"低钠血性惊厥","pinyin":"di'na'xue'xing'jing'jue"},{"word":"低钠血症","pinyin":"di'na'xue'zheng"},{"word":"低血钾","pinyin":"di'xue'jia"},{"word":"低血容量症","pinyin":"di'xue'rong'liang'zheng"},{"word":"低血色素性贫血","pinyin":"di'xue'se'su'xing'pin'xue"},{"word":"低血糖","pinyin":"di'xue'tang"},{"word":"低血糖反应","pinyin":"di'xue'tang'fan'ying"},{"word":"低血糖昏迷","pinyin":"di'xue'tang'hun'mi"},{"word":"低血压","pinyin":"di'xue'ya"},{"word":"淀粉酶降低","pinyin":"dian'fen'mei'jiang'di"},{"word":"淀粉酶增加","pinyin":"dian'fen'mei'zeng'jia"},{"word":"淀粉样变性","pinyin":"dian'fen'yang'bian'xing"},{"word":"电解质异常","pinyin":"dian'jie'zhi'yi'chang"},{"word":"癫痫大发作","pinyin":"dian'xian'da'fa'zuo"},{"word":"跌倒发作","pinyin":"die'dao'fa'zuo"},{"word":"动脉导管开放","pinyin":"dong'mai'dao'guan'kai'fang"},{"word":"动脉畸形","pinyin":"dong'mai'ji'xing"},{"word":"动脉瘤","pinyin":"dong'mai'liu"},{"word":"动脉瘤破裂","pinyin":"dong'mai'liu'po'lie"},{"word":"动脉栓塞","pinyin":"dong'mai'shuan'sai"},{"word":"动脉血栓形成","pinyin":"dong'mai'xue'shuan'xing'cheng"},{"word":"动脉炎","pinyin":"dong'mai'yan"},{"word":"动脉硬化","pinyin":"dong'mai'ying'hua"},{"word":"动脉粥样硬化","pinyin":"dong'mai'zhou'yang'ying'hua"},{"word":"动眼神经危象","pinyin":"dong'yan'shen'jing'wei'xiang"},{"word":"窦房结传导阻滞","pinyin":"dou'fang'jie'chuan'dao'zu'zhi"},{"word":"窦炎","pinyin":"dou'yan"},{"word":"多发性骨髓瘤","pinyin":"duo'fa'xing'gu'sui'liu"},{"word":"多发性畸形","pinyin":"duo'fa'xing'ji'xing"},{"word":"多发性浅血栓性静脉炎","pinyin":"duo'fa'xing'qian'xue'shuan'xing'jing'mai'yan"},{"word":"多发性深血栓性静脉炎","pinyin":"duo'fa'xing'shen'xue'shuan'xing'jing'mai'yan"},{"word":"多发性血栓性静脉炎","pinyin":"duo'fa'xing'xue'shuan'xing'jing'mai'yan"},{"word":"多发性硬化加重","pinyin":"duo'fa'xing'ying'hua'jia'zhong"},{"word":"多发性硬化样综合征","pinyin":"duo'fa'xing'ying'hua'yang'zong'he'zheng"},{"word":"多汗","pinyin":"duo'han"},{"word":"多肌炎","pinyin":"duo'ji'yan"},{"word":"多浆膜炎","pinyin":"duo'jiang'mo'yan"},{"word":"多毛","pinyin":"duo'mao"},{"word":"多毛症","pinyin":"duo'mao'zheng"},{"word":"多毛症加重","pinyin":"duo'mao'zheng'jia'zhong"},{"word":"多尿","pinyin":"duo'niao"},{"word":"多尿症","pinyin":"duo'niao'zheng"},{"word":"多胎妊娠","pinyin":"duo'tai'ren'shen"},{"word":"多形性红斑","pinyin":"duo'xing'xing'hong'ban"},{"word":"恶病质","pinyin":"e'bing'zhi"},{"word":"腭裂","pinyin":"e'lie"},{"word":"恶梦","pinyin":"e'meng"},{"word":"呃逆","pinyin":"e'ni"},{"word":"恶心","pinyin":"e'xin"},{"word":"恶性肝肿瘤","pinyin":"e'xing'gan'zhong'liu"},{"word":"恶性高热","pinyin":"e'xing'gao're"},{"word":"恶性黑瘤","pinyin":"e'xing'hei'liu"},{"word":"恶性喉肿瘤","pinyin":"e'xing'hou'zhong'liu"},{"word":"恶性甲状腺瘤","pinyin":"e'xing'jia'zhuang'xian'liu"},{"word":"恶性淋巴瘤","pinyin":"e'xing'lin'ba'liu"},{"word":"恶性卵巢囊肿","pinyin":"e'xing'luan'chao'nang'zhong"},{"word":"恶性脑瘤","pinyin":"e'xing'nao'liu"},{"word":"恶性皮肤肿瘤","pinyin":"e'xing'pi'fu'zhong'liu"},{"word":"恶性咽肿瘤","pinyin":"e'xing'yan'zhong'liu"},{"word":"恶性胰腺瘤","pinyin":"e'xing'yi'xian'liu"},{"word":"恶性肿瘤","pinyin":"e'xing'zhong'liu"},{"word":"耳毒性","pinyin":"er'du'xing"},{"word":"耳畸形","pinyin":"er'ji'xing"},{"word":"二尖瓣闭锁不全","pinyin":"er'jian'ban'bi'suo'bu'quan"},{"word":"耳聋","pinyin":"er'long"},{"word":"耳鸣","pinyin":"er'ming"},{"word":"耳痛","pinyin":"er'tong"},{"word":"儿童期蜕变性病","pinyin":"er'tong'qi'tui'bian'xing'bing"},{"word":"耳咽鼓管炎","pinyin":"er'yan'gu'guan'yan"},{"word":"耳硬化症","pinyin":"er'ying'hua'zheng"},{"word":"乏力","pinyin":"fa'li"},{"word":"发热","pinyin":"fa're"},{"word":"发音困难","pinyin":"fa'yin'kun'nan"},{"word":"发育迟缓者","pinyin":"fa'yu'chi'huan'zhe"},{"word":"发作性睡病","pinyin":"fa'zuo'xing'shui'bing"},{"word":"泛化性痉挛","pinyin":"fan'hua'xing'jing'luan"},{"word":"反射减弱","pinyin":"fan'she'jian'ruo"},{"word":"反射亢进","pinyin":"fan'she'kang'jin"},{"word":"房颤","pinyin":"fang'chan"},{"word":"房间隔缺","pinyin":"fang'jian'ge'que"},{"word":"放射性烧伤","pinyin":"fang'she'xing'shao'shang"},{"word":"房室传导阻滞","pinyin":"fang'shi'chuan'dao'zu'zhi"},{"word":"房性心律失常","pinyin":"fang'xing'xin'lv'shi'chang"},{"word":"肺癌","pinyin":"fei'ai"},{"word":"肺变应性肉芽肿","pinyin":"fei'bian'ying'xing'rou'ya'zhong"},{"word":"肺部肉芽肿","pinyin":"fei'bu'rou'ya'zhong"},{"word":"肺不张","pinyin":"fei'bu'zhang"},{"word":"非产后泌乳","pinyin":"fei'chan'hou'mi'ru"},{"word":"肺充血","pinyin":"fei'chong'xue"},{"word":"肺出血","pinyin":"fei'chu'xue"},{"word":"非蛋白氮减少","pinyin":"fei'dan'bai'dan'jian'shao"},{"word":"非蛋白氮增多","pinyin":"fei'dan'bai'dan'zeng'duo"},{"word":"非典型性淋巴细胞异常","pinyin":"fei'dian'xing'xing'lin'ba'xi'bao'yi'chang"},{"word":"肺动脉高压","pinyin":"fei'dong'mai'gao'ya"},{"word":"肺梗死","pinyin":"fei'geng'si"},{"word":"肺畸形","pinyin":"fei'ji'xing"},{"word":"非结肠憩室炎","pinyin":"fei'jie'chang'qi'shi'yan"},{"word":"肺浸润","pinyin":"fei'jin'run"},{"word":"肥胖","pinyin":"fei'pang"},{"word":"肺气肿","pinyin":"fei'qi'zhong"},{"word":"肺栓塞","pinyin":"fei'shuan'sai"},{"word":"肺水肿","pinyin":"fei'shui'zhong"},{"word":"非特异性白细胞异常","pinyin":"fei'te'yi'xing'bai'xi'bao'yi'chang"},{"word":"非特异性触痛","pinyin":"fei'te'yi'xing'chu'tong"},{"word":"非特异性出血","pinyin":"fei'te'yi'xing'chu'xie"},{"word":"非特异性垂体瘤","pinyin":"fei'te'yi'xing'chui'ti'liu"},{"word":"非特异性耳病","pinyin":"fei'te'yi'xing'er'bing"},{"word":"非特异性瘤","pinyin":"fei'te'yi'xing'liu"},{"word":"非特异性内分泌病","pinyin":"fei'te'yi'xing'nei'fen'mi'bing"},{"word":"非特异性事故","pinyin":"fei'te'yi'xing'shi'gu"},{"word":"非特异性食欲异常","pinyin":"fei'te'yi'xing'shi'yu'yi'chang"},{"word":"非特异性术后并发症","pinyin":"fei'te'yi'xing'shu'hou'bing'fa'zheng"},{"word":"非特异性胃肠道病","pinyin":"fei'te'yi'xing'wei'chang'dao'bing"},{"word":"非特异性腺癌","pinyin":"fei'te'yi'xing'xian'ai"},{"word":"非特异性先天异常","pinyin":"fei'te'yi'xing'xian'tian'yi'chang"},{"word":"非特异性粘膜炎","pinyin":"fei'te'yi'xing'zhan'mo'yan"},{"word":"非特异性脂代谢病","pinyin":"fei'te'yi'xing'zhi'dai'xie'bing"},{"word":"非特异性子宫病","pinyin":"fei'te'yi'xing'zi'gong'bing"},{"word":"肺萎缩","pinyin":"fei'wei'suo"},{"word":"肺纤维化","pinyin":"fei'xian'wei'hua"},{"word":"肺心病","pinyin":"fei'xin'bing"},{"word":"肺血栓形成","pinyin":"fei'xue'shuan'xing'cheng"},{"word":"肺炎","pinyin":"fei'yan"},{"word":"非药物过敏","pinyin":"fei'yao'wu'guo'min"},{"word":"肺硬化","pinyin":"fei'ying'hua"},{"word":"飞蝇幻视","pinyin":"fei'ying'huan'shi"},{"word":"非预期的药物无效","pinyin":"fei'yu'qi'de'yao'wu'wu'xiao"},{"word":"粪结石","pinyin":"fen'jie'shi"},{"word":"分娩异常","pinyin":"fen'mian'yi'chang"},{"word":"风湿性多肌痛","pinyin":"feng'shi'xing'duo'ji'tong"},{"word":"蜂窝织炎","pinyin":"feng'wo'zhi'yan"},{"word":"腹部强直","pinyin":"fu'bu'qiang'zhi"},{"word":"腹部胀大","pinyin":"fu'bu'zhang'da"},{"word":"附睾炎","pinyin":"fu'gao'yan"},{"word":"腹膜出血","pinyin":"fu'mo'chu'xie"},{"word":"腹膜后出血","pinyin":"fu'mo'hou'chu'xie"},{"word":"腹膜后纤维化","pinyin":"fu'mo'hou'xian'wei'hua"},{"word":"腹膜炎","pinyin":"fu'mo'yan"},{"word":"腹腔内出血","pinyin":"fu'qiang'nei'chu'xie"},{"word":"复视","pinyin":"fu'shi"},{"word":"腹水","pinyin":"fu'shui"},{"word":"腹痛","pinyin":"fu'tong"},{"word":"腹泻","pinyin":"fu'xie"},{"word":"腹胀","pinyin":"fu'zhang"},{"word":"钙质沉着","pinyin":"gai'zhi'chen'zhuo"},{"word":"肝出血","pinyin":"gan'chu'xie"},{"word":"肝大","pinyin":"gan'da"},{"word":"肝功能不全","pinyin":"gan'gong'neng'bu'quan"},{"word":"肝功能异常","pinyin":"gan'gong'neng'yi'chang"},{"word":"肝坏死","pinyin":"gan'huai'si"},{"word":"肝昏迷","pinyin":"gan'hun'mi"},{"word":"感觉迟钝","pinyin":"gan'jue'chi'dun"},{"word":"感觉过敏","pinyin":"gan'jue'guo'min"},{"word":"感觉混乱","pinyin":"gan'jue'hun'luan"},{"word":"感觉神经炎","pinyin":"gan'jue'shen'jing'yan"},{"word":"感觉异常","pinyin":"gan'jue'yi'chang"},{"word":"肝酶升高","pinyin":"gan'mei'sheng'gao"},{"word":"肝囊肿","pinyin":"gan'nang'zhong"},{"word":"肝脾大","pinyin":"gan'pi'da"},{"word":"感染","pinyin":"gan'ran"},{"word":"感染加重","pinyin":"gan'ran'jia'zhong"},{"word":"感染性关节炎","pinyin":"gan'ran'xing'guan'jie'yan"},{"word":"感染易感性增加","pinyin":"gan'ran'yi'gan'xing'zeng'jia"},{"word":"肝肾综合征","pinyin":"gan'shen'zong'he'zheng"},{"word":"肝衰竭","pinyin":"gan'shuai'jie"},{"word":"肝细胞损害","pinyin":"gan'xi'bao'sun'hai"},{"word":"肝炎","pinyin":"gan'yan"},{"word":"干眼病","pinyin":"gan'yan'bing"},{"word":"肝硬变","pinyin":"gan'ying'bian"},{"word":"肝硬化","pinyin":"gan'ying'hua"},{"word":"肝肿瘤","pinyin":"gan'zhong'liu"},{"word":"肛门闭锁","pinyin":"gang'men'bi'suo"},{"word":"肛门骚痒","pinyin":"gang'men'sao'yang"},{"word":"肛门障碍","pinyin":"gang'men'zhang'ai"},{"word":"肛痛","pinyin":"gang'tong"},{"word":"高氨血症","pinyin":"gao'an'xue'zheng"},{"word":"高草酸尿","pinyin":"gao'cao'suan'niao"},{"word":"高催乳素血症","pinyin":"gao'cui'ru'su'xue'zheng"},{"word":"高胆固醇血症","pinyin":"gao'dan'gu'chun'xue'zheng"},{"word":"高钙尿","pinyin":"gao'gai'niao"},{"word":"高钙血症","pinyin":"gao'gai'xue'zheng"},{"word":"高甘油三酯血症","pinyin":"gao'gan'you'san'zhi'xue'zheng"},{"word":"高钾血症","pinyin":"gao'jia'xue'zheng"},{"word":"高磷酸盐血症","pinyin":"gao'lin'suan'yan'xue'zheng"},{"word":"高氯血症","pinyin":"gao'lv'xue'zheng"},{"word":"高镁血症","pinyin":"gao'mei'xue'zheng"},{"word":"高密度脂蛋白减少","pinyin":"gao'mi'du'zhi'dan'bai'jian'shao"},{"word":"高钠血症","pinyin":"gao'na'xue'zheng"},{"word":"高尿酸血症","pinyin":"gao'niao'suan'xue'zheng"},{"word":"高尿酸血症性肾病","pinyin":"gao'niao'suan'xue'zheng'xing'shen'bing"},{"word":"高球蛋白血症","pinyin":"gao'qiu'dan'bai'xue'zheng"},{"word":"高热","pinyin":"gao're"},{"word":"高碳酸血症","pinyin":"gao'tan'suan'xue'zheng"},{"word":"睾丸病","pinyin":"gao'wan'bing"},{"word":"睾丸恶性肿瘤","pinyin":"gao'wan'e'xing'zhong'liu"},{"word":"睾丸发育不全","pinyin":"gao'wan'fa'yu'bu'quan"},{"word":"睾丸炎","pinyin":"gao'wan'yan"},{"word":"高血色素性贫血","pinyin":"gao'xue'se'su'xing'pin'xue"},{"word":"高血糖","pinyin":"gao'xue'tang"},{"word":"高血压","pinyin":"gao'xue'ya"},{"word":"高血压加重","pinyin":"gao'xue'ya'jia'zhong"},{"word":"高血压性脑病","pinyin":"gao'xue'ya'xing'nao'bing"},{"word":"高脂血症","pinyin":"gao'zhi'xue'zheng"},{"word":"格林巴利综合征","pinyin":"ge'lin'ba'li'zong'he'zheng"},{"word":"跟骨骨刺","pinyin":"gen'gu'gu'ci"},{"word":"梗死后心肌破裂","pinyin":"geng'si'hou'xin'ji'po'lie"},{"word":"共济失调","pinyin":"gong'ji'shi'tiao"},{"word":"攻击性反应","pinyin":"gong'ji'xing'fan'ying"},{"word":"宫颈癌","pinyin":"gong'jing'ai"},{"word":"宫颈发育不良","pinyin":"gong'jing'fa'yu'bu'liang"},{"word":"宫颈损害","pinyin":"gong'jing'sun'hai"},{"word":"宫颈涂片试验阳性","pinyin":"gong'jing'tu'pian'shi'yan'yang'xing"},{"word":"宫颈息肉","pinyin":"gong'jing'xi'rou"},{"word":"宫颈炎","pinyin":"gong'jing'yan"},{"word":"巩膜炎","pinyin":"gong'mo'yan"},{"word":"宫内避孕器并发症","pinyin":"gong'nei'bi'yun'qi'bing'fa'zheng"},{"word":"弓形体病","pinyin":"gong'xing'ti'bing"},{"word":"谷氨酰转肽酶增加","pinyin":"gu'an'xian'zhuan'tai'mei'zeng'jia"},{"word":"骨病","pinyin":"gu'bing"},{"word":"谷丙转氨酶升高","pinyin":"gu'bing'zhuan'an'mei'sheng'gao"},{"word":"谷草转氨酶升高","pinyin":"gu'cao'zhuan'an'mei'sheng'gao"},{"word":"固定型皮疹","pinyin":"gu'ding'xing'pi'zhen"},{"word":"骨发育异常","pinyin":"gu'fa'yu'yi'chang"},{"word":"骨肥厚","pinyin":"gu'fei'hou"},{"word":"骨骼畸形","pinyin":"gu'ge'ji'xing"},{"word":"股骨头无血管性坏死","pinyin":"gu'gu'tou'wu'xue'guan'xing'huai'si"},{"word":"骨坏死","pinyin":"gu'huai'si"},{"word":"骨连接","pinyin":"gu'lian'jie"},{"word":"骨瘤","pinyin":"gu'liu"},{"word":"鼓膜穿孔","pinyin":"gu'mo'chuan'kong"},{"word":"骨盆静脉血栓性静脉炎","pinyin":"gu'pen'jing'mai'xue'shuan'xing'jing'mai'yan"},{"word":"孤僻","pinyin":"gu'pi"},{"word":"孤僻病","pinyin":"gu'pi'bing"},{"word":"骨软化","pinyin":"gu'ruan'hua"},{"word":"骨髓纤维变性","pinyin":"gu'sui'xian'wei'bian'xing"},{"word":"骨髓炎","pinyin":"gu'sui'yan"},{"word":"骨髓抑制","pinyin":"gu'sui'yi'zhi"},{"word":"骨髓移植","pinyin":"gu'sui'yi'zhi"},{"word":"骨髓再生不全","pinyin":"gu'sui'zai'sheng'bu'quan"},{"word":"骨髓增生","pinyin":"gu'sui'zeng'sheng"},{"word":"骨髓增生病","pinyin":"gu'sui'zeng'sheng'bing"},{"word":"骨髓转化","pinyin":"gu'sui'zhuan'hua"},{"word":"骨痛","pinyin":"gu'tong"},{"word":"骨无菌性坏死","pinyin":"gu'wu'jun'xing'huai'si"},{"word":"骨炎","pinyin":"gu'yan"},{"word":"骨硬化","pinyin":"gu'ying'hua"},{"word":"骨质软化","pinyin":"gu'zhi'ruan'hua"},{"word":"骨质疏松","pinyin":"gu'zhi'shu'song"},{"word":"骨质疏松症","pinyin":"gu'zhi'shu'song'zheng"},{"word":"关节病","pinyin":"guan'jie'bing"},{"word":"关节成形术","pinyin":"guan'jie'cheng'xing'shu"},{"word":"关节畸形","pinyin":"guan'jie'ji'xing"},{"word":"关节积血","pinyin":"guan'jie'ji'xue"},{"word":"关节内游离体","pinyin":"guan'jie'nei'you'li'ti"},{"word":"关节痛","pinyin":"guan'jie'tong"},{"word":"关节炎","pinyin":"guan'jie'yan"},{"word":"关节炎加重","pinyin":"guan'jie'yan'jia'zhong"},{"word":"冠脉病","pinyin":"guan'mai'bing"},{"word":"冠心病未特指","pinyin":"guan'xin'bing'wei'te'zhi"},{"word":"管行尿","pinyin":"guan'xing'niao"},{"word":"冠状动脉术","pinyin":"guan'zhuang'dong'mai'shu"},{"word":"冠状动脉血栓形成","pinyin":"guan'zhuang'dong'mai'xue'shuan'xing'cheng"},{"word":"光敏感","pinyin":"guang'min'gan"},{"word":"光学缺血性神经病","pinyin":"guang'xue'que'xue'xing'shen'jing'bing"},{"word":"龟头包皮炎","pinyin":"gui'tou'bao'pi'yan"},{"word":"过度成熟分娩","pinyin":"guo'du'cheng'shu'fen'mian"},{"word":"过敏反应未特指","pinyin":"guo'min'fan'ying'wei'te'zhi"},{"word":"过敏性哮喘","pinyin":"guo'min'xing'xiao'chuan"},{"word":"过敏性休克","pinyin":"guo'min'xing'xiu'ke"},{"word":"过敏性紫癫","pinyin":"guo'min'xing'zi'dian"},{"word":"过敏样反应","pinyin":"guo'min'yang'fan'ying"},{"word":"过期流产","pinyin":"guo'qi'liu'chan"},{"word":"汗变色","pinyin":"han'bian'se"},{"word":"汗腺病","pinyin":"han'xian'bing"},{"word":"寒战","pinyin":"han'zhan"},{"word":"颌骨畸形","pinyin":"he'gu'ji'xing"},{"word":"呵欠","pinyin":"he'qian"},{"word":"黑变病","pinyin":"hei'bian'bing"},{"word":"黑粪症","pinyin":"hei'fen'zheng"},{"word":"黑尿病","pinyin":"hei'niao'bing"},{"word":"横膈发育不良","pinyin":"heng'ge'fa'yu'bu'liang"},{"word":"横纹肌溶解","pinyin":"heng'wen'ji'rong'jie"},{"word":"红白血病","pinyin":"hong'bai'xue'bing"},{"word":"红斑","pinyin":"hong'ban"},{"word":"红斑狼疮","pinyin":"hong'ban'lang'chuang"},{"word":"红斑狼疮试验异常","pinyin":"hong'ban'lang'chuang'shi'yan'yi'chang"},{"word":"红斑狼疮性疹","pinyin":"hong'ban'lang'chuang'xing'zhen"},{"word":"红斑狼疮综合征","pinyin":"hong'ban'lang'chuang'zong'he'zheng"},{"word":"红斑狼疮综合征加重","pinyin":"hong'ban'lang'chuang'zong'he'zheng'jia'zhong"},{"word":"红斑性肢痛病","pinyin":"hong'ban'xing'zhi'tong'bing"},{"word":"红斑疹","pinyin":"hong'ban'zhen"},{"word":"虹膜睫状体炎","pinyin":"hong'mo'jie'zhuang'ti'yan"},{"word":"虹膜炎","pinyin":"hong'mo'yan"},{"word":"红人综合征","pinyin":"hong'ren'zong'he'zheng"},{"word":"红细胞发育不全","pinyin":"hong'xi'bao'fa'yu'bu'quan"},{"word":"红细胞凝集","pinyin":"hong'xi'bao'ning'ji"},{"word":"红细胞异常","pinyin":"hong'xi'bao'yi'chang"},{"word":"红细胞增多","pinyin":"hong'xi'bao'zeng'duo"},{"word":"骺分离","pinyin":"hou'fen'li"},{"word":"喉痉挛","pinyin":"hou'jing'luan"},{"word":"喉水肿","pinyin":"hou'shui'zhong"},{"word":"后天脑积水","pinyin":"hou'tian'nao'ji'shui"},{"word":"后天性巨结肠","pinyin":"hou'tian'xing'ju'jie'chang"},{"word":"后天性血管瘤","pinyin":"hou'tian'xing'xue'guan'liu"},{"word":"喉炎","pinyin":"hou'yan"},{"word":"呼吸病","pinyin":"hu'xi'bing"},{"word":"呼吸道出血","pinyin":"hu'xi'dao'chu'xie"},{"word":"呼吸道畸形","pinyin":"hu'xi'dao'ji'xing"},{"word":"呼吸功能不全","pinyin":"hu'xi'gong'neng'bu'quan"},{"word":"呼吸急促","pinyin":"hu'xi'ji'cu"},{"word":"呼吸困难","pinyin":"hu'xi'kun'nan"},{"word":"呼吸兴奋","pinyin":"hu'xi'xing'fen"},{"word":"呼吸性碱中毒","pinyin":"hu'xi'xing'jian'zhong'du"},{"word":"呼吸性酸中毒","pinyin":"hu'xi'xing'suan'zhong'du"},{"word":"呼吸徐缓","pinyin":"hu'xi'xu'huan"},{"word":"呼吸抑制","pinyin":"hu'xi'yi'zhi"},{"word":"滑膜炎","pinyin":"hua'mo'yan"},{"word":"滑囊炎","pinyin":"hua'nang'yan"},{"word":"坏疽","pinyin":"huai'ju"},{"word":"坏疽性脓皮病","pinyin":"huai'ju'xing'nong'pi'bing"},{"word":"坏死性口炎","pinyin":"huai'si'xing'kou'yan"},{"word":"幻觉","pinyin":"huan'jue"},{"word":"换气不足","pinyin":"huan'qi'bu'zu"},{"word":"换气过度","pinyin":"huan'qi'guo'du"},{"word":"黄斑变性","pinyin":"huang'ban'bian'xing"},{"word":"黄疸","pinyin":"huang'dan"},{"word":"黄褐斑","pinyin":"huang'he'ban"},{"word":"黄瘤病","pinyin":"huang'liu'bing"},{"word":"回肠炎","pinyin":"hui'chang'yan"},{"word":"灰婴综合征","pinyin":"hui'ying'zong'he'zheng"},{"word":"昏迷","pinyin":"hun'mi"},{"word":"活动性真菌病","pinyin":"huo'dong'xing'zhen'jun'bing"},{"word":"肌病","pinyin":"ji'bing"},{"word":"肌出血","pinyin":"ji'chu'xie"},{"word":"基底细胞癌","pinyin":"ji'di'xi'bao'ai"},{"word":"继发性脓毒病","pinyin":"ji'fa'xing'nong'du'bing"},{"word":"肌肥厚","pinyin":"ji'fei'hou"},{"word":"肌酐清除率降低","pinyin":"ji'gan'qing'chu'lv'jiang'di"},{"word":"肌红蛋白尿","pinyin":"ji'hong'dan'bai'niao"},{"word":"激活的疼痛性炎症","pinyin":"ji'huo'de'teng'tong'xing'yan'zheng"},{"word":"肌畸形","pinyin":"ji'ji'xing"},{"word":"肌腱损害","pinyin":"ji'jian'sun'hai"},{"word":"肌腱炎","pinyin":"ji'jian'yan"},{"word":"肌痉挛","pinyin":"ji'jing'luan"},{"word":"肌麻痹","pinyin":"ji'ma'bi"},{"word":"棘皮症","pinyin":"ji'pi'zheng"},{"word":"肌肉不随意收缩","pinyin":"ji'rou'bu'sui'yi'shou'suo"},{"word":"肌肉骨骼病","pinyin":"ji'rou'gu'ge'bing"},{"word":"肌肉骨骼痛","pinyin":"ji'rou'gu'ge'tong"},{"word":"肌肉萎缩","pinyin":"ji'rou'wei'suo"},{"word":"肌酸磷酸激酶升高","pinyin":"ji'suan'lin'suan'ji'mei'sheng'gao"},{"word":"脊髓灰质炎","pinyin":"ji'sui'hui'zhi'yan"},{"word":"脊髓脊膜突出","pinyin":"ji'sui'ji'mo'tu'chu"},{"word":"脊髓炎","pinyin":"ji'sui'yan"},{"word":"畸胎瘤","pinyin":"ji'tai'liu"},{"word":"肌痛","pinyin":"ji'tong"},{"word":"肌无力","pinyin":"ji'wu'li"},{"word":"急性白血病","pinyin":"ji'xing'bai'xue'bing"},{"word":"急性全身性小脓疱","pinyin":"ji'xing'quan'shen'xing'xiao'nong'pao"},{"word":"急性肾衰竭","pinyin":"ji'xing'shen'shuai'jie"},{"word":"畸形手","pinyin":"ji'xing'shou"},{"word":"急性荨麻疹","pinyin":"ji'xing'xun'ma'zhen"},{"word":"急性应激性反应","pinyin":"ji'xing'ying'ji'xing'fan'ying"},{"word":"畸形足","pinyin":"ji'xing'zu"},{"word":"肌炎","pinyin":"ji'yan"},{"word":"记忆力减退","pinyin":"ji'yi'li'jian'tui"},{"word":"脊柱畸形","pinyin":"ji'zhu'ji'xing"},{"word":"脊柱裂","pinyin":"ji'zhu'lie"},{"word":"甲病","pinyin":"jia'bing"},{"word":"甲沟炎","pinyin":"jia'gou'yan"},{"word":"钾尿增多","pinyin":"jia'niao'zeng'duo"},{"word":"甲胎蛋白含量增加","pinyin":"jia'tai'dan'bai'han'liang'zeng'jia"},{"word":"假性脑膜炎","pinyin":"jia'xing'nao'mo'yan"},{"word":"假孕","pinyin":"jia'yun"},{"word":"甲状旁腺功能减退","pinyin":"jia'zhuang'pang'xian'gong'neng'jian'tui"},{"word":"甲状旁腺功能亢进","pinyin":"jia'zhuang'pang'xian'gong'neng'kang'jin"},{"word":"甲状腺病","pinyin":"jia'zhuang'xian'bing"},{"word":"甲状腺功能减退","pinyin":"jia'zhuang'xian'gong'neng'jian'tui"},{"word":"甲状腺功能亢进","pinyin":"jia'zhuang'xian'gong'neng'kang'jin"},{"word":"甲状腺功能亢进加重","pinyin":"jia'zhuang'xian'gong'neng'kang'jin'jia'zhong"},{"word":"甲状腺瘤","pinyin":"jia'zhuang'xian'liu"},{"word":"甲状腺囊肿","pinyin":"jia'zhuang'xian'nang'zhong"},{"word":"甲状腺素减少","pinyin":"jia'zhuang'xian'su'jian'shao"},{"word":"甲状腺素增加","pinyin":"jia'zhuang'xian'su'zeng'jia"},{"word":"甲状腺炎","pinyin":"jia'zhuang'xian'yan"},{"word":"甲状腺肿","pinyin":"jia'zhuang'xian'zhong"},{"word":"尖端扭转性室速","pinyin":"jian'duan'niu'zhuan'xing'shi'su"},{"word":"艰难梭菌腹泻","pinyin":"jian'nan'suo'jun'fu'xie"},{"word":"踺破裂","pinyin":"jian'po'lie"},{"word":"间期延长","pinyin":"jian'qi'yan'chang"},{"word":"腱鞘炎","pinyin":"jian'qiao'yan"},{"word":"健忘","pinyin":"jian'wang"},{"word":"间歇性跛行","pinyin":"jian'xie'xing'bo'xing"},{"word":"碱性磷酸酶升高","pinyin":"jian'xing'lin'suan'mei'sheng'gao"},{"word":"间质性肾炎","pinyin":"jian'zhi'xing'shen'yan"},{"word":"碱中毒","pinyin":"jian'zhong'du"},{"word":"交叉感染","pinyin":"jiao'cha'gan'ran"},{"word":"角弓反张","pinyin":"jiao'gong'fan'zhang"},{"word":"角化过度","pinyin":"jiao'hua'guo'du"},{"word":"焦急不安","pinyin":"jiao'ji'bu'an"},{"word":"交流障碍","pinyin":"jiao'liu'zhang'ai"},{"word":"焦虑","pinyin":"jiao'lv"},{"word":"角膜病","pinyin":"jiao'mo'bing"},{"word":"角膜浑浊","pinyin":"jiao'mo'hun'zhuo"},{"word":"角膜积物","pinyin":"jiao'mo'ji'wu"},{"word":"角膜结膜炎","pinyin":"jiao'mo'jie'mo'yan"},{"word":"角膜溃疡","pinyin":"jiao'mo'kui'yang"},{"word":"角膜水肿","pinyin":"jiao'mo'shui'zhong"},{"word":"角膜炎","pinyin":"jiao'mo'yan"},{"word":"胶原病","pinyin":"jiao'yuan'bing"},{"word":"焦燥不安","pinyin":"jiao'zao'bu'an"},{"word":"疖病","pinyin":"jie'bing"},{"word":"结肠癌","pinyin":"jie'chang'ai"},{"word":"结肠憩室病","pinyin":"jie'chang'qi'shi'bing"},{"word":"结肠憩室炎","pinyin":"jie'chang'qi'shi'yan"},{"word":"结肠炎","pinyin":"jie'chang'yan"},{"word":"接触性皮炎","pinyin":"jie'chu'xing'pi'yan"},{"word":"结核菌感染","pinyin":"jie'he'jun'gan'ran"},{"word":"结核性骨炎","pinyin":"jie'he'xing'gu'yan"},{"word":"结痂","pinyin":"jie'jia"},{"word":"结节性多动脉炎","pinyin":"jie'jie'xing'duo'dong'mai'yan"},{"word":"结节性多发性动脉炎","pinyin":"jie'jie'xing'duo'fa'xing'dong'mai'yan"},{"word":"结节性红斑","pinyin":"jie'jie'xing'hong'ban"},{"word":"睫毛生长","pinyin":"jie'mao'sheng'zhang"},{"word":"结膜病","pinyin":"jie'mo'bing"},{"word":"结膜充血","pinyin":"jie'mo'chong'xue"},{"word":"结膜出血","pinyin":"jie'mo'chu'xie"},{"word":"结膜溃疡","pinyin":"jie'mo'kui'yang"},{"word":"结膜色素异常","pinyin":"jie'mo'se'su'yi'chang"},{"word":"结膜炎","pinyin":"jie'mo'yan"},{"word":"结舌","pinyin":"jie'she"},{"word":"截瘫","pinyin":"jie'tan"},{"word":"结性心律不齐","pinyin":"jie'xing'xin'lv'bu'qi"},{"word":"近视","pinyin":"jin'shi"},{"word":"紧张症反应","pinyin":"jin'zhang'zheng'fan'ying"},{"word":"颈动脉血栓形成","pinyin":"jing'dong'mai'xue'shuan'xing'cheng"},{"word":"惊厥","pinyin":"jing'jue"},{"word":"惊厥加重","pinyin":"jing'jue'jia'zhong"},{"word":"惊恐","pinyin":"jing'kong"},{"word":"颈淋巴结病","pinyin":"jing'lin'ba'jie'bing"},{"word":"痉挛性肠梗阻","pinyin":"jing'luan'xing'chang'geng'zu"},{"word":"痉挛性麻痹","pinyin":"jing'luan'xing'ma'bi"},{"word":"静脉闭塞性肝病","pinyin":"jing'mai'bi'se'xing'gan'bing"},{"word":"静脉病","pinyin":"jing'mai'bing"},{"word":"静脉扩张","pinyin":"jing'mai'kuo'zhang"},{"word":"静脉曲张","pinyin":"jing'mai'qu'zhang"},{"word":"静脉痛","pinyin":"jing'mai'tong"},{"word":"静脉炎","pinyin":"jing'mai'yan"},{"word":"静脉炎后综合征","pinyin":"jing'mai'yan'hou'zong'he'zheng"},{"word":"精神病","pinyin":"jing'shen'bing"},{"word":"精神错乱","pinyin":"jing'shen'cuo'luan"},{"word":"精神分裂样反应","pinyin":"jing'shen'fen'lie'yang'fan'ying"},{"word":"精神性失用症","pinyin":"jing'shen'xing'shi'yong'zheng"},{"word":"精神性性交困难","pinyin":"jing'shen'xing'xing'jiao'kun'nan"},{"word":"精神性抑郁","pinyin":"jing'shen'xing'yi'yu"},{"word":"精神运动发育障碍","pinyin":"jing'shen'yun'dong'fa'yu'zhang'ai"},{"word":"精原细胞瘤","pinyin":"jing'yuan'xi'bao'liu"},{"word":"精子颈部环代综合征","pinyin":"jing'zi'jing'bu'huan'dai'zong'he'zheng"},{"word":"精子异常","pinyin":"jing'zi'yi'chang"},{"word":"酒精中毒","pinyin":"jiu'jing'zhong'du"},{"word":"酒渣鼻","pinyin":"jiu'zha'bi"},{"word":"局部反应","pinyin":"ju'bu'fan'ying"},{"word":"局部麻木","pinyin":"ju'bu'ma'mu"},{"word":"局部用药反应","pinyin":"ju'bu'yong'yao'fan'ying"},{"word":"巨人症","pinyin":"ju'ren'zheng"},{"word":"巨细胞性贫血","pinyin":"ju'xi'bao'xing'pin'xue"},{"word":"局限性抽搐","pinyin":"ju'xian'xing'chou'chu"},{"word":"巨幼红细胞性贫血","pinyin":"ju'you'hong'xi'bao'xing'pin'xue"},{"word":"皲裂","pinyin":"jun'lie"},{"word":"菌尿","pinyin":"jun'niao"},{"word":"卡氏肺囊虫感染","pinyin":"ka'shi'fei'nang'chong'gan'ran"},{"word":"咯血","pinyin":"ka'xie"},{"word":"抗胆碱能综合征","pinyin":"kang'dan'jian'neng'zong'he'zheng"},{"word":"亢奋","pinyin":"kang'fen"},{"word":"抗核因子试验阳性","pinyin":"kang'he'yin'zi'shi'yan'yang'xing"},{"word":"抗利尿激素病","pinyin":"kang'li'niao'ji'su'bing"},{"word":"抗利尿激素异常分泌综合征","pinyin":"kang'li'niao'ji'su'yi'chang'fen'mi'zong'he'zheng"},{"word":"糠疹","pinyin":"kang'zhen"},{"word":"咳嗽","pinyin":"ke'sou"},{"word":"口臭","pinyin":"kou'chou"},{"word":"口疮性口炎","pinyin":"kou'chuang'xing'kou'yan"},{"word":"口干","pinyin":"kou'gan"},{"word":"口渴","pinyin":"kou'ke"},{"word":"口腔出血","pinyin":"kou'qiang'chu'xie"},{"word":"口腔良性肿瘤","pinyin":"kou'qiang'liang'xing'zhong'liu"},{"word":"口腔粘膜白斑病","pinyin":"kou'qiang'nian'mo'bai'ban'bing"},{"word":"口炎","pinyin":"kou'yan"},{"word":"哭声异常","pinyin":"ku'sheng'yi'chang"},{"word":"眶周水肿","pinyin":"kuang'zhou'shui'zhong"},{"word":"溃疡性鼻炎","pinyin":"kui'yang'xing'bi'yan"},{"word":"溃疡性结肠炎","pinyin":"kui'yang'xing'jie'chang'yan"},{"word":"溃疡性结肠炎加重","pinyin":"kui'yang'xing'jie'chang'yan'jia'zhong"},{"word":"溃疡性口炎","pinyin":"kui'yang'xing'kou'yan"},{"word":"溃疡性阴道炎","pinyin":"kui'yang'xing'yin'dao'yan"},{"word":"溃疡性直肠炎","pinyin":"kui'yang'xing'zhi'chang'yan"},{"word":"劳动能力丧失","pinyin":"lao'dong'neng'li'sang'shi"},{"word":"类风湿性关节炎","pinyin":"lei'feng'shi'xing'guan'jie'yan"},{"word":"类风湿性关节炎加重","pinyin":"lei'feng'shi'xing'guan'jie'yan'jia'zhong"},{"word":"泪管梗阻","pinyin":"lei'guan'geng'zu"},{"word":"泪腺病","pinyin":"lei'xian'bing"},{"word":"冷凝集试验阳性","pinyin":"leng'ning'ji'shi'yan'yang'xing"},{"word":"冷凝球蛋白血症","pinyin":"leng'ning'qiu'dan'bai'xue'zheng"},{"word":"冷荨麻疹","pinyin":"leng'xun'ma'zhen"},{"word":"里急后重","pinyin":"li'ji'hou'zhong"},{"word":"立毛","pinyin":"li'mao"},{"word":"粒细胞减少","pinyin":"li'xi'bao'jian'shao"},{"word":"粒细胞缺乏症","pinyin":"li'xi'bao'que'fa'zheng"},{"word":"粒细胞性白血病","pinyin":"li'xi'bao'xing'bai'xue'bing"},{"word":"粒细胞增多","pinyin":"li'xi'bao'zeng'duo"},{"word":"良性垂体瘤","pinyin":"liang'xing'chui'ti'liu"},{"word":"良性肝肿瘤","pinyin":"liang'xing'gan'zhong'liu"},{"word":"良性喉肿瘤","pinyin":"liang'xing'hou'zhong'liu"},{"word":"良性脑瘤","pinyin":"liang'xing'nao'liu"},{"word":"疗效降低","pinyin":"liao'xiao'jiang'di"},{"word":"疗效增加","pinyin":"liao'xiao'zeng'jia"},{"word":"淋巴管炎","pinyin":"lin'ba'guan'yan"},{"word":"淋巴结病","pinyin":"lin'ba'jie'bing"},{"word":"淋巴瘤样病","pinyin":"lin'ba'liu'yang'bing"},{"word":"淋巴水肿","pinyin":"lin'ba'shui'zhong"},{"word":"淋巴细胞减少","pinyin":"lin'ba'xi'bao'jian'shao"},{"word":"淋巴细胞型白血病","pinyin":"lin'ba'xi'bao'xing'bai'xue'bing"},{"word":"淋巴细胞增多","pinyin":"lin'ba'xi'bao'zeng'duo"},{"word":"流产","pinyin":"liu'chan"},{"word":"流感样症状","pinyin":"liu'gan'yang'zheng'zhuang"},{"word":"硫红血红蛋白血症","pinyin":"liu'hong'xue'hong'dan'bai'xue'zheng"},{"word":"流泪异常","pinyin":"liu'lei'yi'chang"},{"word":"颅内产伤","pinyin":"lu'nei'chan'shang"},{"word":"颅内出血","pinyin":"lu'nei'chu'xue"},{"word":"颅内压升高","pinyin":"lu'nei'ya'sheng'gao"},{"word":"颅神经损害","pinyin":"lu'shen'jing'sun'hai"},{"word":"颅神经炎","pinyin":"lu'shen'jing'yan"},{"word":"卵巢病","pinyin":"luan'chao'bing"},{"word":"卵巢囊肿","pinyin":"luan'chao'nang'zhong"},{"word":"滤疱性疹","pinyin":"lv'pao'xing'zhen"},{"word":"麻痹","pinyin":"ma'bi"},{"word":"麻痹性肠梗阻","pinyin":"ma'bi'xing'chang'geng'zu"},{"word":"脉管炎","pinyin":"mai'guan'yan"},{"word":"脉弱","pinyin":"mai'ruo"},{"word":"慢性疲劳综合征","pinyin":"man'xing'pi'lao'zong'he'zheng"},{"word":"盲点","pinyin":"mang'dian"},{"word":"毛发变色","pinyin":"mao'fa'bian'se"},{"word":"毛发结构异常","pinyin":"mao'fa'jie'gou'yi'chang"},{"word":"毛发稀少症","pinyin":"mao'fa'xi'shao'zheng"},{"word":"毛囊炎","pinyin":"mao'nang'yan"},{"word":"毛细血管脆性增加","pinyin":"mao'xi'xue'guan'cui'xing'zeng'jia"},{"word":"毛细血管扩张","pinyin":"mao'xi'xue'guan'kuo'zhang"},{"word":"梅毒试验假阳性","pinyin":"mei'du'shi'yan'jia'yang'xing"},{"word":"酶活性异常","pinyin":"mei'huo'xing'yi'chang"},{"word":"霉菌性皮炎","pinyin":"mei'jun'xing'pi'yan"},{"word":"门静脉高压","pinyin":"men'jing'mai'gao'ya"},{"word":"梦行","pinyin":"meng'xing"},{"word":"弥漫性血管内凝血","pinyin":"mi'man'xing'xue'guan'nei'ning'xue"},{"word":"泌尿道疾病","pinyin":"mi'niao'dao'ji'bing"},{"word":"泌尿生殖器畸形","pinyin":"mi'niao'sheng'zhi'qi'ji'xing"},{"word":"面部畸形","pinyin":"mian'bu'ji'xing"},{"word":"面部水肿","pinyin":"mian'bu'shui'zhong"},{"word":"免疫球蛋白减少","pinyin":"mian'yi'qiu'dan'bai'jian'shao"},{"word":"免疫球蛋白增加","pinyin":"mian'yi'qiu'dan'bai'zeng'jia"},{"word":"免疫系统疾病","pinyin":"mian'yi'xi'tong'ji'bing"},{"word":"免疫阳性","pinyin":"mian'yi'yang'xing"},{"word":"末梢神经病","pinyin":"mo'shao'shen'jing'bing"},{"word":"末梢水肿","pinyin":"mo'shao'shui'zhong"},{"word":"磨牙","pinyin":"mo'ya"},{"word":"木僵","pinyin":"mu'jiang"},{"word":"耐受性降低","pinyin":"nai'shou'xing'jiang'di"},{"word":"耐受性增加","pinyin":"nai'shou'xing'zeng'jia"},{"word":"耐药","pinyin":"nai'yao"},{"word":"男性不育","pinyin":"nan'xing'bu'yu"},{"word":"男性会阴痛","pinyin":"nan'xing'hui'yin'tong"},{"word":"男性泌乳","pinyin":"nan'xing'mi'ru"},{"word":"男性女性化","pinyin":"nan'xing'nv'xing'hua"},{"word":"男性乳房恶性瘤","pinyin":"nan'xing'ru'fang'e'xing'liu"},{"word":"男性乳房瘤","pinyin":"nan'xing'ru'fang'liu"},{"word":"男性乳房痛","pinyin":"nan'xing'ru'fang'tong"},{"word":"男性乳腺炎","pinyin":"nan'xing'ru'xian'yan"},{"word":"男性生育力降低","pinyin":"nan'xing'sheng'yu'li'jiang'di"},{"word":"男性生殖器皮疹","pinyin":"nan'xing'sheng'zhi'qi'pi'zhen"},{"word":"男性生殖器骚痒","pinyin":"nan'xing'sheng'zhi'qi'sao'yang"},{"word":"男性诱变效应","pinyin":"nan'xing'you'bian'xiao'ying"},{"word":"男子女性型乳房","pinyin":"nan'zi'nv'xing'xing'ru'fang"},{"word":"囊下内障","pinyin":"nang'xia'nei'zhang"},{"word":"囊性纤维化","pinyin":"nang'xing'xian'wei'hua"},{"word":"囊样斑点水肿","pinyin":"nang'yang'ban'dian'shui'zhong"},{"word":"脑病","pinyin":"nao'bing"},{"word":"脑出血","pinyin":"nao'chu'xue"},{"word":"脑电图异常","pinyin":"nao'dian'tu'yi'chang"},{"word":"脑动脉血栓形成","pinyin":"nao'dong'mai'xue'shuan'xing'cheng"},{"word":"脑干病","pinyin":"nao'gan'bing"},{"word":"脑梗死","pinyin":"nao'geng'si"},{"word":"脑积水","pinyin":"nao'ji'shui"},{"word":"脑脊髓炎","pinyin":"nao'ji'sui'yan"},{"word":"脑脊髓液细胞增多","pinyin":"nao'ji'sui'ye'xi'bao'zeng'duo"},{"word":"脑脊液异常","pinyin":"nao'ji'ye'yi'chang"},{"word":"脑静脉血栓性静脉炎","pinyin":"nao'jing'mai'xue'shuan'xing'jing'mai'yan"},{"word":"脑磷脂絮状试验异常","pinyin":"nao'lin'zhi'xu'zhuang'shi'yan'yi'chang"},{"word":"脑膜脑炎","pinyin":"nao'mo'nao'yan"},{"word":"脑膜炎","pinyin":"nao'mo'yan"},{"word":"脑膨出","pinyin":"nao'peng'chu"},{"word":"脑缺氧","pinyin":"nao'que'yang"},{"word":"脑栓塞","pinyin":"nao'shuan'sai"},{"word":"脑水肿","pinyin":"nao'shui'zhong"},{"word":"脑萎缩","pinyin":"nao'wei'suo"},{"word":"脑血管病","pinyin":"nao'xue'guan'bing"},{"word":"脑血管意外未特指","pinyin":"nao'xue'guan'yi'wai'wei'te'zhi"},{"word":"脑血栓形成","pinyin":"nao'xue'shuan'xing'cheng"},{"word":"脑肿瘤","pinyin":"nao'zhong'liu"},{"word":"内分泌失调","pinyin":"nei'fen'mi'shi'tiao"},{"word":"粘膜白斑病","pinyin":"nian'mo'bai'ban'bing"},{"word":"粘膜疹","pinyin":"nian'mo'zhen"},{"word":"粘液性水肿","pinyin":"nian'ye'xing'shui'zhong"},{"word":"念珠菌病","pinyin":"nian'zhu'jun'bing"},{"word":"尿崩","pinyin":"niao'beng"},{"word":"尿道病","pinyin":"niao'dao'bing"},{"word":"尿道感染","pinyin":"niao'dao'gan'ran"},{"word":"尿道畸形","pinyin":"niao'dao'ji'xing"},{"word":"尿道下裂","pinyin":"niao'dao'xia'lie"},{"word":"尿毒症","pinyin":"niao'du'zheng"},{"word":"尿毒症昏迷","pinyin":"niao'du'zheng'hun'mi"},{"word":"尿急","pinyin":"niao'ji"},{"word":"尿频","pinyin":"niao'pin"},{"word":"尿失禁","pinyin":"niao'shi'jin"},{"word":"尿素减少","pinyin":"niao'su'jian'shao"},{"word":"尿痛","pinyin":"niao'tong"},{"word":"尿异常","pinyin":"niao'yi'chang"},{"word":"尿潴留","pinyin":"niao'zhu'liu"},{"word":"凝血功能障碍","pinyin":"ning'xue'gong'neng'zhang'ai"},{"word":"凝血酶原减少","pinyin":"ning'xue'mei'yuan'jian'shao"},{"word":"凝血酶原增加","pinyin":"ning'xue'mei'yuan'zeng'jia"},{"word":"凝血时间缩短","pinyin":"ning'xue'shi'jian'suo'duan"},{"word":"凝血时间延长","pinyin":"ning'xue'shi'jian'yan'chang"},{"word":"凝血因子减少","pinyin":"ning'xue'yin'zi'jian'shao"},{"word":"凝血因子增加","pinyin":"ning'xue'yin'zi'zeng'jia"},{"word":"凝血障碍","pinyin":"ning'xue'zhang'ai"},{"word":"牛痘反应加重","pinyin":"niu'dou'fan'ying'jia'zhong"},{"word":"脓毒病","pinyin":"nong'du'bing"},{"word":"脓尿","pinyin":"nong'niao"},{"word":"脓疱性疹","pinyin":"nong'pao'xing'zhen"},{"word":"脓肿","pinyin":"nong'zhong"},{"word":"暖气","pinyin":"nuan'qi"},{"word":"女性不育","pinyin":"nv'xing'bu'yu"},{"word":"女性会阴痛","pinyin":"nv'xing'hui'yin'tong"},{"word":"女性男性化","pinyin":"nv'xing'nan'xing'hua"},{"word":"女性乳房恶性瘤","pinyin":"nv'xing'ru'fang'e'xing'liu"},{"word":"女性乳房良性瘤","pinyin":"nv'xing'ru'fang'liang'xing'liu"},{"word":"女性乳房瘤","pinyin":"nv'xing'ru'fang'liu"},{"word":"女性乳房痛","pinyin":"nv'xing'ru'fang'tong"},{"word":"女性生育力降低","pinyin":"nv'xing'sheng'yu'li'jiang'di"},{"word":"女性生殖器病","pinyin":"nv'xing'sheng'zhi'qi'bing"},{"word":"女性性快感缺失","pinyin":"nv'xing'xing'kuai'gan'que'shi"},{"word":"女性诱变效应","pinyin":"nv'xing'you'bian'xiao'ying"},{"word":"呕吐","pinyin":"ou'tu"},{"word":"呕血","pinyin":"ou'xue"},{"word":"帕金森症加重","pinyin":"pa'jin'sen'zheng'jia'zhong"},{"word":"帕金森综合征","pinyin":"pa'jin'sen'zong'he'zheng"},{"word":"排尿困难","pinyin":"pai'niao'kun'nan"},{"word":"排尿障碍","pinyin":"pai'niao'zhang'ai"},{"word":"膀胱癌","pinyin":"pang'guang'ai"},{"word":"膀胱畸形","pinyin":"pang'guang'ji'xing"},{"word":"膀胱结石","pinyin":"pang'guang'jie'shi"},{"word":"膀胱乳头瘤","pinyin":"pang'guang'ru'tou'liu"},{"word":"膀胱脱垂","pinyin":"pang'guang'tuo'chui"},{"word":"膀胱炎","pinyin":"pang'guang'yan"},{"word":"盆腔炎","pinyin":"pen'qiang'yan"},{"word":"脾病","pinyin":"pi'bing"},{"word":"皮肤变色","pinyin":"pi'fu'bian'se"},{"word":"皮肤病","pinyin":"pi'fu'bing"},{"word":"皮肤肥厚","pinyin":"pi'fu'fei'hou"},{"word":"皮肤干燥","pinyin":"pi'fu'gan'zao"},{"word":"皮肤划纹症","pinyin":"pi'fu'hua'wen'zheng"},{"word":"皮肤坏死","pinyin":"pi'fu'huai'si"},{"word":"皮肤畸形","pinyin":"pi'fu'ji'xing"},{"word":"皮肤结节","pinyin":"pi'fu'jie'jie"},{"word":"皮肤溃疡","pinyin":"pi'fu'kui'yang"},{"word":"皮肤粘膜淋巴结节","pinyin":"pi'fu'nian'mo'lin'ba'jie'jie"},{"word":"皮肤气味异常","pinyin":"pi'fu'qi'wei'yi'chang"},{"word":"皮肤色素减退","pinyin":"pi'fu'se'su'jian'tui"},{"word":"皮肤湿冷","pinyin":"pi'fu'shi'leng"},{"word":"皮肤脱落","pinyin":"pi'fu'tuo'luo"},{"word":"皮肤萎缩","pinyin":"pi'fu'wei'suo"},{"word":"皮肤纹理异常","pinyin":"pi'fu'wen'li'yi'chang"},{"word":"皮肤营养不良","pinyin":"pi'fu'ying'yang'bu'liang"},{"word":"皮肤再生不良","pinyin":"pi'fu'zai'sheng'bu'liang"},{"word":"疲劳","pinyin":"pi'lao"},{"word":"皮炎","pinyin":"pi'yan"},{"word":"皮样囊肿","pinyin":"pi'yang'nang'zhong"},{"word":"皮疹","pinyin":"pi'zhen"},{"word":"皮质醇降低","pinyin":"pi'zhi'chun'jiang'di"},{"word":"皮质醇增加","pinyin":"pi'zhi'chun'zeng'jia"},{"word":"皮质盲","pinyin":"pi'zhi'mang"},{"word":"皮脂溢","pinyin":"pi'zhi'yi"},{"word":"脾肿大","pinyin":"pi'zhong'da"},{"word":"偏侧肥大","pinyin":"pian'ce'fei'da"},{"word":"偏盲","pinyin":"pian'mang"},{"word":"偏瘫","pinyin":"pian'tan"},{"word":"偏头痛","pinyin":"pian'tou'tong"},{"word":"偏头痛加重","pinyin":"pian'tou'tong'jia'zhong"},{"word":"偏执狂反应","pinyin":"pian'zhi'kuang'fan'ying"},{"word":"贫血","pinyin":"pin'xue"},{"word":"贫血未特指","pinyin":"pin'xue'wei'te'zhi"},{"word":"剖腹生产术","pinyin":"pou'fu'sheng'chan'shu"},{"word":"葡萄膜炎","pinyin":"pu'tao'mo'yan"},{"word":"葡萄球菌感染","pinyin":"pu'tao'qiu'jun'gan'ran"},{"word":"葡萄胎","pinyin":"pu'tao'tai"},{"word":"脐带异常","pinyin":"qi'dai'yi'chang"},{"word":"脐畸形","pinyin":"qi'ji'xing"},{"word":"脐疝","pinyin":"qi'shan"},{"word":"憩室","pinyin":"qi'shi"},{"word":"憩室病","pinyin":"qi'shi'bing"},{"word":"期外收缩","pinyin":"qi'wai'shou'suo"},{"word":"气胸","pinyin":"qi'xiong"},{"word":"浅表血栓性静脉炎","pinyin":"qian'biao'xue'shuan'xing'jing'mai'yan"},{"word":"前房出血","pinyin":"qian'fang'chu'xie"},{"word":"嵌甲","pinyin":"qian'jia"},{"word":"浅静脉炎","pinyin":"qian'jing'mai'yan"},{"word":"前列腺病加重","pinyin":"qian'lie'xian'bing'jia'zhong"},{"word":"前列腺增生","pinyin":"qian'lie'xian'zeng'sheng"},{"word":"前庭病","pinyin":"qian'ting'bing"},{"word":"腔静脉血栓性静脉炎","pinyin":"qiang'jing'mai'xue'shuan'xing'jing'mai'yan"},{"word":"切断术","pinyin":"qie'duan'shu"},{"word":"青春期早熟","pinyin":"qing'chun'qi'zao'shu"},{"word":"轻度偏瘫","pinyin":"qing'du'pian'tan"},{"word":"青光眼","pinyin":"qing'guang'yan"},{"word":"轻瘫","pinyin":"qing'tan"},{"word":"情绪不稳定","pinyin":"qing'xu'bu'wen'ding"},{"word":"球蛋白增加","pinyin":"qiu'dan'bai'zeng'jia"},{"word":"球红细胞性贫血","pinyin":"qiu'hong'xi'bao'xing'pin'xue"},{"word":"球后视神经炎","pinyin":"qiu'hou'shi'shen'jing'yan"},{"word":"丘斯综合征","pinyin":"qiu'si'zong'he'zheng"},{"word":"龋齿","pinyin":"qu'chi"},{"word":"龋齿加重","pinyin":"qu'chi'jia'zhong"},{"word":"醛固酮增加","pinyin":"quan'gu'tong'zeng'jia"},{"word":"全身性水肿","pinyin":"quan'shen'xing'shui'zhong"},{"word":"全血细胞减少","pinyin":"quan'xue'xi'bao'jian'shao"},{"word":"缺铁性贫血","pinyin":"que'tie'xing'pin'xue"},{"word":"缺血性坏死","pinyin":"que'xue'xing'huai'si"},{"word":"缺氧","pinyin":"que'yang"},{"word":"染色体损害","pinyin":"ran'se'ti'sun'hai"},{"word":"热潮红","pinyin":"re'chao'hong"},{"word":"热惊厥","pinyin":"re'jing'jue"},{"word":"人格解体","pinyin":"ren'ge'jie'ti"},{"word":"人格障碍","pinyin":"ren'ge'zhang'ai"},{"word":"人免疫缺陷病毒试验阳性","pinyin":"ren'mian'yi'que'xian'bing'du'shi'yan'yang'xing"},{"word":"妊娠出血","pinyin":"ren'shen'chu'xie"},{"word":"妊娠疱疹","pinyin":"ren'shen'pao'zhen"},{"word":"妊娠试验假阳性","pinyin":"ren'shen'shi'yan'jia'yang'xing"},{"word":"认识病","pinyin":"ren'shi'bing"},{"word":"绒膜羊膜炎","pinyin":"rong'mo'yang'mo'yan"},{"word":"溶血","pinyin":"rong'xue"},{"word":"溶血性黄疸","pinyin":"rong'xue'xing'huang'dan"},{"word":"溶血性贫血","pinyin":"rong'xue'xing'pin'xue"},{"word":"肉瘤","pinyin":"rou'liu"},{"word":"肉瘤样病","pinyin":"rou'liu'yang'bing"},{"word":"肉芽肿损害","pinyin":"rou'ya'zhong'sun'hai"},{"word":"褥疮溃疡","pinyin":"ru'chuang'kui'yang"},{"word":"乳房充血","pinyin":"ru'fang'chong'xue"},{"word":"乳房畸形","pinyin":"ru'fang'ji'xing"},{"word":"乳房痛","pinyin":"ru'fang'tong"},{"word":"乳房萎缩","pinyin":"ru'fang'wei'suo"},{"word":"乳房增生","pinyin":"ru'fang'zeng'sheng"},{"word":"乳房胀大","pinyin":"ru'fang'zhang'da"},{"word":"乳酸脱氢酶增加","pinyin":"ru'suan'tuo'qing'mei'zeng'jia"},{"word":"乳酸性酸中毒","pinyin":"ru'suan'xing'suan'zhong'du"},{"word":"乳头溃疡","pinyin":"ru'tou'kui'yang"},{"word":"乳腺炎","pinyin":"ru'xian'yan"},{"word":"乳腺增生","pinyin":"ru'xian'zeng'sheng"},{"word":"乳溢","pinyin":"ru'yi"},{"word":"软骨营养不良","pinyin":"ruan'gu'ying'yang'bu'liang"},{"word":"三叉神经痛","pinyin":"san'cha'shen'jing'tong"},{"word":"瘙痒","pinyin":"sao'yang"},{"word":"骚痒","pinyin":"sao'yang"},{"word":"色盲","pinyin":"se'mang"},{"word":"色视症","pinyin":"se'shi'zheng"},{"word":"色素沉着","pinyin":"se'su'chen'zhuo"},{"word":"闪光幻觉","pinyin":"shan'guang'huan'jue"},{"word":"上呼吸道感染","pinyin":"shang'hu'xi'dao'gan'ran"},{"word":"上睑下垂","pinyin":"shang'jian'xia'chui"},{"word":"伤口感染","pinyin":"shang'kou'gan'ran"},{"word":"上运动神经原损害","pinyin":"shang'yun'dong'shen'jing'yuan'sun'hai"},{"word":"少尿","pinyin":"shao'niao"},{"word":"少尿症","pinyin":"shao'niao'zheng"},{"word":"舌变色","pinyin":"she'bian'se"},{"word":"舌病","pinyin":"she'bing"},{"word":"射精不能","pinyin":"she'jing'bu'neng"},{"word":"射精障碍","pinyin":"she'jing'zhang'ai"},{"word":"舌溃疡","pinyin":"she'kui'yang"},{"word":"舌麻痹","pinyin":"she'ma'bi"},{"word":"舌水肿","pinyin":"she'shui'zhong"},{"word":"麝香草酚浊度试验异常","pinyin":"she'xiang'cao'fen'zhuo'du'shi'yan'yi'chang"},{"word":"舌炎","pinyin":"she'yan"},{"word":"肾癌","pinyin":"shen'ai"},{"word":"肾病","pinyin":"shen'bing"},{"word":"渗出性红斑","pinyin":"shen'chu'xing'hong'ban"},{"word":"肾动脉硬化","pinyin":"shen'dong'mai'ying'hua"},{"word":"肾发育不全","pinyin":"shen'fa'yu'bu'quan"},{"word":"肾功能不全","pinyin":"shen'gong'neng'bu'quan"},{"word":"肾功能异常","pinyin":"shen'gong'neng'yi'chang"},{"word":"肾积水","pinyin":"shen'ji'shui"},{"word":"肾间质纤维化","pinyin":"shen'jian'zhi'xian'wei'hua"},{"word":"肾结石","pinyin":"shen'jie'shi"},{"word":"神经病","pinyin":"shen'jing'bing"},{"word":"神经根损害","pinyin":"shen'jing'gen'sun'hai"},{"word":"神经官能症","pinyin":"shen'jing'guan'neng'zheng"},{"word":"神经过敏","pinyin":"shen'jing'guo'min"},{"word":"神经瘤","pinyin":"shen'jing'liu"},{"word":"深静脉炎","pinyin":"shen'jing'mai'yan"},{"word":"神经痛","pinyin":"shen'jing'tong"},{"word":"神经细胞瘤","pinyin":"shen'jing'xi'bao'liu"},{"word":"神经纤维瘤加重","pinyin":"shen'jing'xian'wei'liu'jia'zhong"},{"word":"神经性耳聋","pinyin":"shen'jing'xing'er'long"},{"word":"神经性贪食","pinyin":"shen'jing'xing'tan'shi"},{"word":"神经性厌食","pinyin":"shen'jing'xing'yan'shi"},{"word":"神经炎","pinyin":"shen'jing'yan"},{"word":"神经抑制药恶性综合征","pinyin":"shen'jing'yi'zhi'yao'e'xing'zong'he'zheng"},{"word":"肾挛缩","pinyin":"shen'luan'suo"},{"word":"肾囊肿","pinyin":"shen'nang'zhong"},{"word":"肾脓肿","pinyin":"shen'nong'zhong"},{"word":"肾皮质坏死","pinyin":"shen'pi'zhi'huai'si"},{"word":"肾乳头坏死","pinyin":"shen'ru'tou'huai'si"},{"word":"肾上腺出血","pinyin":"shen'shang'xian'chu'xie"},{"word":"肾上腺功能减退","pinyin":"shen'shang'xian'gong'neng'jian'tui"},{"word":"肾上腺皮质功能减退","pinyin":"shen'shang'xian'pi'zhi'gong'neng'jian'tui"},{"word":"肾上腺皮质功能亢进","pinyin":"shen'shang'xian'pi'zhi'gong'neng'kang'jin"},{"word":"肾痛","pinyin":"shen'tong"},{"word":"肾小管病","pinyin":"shen'xiao'guan'bing"},{"word":"肾小管坏死","pinyin":"shen'xiao'guan'huai'si"},{"word":"肾小球功能异常","pinyin":"shen'xiao'qiu'gong'neng'yi'chang"},{"word":"肾小球肾炎","pinyin":"shen'xiao'qiu'shen'yan"},{"word":"肾性尿崩症","pinyin":"shen'xing'niao'beng'zheng"},{"word":"深血栓性静脉炎","pinyin":"shen'xue'shuan'xing'jing'mai'yan"},{"word":"肾炎","pinyin":"shen'yan"},{"word":"肾移植","pinyin":"shen'yi'zhi"},{"word":"肾硬化","pinyin":"shen'ying'hua"},{"word":"肾盂肾炎","pinyin":"shen'yu'shen'yan"},{"word":"肾胀大","pinyin":"shen'zhang'da"},{"word":"声带麻痹","pinyin":"sheng'dai'ma'bi"},{"word":"生长迟缓","pinyin":"sheng'zhang'chi'huan"},{"word":"生长加速","pinyin":"sheng'zhang'jia'su"},{"word":"生殖器畸形","pinyin":"sheng'zhi'qi'ji'xing"},{"word":"生殖器溃疡","pinyin":"sheng'zhi'qi'kui'yang"},{"word":"生殖器念珠菌病","pinyin":"sheng'zhi'qi'nian'zhu'jun'bing"},{"word":"生殖器骚痒","pinyin":"sheng'zhi'qi'sao'yang"},{"word":"生殖器水肿","pinyin":"sheng'zhi'qi'shui'zhong"},{"word":"室颤","pinyin":"shi'chan"},{"word":"食道病","pinyin":"shi'dao'bing"},{"word":"十二指肠闭锁","pinyin":"shi'er'zhi'chang'bi'suo"},{"word":"十二指肠溃疡","pinyin":"shi'er'zhi'chang'kui'yang"},{"word":"十二指肠溃疡出血","pinyin":"shi'er'zhi'chang'kui'yang'chu'xie"},{"word":"十二指肠溃疡穿孔","pinyin":"shi'er'zhi'chang'kui'yang'chuan'kong"},{"word":"十二指肠溃疡复发","pinyin":"shi'er'zhi'chang'kui'yang'fu'fa"},{"word":"十二指肠炎","pinyin":"shi'er'zhi'chang'yan"},{"word":"嗜铬细胞瘤","pinyin":"shi'ge'xi'bao'liu"},{"word":"食管癌","pinyin":"shi'guan'ai"},{"word":"食管闭锁","pinyin":"shi'guan'bi'suo"},{"word":"食管穿孔","pinyin":"shi'guan'chuan'kong"},{"word":"食管痉挛","pinyin":"shi'guan'jing'luan"},{"word":"食管静脉曲张","pinyin":"shi'guan'jing'mai'qu'zhang"},{"word":"食管溃疡","pinyin":"shi'guan'kui'yang"},{"word":"食管溃疡出血","pinyin":"shi'guan'kui'yang'chu'xie"},{"word":"食管狭窄","pinyin":"shi'guan'xia'zhai"},{"word":"食管炎","pinyin":"shi'guan'yan"},{"word":"室间隔缺损","pinyin":"shi'jian'ge'que'sun"},{"word":"嗜碱细胞增多","pinyin":"shi'jian'xi'bao'zeng'duo"},{"word":"视觉异常","pinyin":"shi'jue'yi'chang"},{"word":"视力模糊","pinyin":"shi'li'mo'hu"},{"word":"失眠","pinyin":"shi'mian"},{"word":"失明","pinyin":"shi'ming"},{"word":"视乳头水肿","pinyin":"shi'ru'tou'shui'zhong"},{"word":"室上性期外收缩","pinyin":"shi'shang'xing'qi'wai'shou'suo"},{"word":"室上性心动过速","pinyin":"shi'shang'xing'xin'dong'guo'su"},{"word":"失神","pinyin":"shi'shen"},{"word":"视神经乳头水肿","pinyin":"shi'shen'jing'ru'tou'shui'zhong"},{"word":"视神经萎缩","pinyin":"shi'shen'jing'wei'suo"},{"word":"视神经炎","pinyin":"shi'shen'jing'yan"},{"word":"嗜睡","pinyin":"shi'shui"},{"word":"嗜酸性肉芽肿","pinyin":"shi'suan'xing'rou'ya'zhong"},{"word":"嗜酸性细胞肺炎","pinyin":"shi'suan'xing'xi'bao'fei'yan"},{"word":"嗜酸性细胞增多症","pinyin":"shi'suan'xing'xi'bao'zeng'duo'zheng"},{"word":"视网膜病","pinyin":"shi'wang'mo'bing"},{"word":"视网膜沉淀","pinyin":"shi'wang'mo'chen'dian"},{"word":"视网膜出血","pinyin":"shi'wang'mo'chu'xie"},{"word":"视网膜动脉血栓形成","pinyin":"shi'wang'mo'dong'mai'xue'shuan'xing'cheng"},{"word":"视网膜分离","pinyin":"shi'wang'mo'fen'li"},{"word":"视网膜静脉血栓形成","pinyin":"shi'wang'mo'jing'mai'xue'shuan'xing'cheng"},{"word":"视网膜水肿","pinyin":"shi'wang'mo'shui'zhong"},{"word":"视网膜脱落","pinyin":"shi'wang'mo'tuo'luo"},{"word":"视网膜炎","pinyin":"shi'wang'mo'yan"},{"word":"室性期前收缩","pinyin":"shi'xing'qi'qian'shou'suo"},{"word":"室性心动过速","pinyin":"shi'xing'xin'dong'guo'su"},{"word":"室性心律失常","pinyin":"shi'xing'xin'lv'shi'chang"},{"word":"视野缺损","pinyin":"shi'ye'que'sun"},{"word":"食欲亢进","pinyin":"shi'yu'kang'jin"},{"word":"食欲缺乏","pinyin":"shi'yu'que'fa"},{"word":"失语症","pinyin":"shi'yu'zheng"},{"word":"湿疹","pinyin":"shi'zhen"},{"word":"手指畸形","pinyin":"shou'zhi'ji'xing"},{"word":"输卵管炎","pinyin":"shu'luan'guan'yan"},{"word":"舒缩间期过长","pinyin":"shu'suo'jian'qi'guo'chang"},{"word":"束支传导阻滞","pinyin":"shu'zhi'chuan'dao'zu'zhi"},{"word":"睡眠障碍","pinyin":"shui'mian'zhang'ai"},{"word":"水疱疹","pinyin":"shui'pao'zhen"},{"word":"水肿","pinyin":"shui'zhong"},{"word":"死产","pinyin":"si'chan"},{"word":"撕裂","pinyin":"si'lie"},{"word":"死胎","pinyin":"si'tai"},{"word":"死亡","pinyin":"si'wang"},{"word":"思维异常","pinyin":"si'wei'yi'chang"},{"word":"四肢麻痹","pinyin":"si'zhi'ma'bi"},{"word":"酸性磷酸酶升高","pinyin":"suan'xing'lin'suan'mei'sheng'gao"},{"word":"酸中毒","pinyin":"suan'zhong'du"},{"word":"梭状芽孢杆菌感染","pinyin":"suo'zhuang'ya'bao'gan'jun'gan'ran"},{"word":"胎儿发育不良","pinyin":"tai'er'fa'yu'bu'liang"},{"word":"胎儿过大","pinyin":"tai'er'guo'da"},{"word":"胎儿过小","pinyin":"tai'er'guo'xiao"},{"word":"胎儿窘迫","pinyin":"tai'er'jiong'po"},{"word":"胎儿女性男性化","pinyin":"tai'er'nv'xing'nan'xing'hua"},{"word":"胎儿全脑垂体功能不足","pinyin":"tai'er'quan'nao'chui'ti'gong'neng'bu'zu"},{"word":"胎儿水肿","pinyin":"tai'er'shui'zhong"},{"word":"胎儿心搏徐缓","pinyin":"tai'er'xin'bo'xu'huan"},{"word":"胎儿心律失常","pinyin":"tai'er'xin'lv'shi'chang"},{"word":"胎粪增加","pinyin":"tai'fen'zeng'jia"},{"word":"胎盘病","pinyin":"tai'pan'bing"},{"word":"苔癣样皮炎","pinyin":"tai'xuan'yang'pi'yan"},{"word":"痰病","pinyin":"tan'bing"},{"word":"痰量增多","pinyin":"tan'liang'zeng'duo"},{"word":"糖耐量异常","pinyin":"tang'nai'liang'yi'chang"},{"word":"糖尿","pinyin":"tang'niao"},{"word":"糖尿病","pinyin":"tang'niao'bing"},{"word":"糖尿病复发","pinyin":"tang'niao'bing'fu'fa"},{"word":"糖尿病昏迷","pinyin":"tang'niao'bing'hun'mi"},{"word":"糖尿病加重","pinyin":"tang'niao'bing'jia'zhong"},{"word":"糖尿病性溃疡","pinyin":"tang'niao'bing'xing'kui'yang"},{"word":"糖皮质激素增加","pinyin":"tang'pi'zhi'ji'su'zeng'jia"},{"word":"特异性心电图异常","pinyin":"te'yi'xing'xin'dian'tu'yi'chang"},{"word":"疼痛","pinyin":"teng'tong"},{"word":"体臭","pinyin":"ti'chou"},{"word":"体位性低血压","pinyin":"ti'wei'xing'di'xue'ya"},{"word":"体位异常","pinyin":"ti'wei'yi'chang"},{"word":"体温过低","pinyin":"ti'wen'guo'di"},{"word":"体重减少","pinyin":"ti'zhong'jian'shao"},{"word":"体重降低","pinyin":"ti'zhong'jiang'di"},{"word":"体重增加","pinyin":"ti'zhong'zeng'jia"},{"word":"天疱疮样反应","pinyin":"tian'pao'chuang'yang'fan'ying"},{"word":"调节异常","pinyin":"tiao'jie'yi'chang"},{"word":"铁代谢障碍","pinyin":"tie'dai'xie'zhang'ai"},{"word":"铁粒幼红细胞性贫血","pinyin":"tie'li'you'hong'xi'bao'xing'pin'xue"},{"word":"铁粒幼细胞贫血","pinyin":"tie'li'you'xi'bao'pin'xue"},{"word":"铁质沉着出血","pinyin":"tie'zhi'chen'zhuo'chu'xie"},{"word":"听觉过敏","pinyin":"ting'jue'guo'min"},{"word":"听力降低","pinyin":"ting'li'jiang'di"},{"word":"听力损害","pinyin":"ting'li'sun'hai"},{"word":"听力损伤","pinyin":"ting'li'sun'shang"},{"word":"酮病","pinyin":"tong'bing"},{"word":"痛风","pinyin":"tong'feng"},{"word":"痛经","pinyin":"tong'jing"},{"word":"瞳孔不等","pinyin":"tong'kong'bu'deng"},{"word":"瞳孔反射削弱","pinyin":"tong'kong'fan'she'xue'ruo"},{"word":"瞳孔散大","pinyin":"tong'kong'san'da"},{"word":"瞳孔缩小","pinyin":"tong'kong'suo'xiao"},{"word":"痛性肥胖症","pinyin":"tong'xing'fei'pang'zheng"},{"word":"痛性尿沥","pinyin":"tong'xing'niao'li"},{"word":"头发稀疏","pinyin":"tou'fa'xi'shu"},{"word":"头颅畸形","pinyin":"tou'lu'ji'xing"},{"word":"头痛","pinyin":"tou'tong"},{"word":"头晕","pinyin":"tou'yun"},{"word":"突眼","pinyin":"tu'yan"},{"word":"腿动脉血栓形成","pinyin":"tui'dong'mai'xue'shuan'xing'cheng"},{"word":"退膜性子宫内膜炎","pinyin":"tui'mo'xing'zi'gong'nei'mo'yan"},{"word":"腿浅血栓性静脉炎","pinyin":"tui'qian'xue'shuan'xing'jing'mai'yan"},{"word":"腿深血栓性静脉炎","pinyin":"tui'shen'xue'shuan'xing'jing'mai'yan"},{"word":"腿血栓性静脉炎","pinyin":"tui'xue'shuan'xing'jing'mai'yan"},{"word":"吞咽困难","pinyin":"tun'yan'kun'nan"},{"word":"脱发","pinyin":"tuo'fa"},{"word":"脱水","pinyin":"tuo'shui"},{"word":"唾液管梗阻","pinyin":"tuo'ye'guan'geng'zu"},{"word":"唾液腺痛","pinyin":"tuo'ye'xian'tong"},{"word":"唾液腺胀大","pinyin":"tuo'ye'xian'zhang'da"},{"word":"唾液异常","pinyin":"tuo'ye'yi'chang"},{"word":"唾液增加","pinyin":"tuo'ye'zeng'jia"},{"word":"外耳炎","pinyin":"wai'er'yan"},{"word":"外生殖器不明","pinyin":"wai'sheng'zhi'qi'bu'ming"},{"word":"外阴干燥","pinyin":"wai'yin'gan'zao"},{"word":"外周坏疽","pinyin":"wai'zhou'huai'ju"},{"word":"外周局部性缺血","pinyin":"wai'zhou'ju'bu'xing'que'xue"},{"word":"外周神经损害","pinyin":"wai'zhou'shen'jing'sun'hai"},{"word":"腕管综合征","pinyin":"wan'guan'zong'he'zheng"},{"word":"完全性房室传导阻滞","pinyin":"wan'quan'xing'fang'shi'chuan'dao'zu'zhi"},{"word":"妄想","pinyin":"wang'xiang"},{"word":"网状青斑","pinyin":"wang'zhuang'qing'ban"},{"word":"网状细胞增多","pinyin":"wang'zhuang'xi'bao'zeng'duo"},{"word":"胃癌","pinyin":"wei'ai"},{"word":"胃肠道出血","pinyin":"wei'chang'dao'chu'xie"},{"word":"胃肠道恶性肿瘤","pinyin":"wei'chang'dao'e'xing'zhong'liu"},{"word":"胃肠道畸形","pinyin":"wei'chang'dao'ji'xing"},{"word":"胃肠道粘膜变色","pinyin":"wei'chang'dao'nian'mo'bian'se"},{"word":"胃肠道粘膜广泛性坏死","pinyin":"wei'chang'dao'nian'mo'guang'fan'xing'huai'si"},{"word":"胃肠道念珠菌病","pinyin":"wei'chang'dao'nian'zhu'jun'bing"},{"word":"胃肠炎","pinyin":"wei'chang'yan"},{"word":"胃肠胀气","pinyin":"wei'chang'zhang'qi"},{"word":"胃穿孔","pinyin":"wei'chuan'kong"},{"word":"胃腹部不适","pinyin":"wei'fu'bu'bu'shi"},{"word":"胃功能紊乱","pinyin":"wei'gong'neng'wen'luan"},{"word":"畏光","pinyin":"wei'guang"},{"word":"胃痉挛","pinyin":"wei'jing'luan"},{"word":"味觉倒错","pinyin":"wei'jue'dao'cuo"},{"word":"味觉丧失","pinyin":"wei'jue'sang'shi"},{"word":"胃溃疡","pinyin":"wei'kui'yang"},{"word":"胃溃疡出血","pinyin":"wei'kui'yang'chu'xie"},{"word":"胃溃疡穿孔","pinyin":"wei'kui'yang'chuan'kong"},{"word":"胃扩张","pinyin":"wei'kuo'zhang"},{"word":"伪膜性肠炎","pinyin":"wei'mo'xing'chang'yan"},{"word":"伪膜性结肠炎","pinyin":"wei'mo'xing'jie'chang'yan"},{"word":"维生素缺少","pinyin":"wei'sheng'su'que'shao"},{"word":"胃食管返流","pinyin":"wei'shi'guan'fan'liu"},{"word":"胃酸过多","pinyin":"wei'suan'guo'duo"},{"word":"胃酸过少症","pinyin":"wei'suan'guo'shao'zheng"},{"word":"萎缩性阴道炎","pinyin":"wei'suo'xing'yin'dao'yan"},{"word":"胃痛","pinyin":"wei'tong"},{"word":"胃炎","pinyin":"wei'yan"},{"word":"胃灼热","pinyin":"wei'zhuo're"},{"word":"舞蹈手足徐动症","pinyin":"wu'dao'shou'zu'xu'dong'zheng"},{"word":"无力","pinyin":"wu'li"},{"word":"无脑畸形","pinyin":"wu'nao'ji'xing"},{"word":"无尿症","pinyin":"wu'niao'zheng"},{"word":"细胞介导免疫反应","pinyin":"xi'bao'jie'dao'mian'yi'fan'ying"},{"word":"细菌感染","pinyin":"xi'jun'gan'ran"},{"word":"吸收不良","pinyin":"xi'shou'bu'liang"},{"word":"下丘脑垂体功能不全","pinyin":"xia'qiu'nao'chui'ti'gong'neng'bu'quan"},{"word":"下肢痉挛","pinyin":"xia'zhi'jing'luan"},{"word":"下肢痛","pinyin":"xia'zhi'tong"},{"word":"腺病毒感染","pinyin":"xian'bing'du'gan'ran"},{"word":"腺瘤","pinyin":"xian'liu"},{"word":"腺体肥大","pinyin":"xian'ti'fei'da"},{"word":"先天性白内障","pinyin":"xian'tian'xing'bai'nei'zhang"},{"word":"先天性驰缓性麻痹","pinyin":"xian'tian'xing'chi'huan'xing'ma'bi"},{"word":"先天性多毛症","pinyin":"xian'tian'xing'duo'mao'zheng"},{"word":"先天性耳聋","pinyin":"xian'tian'xing'er'long"},{"word":"先天性二肢缺肢畸形","pinyin":"xian'tian'xing'er'zhi'que'zhi'ji'xing"},{"word":"先天性肺动脉瓣狭窄","pinyin":"xian'tian'xing'fei'dong'mai'ban'xia'zhai"},{"word":"先天性黑变病","pinyin":"xian'tian'xing'hei'bian'bing"},{"word":"先天性甲病","pinyin":"xian'tian'xing'jia'bing"},{"word":"先天性甲状腺功能减退","pinyin":"xian'tian'xing'jia'zhuang'xian'gong'neng'jian'tui"},{"word":"先天性甲状腺肿","pinyin":"xian'tian'xing'jia'zhuang'xian'zhong"},{"word":"先天性痉挛性麻痹","pinyin":"xian'tian'xing'jing'luan'xing'ma'bi"},{"word":"先天性巨结肠","pinyin":"xian'tian'xing'ju'jie'chang"},{"word":"先天性脑损害","pinyin":"xian'tian'xing'nao'sun'hai"},{"word":"先天性缺肢畸形","pinyin":"xian'tian'xing'que'zhi'ji'xing"},{"word":"先天性三肢缺肢畸形","pinyin":"xian'tian'xing'san'zhi'que'zhi'ji'xing"},{"word":"先天性疝","pinyin":"xian'tian'xing'shan"},{"word":"先天性肾上腺生殖综合征","pinyin":"xian'tian'xing'shen'shang'xian'sheng'zhi'zong'he'zheng"},{"word":"先天性失明","pinyin":"xian'tian'xing'shi'ming"},{"word":"先天性四肢缺肢畸形","pinyin":"xian'tian'xing'si'zhi'que'zhi'ji'xing"},{"word":"先天性听力障碍","pinyin":"xian'tian'xing'ting'li'zhang'ai"},{"word":"先天性眼球震颤","pinyin":"xian'tian'xing'yan'qiu'zhen'chan"},{"word":"先天性一肢缺肢畸形","pinyin":"xian'tian'xing'yi'zhi'que'zhi'ji'xing"},{"word":"先天性子宫异常","pinyin":"xian'tian'xing'zi'gong'yi'chang"},{"word":"先天愚型","pinyin":"xian'tian'yu'xing"},{"word":"纤维蛋白溶解增加","pinyin":"xian'wei'dan'bai'rong'jie'zeng'jia"},{"word":"纤维囊性乳腺炎","pinyin":"xian'wei'nang'xing'ru'xian'yan"},{"word":"纤维性肺泡炎","pinyin":"xian'wei'xing'fei'pao'yan"},{"word":"纤维性海绵体炎","pinyin":"xian'wei'xing'hai'mian'ti'yan"},{"word":"涎腺炎","pinyin":"xian'xian'yan"},{"word":"先兆","pinyin":"xian'zhao"},{"word":"先兆子痫","pinyin":"xian'zhao'zi'xian"},{"word":"小肠坏疽","pinyin":"xiao'chang'huai'ju"},{"word":"小肠结膜炎","pinyin":"xiao'chang'jie'mo'yan"},{"word":"小肠局部缺血","pinyin":"xiao'chang'ju'bu'que'xue"},{"word":"哮喘","pinyin":"xiao'chuan"},{"word":"小红细胞性贫血","pinyin":"xiao'hong'xi'bao'xing'pin'xue"},{"word":"消化不良","pinyin":"xiao'hua'bu'liang"},{"word":"消化性溃疡","pinyin":"xiao'hua'xing'kui'yang"},{"word":"消化性溃疡出血","pinyin":"xiao'hua'xing'kui'yang'chu'xie"},{"word":"消化性溃疡穿孔","pinyin":"xiao'hua'xing'kui'yang'chuan'kong"},{"word":"消化性溃疡复发","pinyin":"xiao'hua'xing'kui'yang'fu'fa"},{"word":"消化性溃疡加重","pinyin":"xiao'hua'xing'kui'yang'jia'zhong"},{"word":"小脑综合征","pinyin":"xiao'nao'zong'he'zheng"},{"word":"小头","pinyin":"xiao'tou"},{"word":"斜颈","pinyin":"xie'jing"},{"word":"血块回缩滞后","pinyin":"xie'kuai'hui'suo'zhi'hou"},{"word":"血块栓塞","pinyin":"xie'kuai'shuan'se"},{"word":"斜视","pinyin":"xie'shi"},{"word":"协调异常","pinyin":"xie'tiao'yi'chang"},{"word":"心瓣膜病","pinyin":"xin'ban'mo'bing"},{"word":"心瓣膜置换术","pinyin":"xin'ban'mo'zhi'huan'shu"},{"word":"心包积血","pinyin":"xin'bao'ji'xue"},{"word":"心包积液","pinyin":"xin'bao'ji'ye"},{"word":"心包炎","pinyin":"xin'bao'yan"},{"word":"心电图异常","pinyin":"xin'dian'tu'yi'chang"},{"word":"心动过缓","pinyin":"xin'dong'guo'huan"},{"word":"心动过速","pinyin":"xin'dong'guo'su"},{"word":"心动徐缓","pinyin":"xin'dong'xu'huan"},{"word":"心功能不全","pinyin":"xin'gong'neng'bu'quan"},{"word":"心悸","pinyin":"xin'ji"},{"word":"心肌病","pinyin":"xin'ji'bing"},{"word":"心肌梗死","pinyin":"xin'ji'geng'si"},{"word":"心肌酶升高","pinyin":"xin'ji'mei'sheng'gao"},{"word":"心肌缺血","pinyin":"xin'ji'que'xue"},{"word":"心肌纤维化","pinyin":"xin'ji'xian'wei'hua"},{"word":"心肌炎","pinyin":"xin'ji'yan"},{"word":"心绞痛","pinyin":"xin'jiao'tong"},{"word":"心绞痛加重","pinyin":"xin'jiao'tong'jia'zhong"},{"word":"欣快感","pinyin":"xin'kuai'gan"},{"word":"心理缺陷","pinyin":"xin'li'que'xian"},{"word":"心力衰竭","pinyin":"xin'li'shuai'jie"},{"word":"心律失常","pinyin":"xin'lv'shi'chang"},{"word":"心律失常未特指","pinyin":"xin'lv'shi'chang'wei'te'zhi"},{"word":"心酶增加","pinyin":"xin'mei'zeng'jia"},{"word":"心内膜纤维化","pinyin":"xin'nei'mo'xian'wei'hua"},{"word":"心内膜炎","pinyin":"xin'nei'mo'yan"},{"word":"心前区痛","pinyin":"xin'qian'qu'tong"},{"word":"锌缺乏","pinyin":"xin'que'fa"},{"word":"新生儿白细胞减少","pinyin":"xin'sheng'er'bai'xi'bao'jian'shao"},{"word":"新生儿白血病","pinyin":"xin'sheng'er'bai'xue'bing"},{"word":"新生儿病","pinyin":"xin'sheng'er'bing"},{"word":"新生儿撤药性综合征","pinyin":"xin'sheng'er'che'yao'xing'zong'he'zheng"},{"word":"新生儿低血糖","pinyin":"xin'sheng'er'di'xue'tang"},{"word":"新生儿发热","pinyin":"xin'sheng'er'fa're"},{"word":"新生儿肺膨胀不全","pinyin":"xin'sheng'er'fei'peng'zhang'bu'quan"},{"word":"新生儿非特异性出血","pinyin":"xin'sheng'er'fei'te'yi'xing'chu'xie"},{"word":"新生儿腹泻","pinyin":"xin'sheng'er'fu'xie"},{"word":"新生儿肝脾大","pinyin":"xin'sheng'er'gan'pi'da"},{"word":"新生儿肝细胞损害","pinyin":"xin'sheng'er'gan'xi'bao'sun'hai"},{"word":"新生儿肝炎","pinyin":"xin'sheng'er'gan'yan"},{"word":"新生儿呼吸道出血","pinyin":"xin'sheng'er'hu'xi'dao'chu'xie"},{"word":"新生儿呼吸窘迫综合征","pinyin":"xin'sheng'er'hu'xi'jiong'po'zong'he'zheng"},{"word":"新生儿呼吸系统疾病","pinyin":"xin'sheng'er'hu'xi'xi'tong'ji'bing"},{"word":"新生儿呼吸抑制","pinyin":"xin'sheng'er'hu'xi'yi'zhi"},{"word":"新生儿坏疽","pinyin":"xin'sheng'er'huai'ju"},{"word":"新生儿黄疸","pinyin":"xin'sheng'er'huang'dan"},{"word":"新生儿肌张力减退","pinyin":"xin'sheng'er'ji'zhang'li'jian'tui"},{"word":"新生儿焦虑不安","pinyin":"xin'sheng'er'jiao'lv'bu'an"},{"word":"新生儿进食病","pinyin":"xin'sheng'er'jin'shi'bing"},{"word":"新生儿惊厥","pinyin":"xin'sheng'er'jing'jue"},{"word":"新生儿麻痹性肠梗阻","pinyin":"xin'sheng'er'ma'bi'xing'chang'geng'zu"},{"word":"新生儿脑病","pinyin":"xin'sheng'er'nao'bing"},{"word":"新生儿脑出血","pinyin":"xin'sheng'er'nao'chu'xue"},{"word":"新生儿尿道感染","pinyin":"xin'sheng'er'niao'dao'gan'ran"},{"word":"新生儿凝血障碍","pinyin":"xin'sheng'er'ning'xue'zhang'ai"},{"word":"新生儿脓毒病","pinyin":"xin'sheng'er'nong'du'bing"},{"word":"新生儿呕吐","pinyin":"xin'sheng'er'ou'tu"},{"word":"新生儿贫血","pinyin":"xin'sheng'er'pin'xue"},{"word":"新生儿视觉异常","pinyin":"xin'sheng'er'shi'jue'yi'chang"},{"word":"新生儿嗜睡","pinyin":"xin'sheng'er'shi'shui"},{"word":"新生儿死亡","pinyin":"xin'sheng'er'si'wang"},{"word":"新生儿体重减少","pinyin":"xin'sheng'er'ti'zhong'jian'shao"},{"word":"新生儿心律不齐","pinyin":"xin'sheng'er'xin'lv'bu'qi"},{"word":"新生儿心脏停搏","pinyin":"xin'sheng'er'xin'zang'ting'bo"},{"word":"新生儿血栓性静脉炎","pinyin":"xin'sheng'er'xue'shuan'xing'jing'mai'yan"},{"word":"新生儿血小板减少","pinyin":"xin'sheng'er'xue'xiao'ban'jian'shao"},{"word":"新生儿循环衰竭","pinyin":"xin'sheng'er'xun'huan'shuai'jie"},{"word":"新生儿厌食","pinyin":"xin'sheng'er'yan'shi"},{"word":"新生儿运动过度","pinyin":"xin'sheng'er'yun'dong'guo'du"},{"word":"新生儿运动减少","pinyin":"xin'sheng'er'yun'dong'jian'shao"},{"word":"新生儿运动障碍","pinyin":"xin'sheng'er'yun'dong'zhang'ai"},{"word":"新生儿疹","pinyin":"xin'sheng'er'zhen"},{"word":"新生儿震颤","pinyin":"xin'sheng'er'zhen'chan"},{"word":"新生儿窒息","pinyin":"xin'sheng'er'zhi'xi"},{"word":"新生儿紫癜","pinyin":"xin'sheng'er'zi'dian"},{"word":"新生儿紫绀","pinyin":"xin'sheng'er'zi'gan"},{"word":"心室颤动","pinyin":"xin'shi'chan'dong"},{"word":"心跳骤停","pinyin":"xin'tiao'zhou'ting"},{"word":"心脏病","pinyin":"xin'zang'bing"},{"word":"心脏传导阻滞","pinyin":"xin'zang'chuan'dao'zu'zhi"},{"word":"心脏毒性未特指","pinyin":"xin'zang'du'xing'wei'te'zhi"},{"word":"心脏肥大","pinyin":"xin'zang'fei'da"},{"word":"心脏畸形","pinyin":"xin'zang'ji'xing"},{"word":"心脏起搏器","pinyin":"xin'zang'qi'bo'qi"},{"word":"心脏停搏","pinyin":"xin'zang'ting'bo"},{"word":"心脏纤颤","pinyin":"xin'zang'xian'chan"},{"word":"性染色体病","pinyin":"xing'ran'se'ti'bing"},{"word":"性欲高潮异常","pinyin":"xing'yu'gao'chao'yi'chang"},{"word":"性欲减退","pinyin":"xing'yu'jian'tui"},{"word":"性欲增加","pinyin":"xing'yu'zeng'jia"},{"word":"胸骨下痛","pinyin":"xiong'gu'xia'tong"},{"word":"胸淋巴结病","pinyin":"xiong'lin'ba'jie'bing"},{"word":"胸膜间皮瘤","pinyin":"xiong'mo'jian'pi'liu"},{"word":"胸膜痛","pinyin":"xiong'mo'tong"},{"word":"胸膜纤维化","pinyin":"xiong'mo'xian'wei'hua"},{"word":"胸膜炎","pinyin":"xiong'mo'yan"},{"word":"胸腔积液","pinyin":"xiong'qiang'ji'ye"},{"word":"胸痛","pinyin":"xiong'tong"},{"word":"胸透异常","pinyin":"xiong'tou'yi'chang"},{"word":"胸腺肥大","pinyin":"xiong'xian'fei'da"},{"word":"雄性激素缺乏","pinyin":"xiong'xing'ji'su'que'fa"},{"word":"嗅觉倒错","pinyin":"xiu'jue'dao'cuo"},{"word":"溴疹","pinyin":"xiu'zhen"},{"word":"溴中毒","pinyin":"xiu'zhong'du"},{"word":"眩晕","pinyin":"xuan'yun"},{"word":"血沉加快","pinyin":"xue'chen'jia'kuai"},{"word":"血管病","pinyin":"xue'guan'bing"},{"word":"血管成形术","pinyin":"xue'guan'cheng'xing'shu"},{"word":"血管痉挛","pinyin":"xue'guan'jing'luan"},{"word":"血管扩张","pinyin":"xue'guan'kuo'zhang"},{"word":"血管神经性水肿","pinyin":"xue'guan'shen'jing'xing'shui'zhong"},{"word":"血管舒张","pinyin":"xue'guan'shu'zhang"},{"word":"血管异常","pinyin":"xue'guan'yi'chang"},{"word":"血红蛋白过多","pinyin":"xue'hong'dan'bai'guo'duo"},{"word":"血浆渗透压升高","pinyin":"xue'jiang'shen'tou'ya'sheng'gao"},{"word":"血浆酮蓝蛋白增加","pinyin":"xue'jiang'tong'lan'dan'bai'zeng'jia"},{"word":"血浆纤维蛋白原减少","pinyin":"xue'jiang'xian'wei'dan'bai'yuan'jian'shao"},{"word":"血浆纤维蛋白原增加","pinyin":"xue'jiang'xian'wei'dan'bai'yuan'zeng'jia"},{"word":"血尿","pinyin":"xue'niao"},{"word":"血尿素氮增高","pinyin":"xue'niao'su'dan'zeng'gao"},{"word":"血尿素氮增加","pinyin":"xue'niao'su'dan'zeng'jia"},{"word":"血清病","pinyin":"xue'qing'bing"},{"word":"血清蛋白结合碘减少","pinyin":"xue'qing'dan'bai'jie'he'dian'jian'shao"},{"word":"血清蛋白结合碘增加","pinyin":"xue'qing'dan'bai'jie'he'dian'zeng'jia"},{"word":"血清肉毒碱增加","pinyin":"xue'qing'rou'du'jian'zeng'jia"},{"word":"血清铁减少","pinyin":"xue'qing'tie'jian'shao"},{"word":"血清铁增加","pinyin":"xue'qing'tie'zeng'jia"},{"word":"血清叶酸试验异常","pinyin":"xue'qing'ye'suan'shi'yan'yi'chang"},{"word":"血清叶酸盐试验异常","pinyin":"xue'qing'ye'suan'yan'shi'yan'yi'chang"},{"word":"血容量增加","pinyin":"xue'rong'liang'zeng'jia"},{"word":"血色素沉着","pinyin":"xue'se'su'chen'zhuo"},{"word":"血色素正常性贫血","pinyin":"xue'se'su'zheng'chang'xing'pin'xue"},{"word":"血栓栓塞","pinyin":"xue'shuan'shuan'se"},{"word":"血栓形成","pinyin":"xue'shuan'xing'cheng"},{"word":"血栓性静脉炎","pinyin":"xue'shuan'xing'jing'mai'yan"},{"word":"血小板减少","pinyin":"xue'xiao'ban'jian'shao"},{"word":"血小板减少性紫癜","pinyin":"xue'xiao'ban'jian'shao'xing'zi'dian"},{"word":"血小板减少血栓形成性紫癜","pinyin":"xue'xiao'ban'jian'shao'xue'shuan'xing'cheng'xing'zi'dian"},{"word":"血小板粘性降低","pinyin":"xue'xiao'ban'nian'xing'jiang'di"},{"word":"血小板粘性升高","pinyin":"xue'xiao'ban'nian'xing'sheng'gao"},{"word":"血小板异常","pinyin":"xue'xiao'ban'yi'chang"},{"word":"血小板增多","pinyin":"xue'xiao'ban'zeng'duo"},{"word":"血性腹泻","pinyin":"xue'xing'fu'xie"},{"word":"血胸","pinyin":"xue'xiong"},{"word":"血药浓度降低","pinyin":"xue'yao'nong'du'jiang'di"},{"word":"血药浓度增高","pinyin":"xue'yao'nong'du'zeng'gao"},{"word":"血质不调","pinyin":"xue'zhi'bu'tiao"},{"word":"血肿","pinyin":"xue'zhong"},{"word":"循环精神病样反应","pinyin":"xun'huan'jing'shen'bing'yang'fan'ying"},{"word":"循环衰竭","pinyin":"xun'huan'shuai'jie"},{"word":"荨麻疹","pinyin":"xun'ma'zhen"},{"word":"牙变色","pinyin":"ya'bian'se"},{"word":"牙病","pinyin":"ya'bing"},{"word":"牙发育不良","pinyin":"ya'fa'yu'bu'liang"},{"word":"牙畸形","pinyin":"ya'ji'xing"},{"word":"牙痛","pinyin":"ya'tong"},{"word":"牙龈变色","pinyin":"ya'yin'bian'se"},{"word":"牙龈出血","pinyin":"ya'yin'chu'xue"},{"word":"牙龈退缩","pinyin":"ya'yin'tui'suo"},{"word":"牙龈萎缩","pinyin":"ya'yin'wei'suo"},{"word":"牙龈炎","pinyin":"ya'yin'yan"},{"word":"牙龈增生","pinyin":"ya'yin'zeng'sheng"},{"word":"牙周病","pinyin":"ya'zhou'bing"},{"word":"眼出血","pinyin":"yan'chu'xie"},{"word":"眼肌麻痹","pinyin":"yan'ji'ma'bi"},{"word":"眼畸形","pinyin":"yan'ji'xing"},{"word":"眼睑回缩","pinyin":"yan'jian'hui'suo"},{"word":"眼睑痉挛","pinyin":"yan'jian'jing'luan"},{"word":"眼睑下垂","pinyin":"yan'jian'xia'chui"},{"word":"眼睑炎","pinyin":"yan'jian'yan"},{"word":"眼疱疹","pinyin":"yan'pao'zhen"},{"word":"眼球突出","pinyin":"yan'qiu'tu'chu"},{"word":"眼球震颤","pinyin":"yan'qiu'zhen'chan"},{"word":"厌食","pinyin":"yan'shi"},{"word":"咽水肿","pinyin":"yan'shui'zhong"},{"word":"延髓麻痹","pinyin":"yan'sui'ma'bi"},{"word":"延髓神经炎","pinyin":"yan'sui'shen'jing'yan"},{"word":"眼痛","pinyin":"yan'tong"},{"word":"咽下困难","pinyin":"yan'xia'kun'nan"},{"word":"眼压增高","pinyin":"yan'ya'zeng'gao"},{"word":"咽炎","pinyin":"yan'yan"},{"word":"眼异常","pinyin":"yan'yi'chang"},{"word":"羊膜腔穿刺术异常","pinyin":"yang'mo'qiang'chuan'ci'shu'yi'chang"},{"word":"羊水过多","pinyin":"yang'shui'guo'duo"},{"word":"羊水过少","pinyin":"yang'shui'guo'shao"},{"word":"阳痿","pinyin":"yang'wei"},{"word":"腰背痛","pinyin":"yao'bei'tong"},{"word":"药物滥用","pinyin":"yao'wu'lan'yong"},{"word":"药物特异性抗体","pinyin":"yao'wu'te'yi'xing'kang'ti"},{"word":"药物无效","pinyin":"yao'wu'wu'xiao"},{"word":"药物依赖性","pinyin":"yao'wu'yi'lai'xing"},{"word":"夜盲","pinyin":"ye'mang"},{"word":"夜尿症","pinyin":"ye'niao'zheng"},{"word":"叶酸缺乏性贫血","pinyin":"ye'suan'que'fa'xing'pin'xue"},{"word":"液体过剩","pinyin":"ye'ti'guo'sheng"},{"word":"液体潴留","pinyin":"ye'ti'zhu'liu"},{"word":"癔病","pinyin":"yi'bing"},{"word":"异常出血","pinyin":"yi'chang'chu'xie"},{"word":"异常巨核细胞症","pinyin":"yi'chang'ju'he'xi'bao'zheng"},{"word":"异常色素沉着","pinyin":"yi'chang'se'su'chen'zhuo"},{"word":"乙醇不耐受","pinyin":"yi'chun'bu'nai'shou"},{"word":"遗精","pinyin":"yi'jing"},{"word":"依赖性水肿","pinyin":"yi'lai'xing'shui'zhong"},{"word":"意识模糊","pinyin":"yi'shi'mo'hu"},{"word":"意外疗效","pinyin":"yi'wai'liao'xiao"},{"word":"意外妊娠","pinyin":"yi'wai'ren'shen"},{"word":"异位妊娠","pinyin":"yi'wei'ren'shen"},{"word":"异物创伤","pinyin":"yi'wu'chuang'shang"},{"word":"异物吸入","pinyin":"yi'wu'xi'ru"},{"word":"胰腺病","pinyin":"yi'xian'bing"},{"word":"胰腺囊肿","pinyin":"yi'xian'nang'zhong"},{"word":"胰腺炎","pinyin":"yi'xian'yan"},{"word":"抑郁","pinyin":"yi'yu"},{"word":"抑郁加重","pinyin":"yi'yu'jia'zhong"},{"word":"咿扎音","pinyin":"yi'zha'yin"},{"word":"阴道闭锁","pinyin":"yin'dao'bi'suo"},{"word":"阴道出血","pinyin":"yin'dao'chu'xue"},{"word":"阴道恶性瘤","pinyin":"yin'dao'e'xing'liu"},{"word":"阴道疾病","pinyin":"yin'dao'ji'bing"},{"word":"阴道良性瘤","pinyin":"yin'dao'liang'xing'liu"},{"word":"阴道炎","pinyin":"yin'dao'yan"},{"word":"隐睾病","pinyin":"yin'gao'bing"},{"word":"阴户病","pinyin":"yin'hu'bing"},{"word":"阴茎病","pinyin":"yin'jing'bing"},{"word":"阴茎异常勃起","pinyin":"yin'jing'yi'chang'bo'qi"},{"word":"银屑病","pinyin":"yin'xie'bing"},{"word":"银屑病加重","pinyin":"yin'xie'bing'jia'zhong"},{"word":"银屑病样疹","pinyin":"yin'xie'bing'yang'zhen"},{"word":"银质沉着病","pinyin":"yin'zhi'chen'zhuo'bing"},{"word":"婴儿猝死综合征","pinyin":"ying'er'cu'si'zong'he'zheng"},{"word":"婴儿孤僻症","pinyin":"ying'er'gu'pi'zheng"},{"word":"硬化性腹膜炎","pinyin":"ying'hua'xing'fu'mo'yan"},{"word":"硬结","pinyin":"ying'jie"},{"word":"硬结性红斑","pinyin":"ying'jie'xing'hong'ban"},{"word":"硬皮病","pinyin":"ying'pi'bing"},{"word":"营养不良","pinyin":"ying'yang'bu'liang"},{"word":"用药部位出血","pinyin":"yong'yao'bu'wei'chu'xie"},{"word":"用药部位麻木","pinyin":"yong'yao'bu'wei'ma'mu"},{"word":"用药部位水肿","pinyin":"yong'yao'bu'wei'shui'zhong"},{"word":"用药部位疼痛","pinyin":"yong'yao'bu'wei'teng'tong"},{"word":"有关妇产科的疼痛","pinyin":"you'guan'fu'chan'ke'de'teng'tong"},{"word":"幽门狭窄","pinyin":"you'men'xia'zhai"},{"word":"右心衰竭","pinyin":"you'xin'shuai'jie"},{"word":"语言障碍","pinyin":"yu'yan'zhang'ai"},{"word":"月经过多","pinyin":"yue'jing'guo'duo"},{"word":"月经间期出血","pinyin":"yue'jing'jian'qi'chu'xie"},{"word":"月经痛","pinyin":"yue'jing'tong"},{"word":"月经紊乱","pinyin":"yue'jing'wen'luan"},{"word":"运动减少","pinyin":"yun'dong'jian'shao"},{"word":"运动神经炎","pinyin":"yun'dong'shen'jing'yan"},{"word":"运动障碍","pinyin":"yun'dong'zhang'ai"},{"word":"晕厥","pinyin":"yun'jue"},{"word":"再生不良性贫血","pinyin":"zai'sheng'bu'liang'xing'pin'xue"},{"word":"再生障碍性贫血","pinyin":"zai'sheng'zhang'ai'xing'pin'xue"},{"word":"暂时性失明","pinyin":"zan'shi'xing'shi'ming"},{"word":"早产","pinyin":"zao'chan"},{"word":"躁狂","pinyin":"zao'kuang"},{"word":"躁狂反应","pinyin":"zao'kuang'fan'ying"},{"word":"早泄","pinyin":"zao'xie"},{"word":"谵妄","pinyin":"zhan'wang"},{"word":"张力减退","pinyin":"zhang'li'jian'tui"},{"word":"张力亢进","pinyin":"zhang'li'kang'jin"},{"word":"张力障碍","pinyin":"zhang'li'zhang'ai"},{"word":"震颤","pinyin":"zhen'chan"},{"word":"震荡","pinyin":"zhen'dang"},{"word":"镇静","pinyin":"zhen'jing"},{"word":"真菌感染","pinyin":"zhen'jun'gan'ran"},{"word":"正常红细胞性贫血","pinyin":"zheng'chang'hong'xi'bao'xing'pin'xue"},{"word":"正铁血红蛋白尿","pinyin":"zheng'tie'xue'hong'dan'bai'niao"},{"word":"正铁血红蛋白血","pinyin":"zheng'tie'xue'hong'dan'bai'xue"},{"word":"致癌致突变致畸的药物","pinyin":"zhi'ai'zhi'tu'bian'zhi'ji'de'yao'wu"},{"word":"直肠癌","pinyin":"zhi'chang'ai"},{"word":"直肠病","pinyin":"zhi'chang'bing"},{"word":"直肠出血","pinyin":"zhi'chang'chu'xie"},{"word":"直肠炎","pinyin":"zhi'chang'yan"},{"word":"脂沉积","pinyin":"zhi'chen'ji"},{"word":"痔疮","pinyin":"zhi'chuang"},{"word":"痔疮栓塞","pinyin":"zhi'chuang'shuan'se"},{"word":"脂肪病","pinyin":"zhi'fang'bing"},{"word":"脂肪肝","pinyin":"zhi'fang'gan"},{"word":"脂肪瘤","pinyin":"zhi'fang'liu"},{"word":"脂肪萎缩","pinyin":"zhi'fang'wei'suo"},{"word":"脂肪泻","pinyin":"zhi'fang'xie"},{"word":"脂肪再分布","pinyin":"zhi'fang'zai'fen'bu"},{"word":"肢畸形","pinyin":"zhi'ji'xing"},{"word":"脂膜炎","pinyin":"zhi'mo'yan"},{"word":"支气管痉挛","pinyin":"zhi'qi'guan'jing'luan"},{"word":"支气管痉挛加重","pinyin":"zhi'qi'guan'jing'luan'jia'zhong"},{"word":"支气管扩张","pinyin":"zhi'qi'guan'kuo'zhang"},{"word":"支气管瘤","pinyin":"zhi'qi'guan'liu"},{"word":"支气管狭窄","pinyin":"zhi'qi'guan'xia'zhai"},{"word":"支气管炎","pinyin":"zhi'qi'guan'yan"},{"word":"植入并发症","pinyin":"zhi'ru'bing'fa'zheng"},{"word":"肢体栓塞","pinyin":"zhi'ti'shuan'se"},{"word":"窒息","pinyin":"zhi'xi"},{"word":"脂营养不良","pinyin":"zhi'ying'yang'bu'liang"},{"word":"种痘并发症","pinyin":"zhong'dou'bing'fa'zheng"},{"word":"中毒性表皮坏死症","pinyin":"zhong'du'xing'biao'pi'huai'si'zheng"},{"word":"中耳炎","pinyin":"zhong'er'yan"},{"word":"中枢神经系统抑制","pinyin":"zhong'shu'shen'jing'xi'tong'yi'zhi"},{"word":"重症肌无力样综合征","pinyin":"zhong'zheng'ji'wu'li'yang'zong'he'zheng"},{"word":"主动脉缩窄","pinyin":"zhu'dong'mai'suo'zhai"},{"word":"主动脉狭窄","pinyin":"zhu'dong'mai'xia'zhai"},{"word":"侏儒症","pinyin":"zhu'ru'zheng"},{"word":"注射部位反应","pinyin":"zhu'she'bu'wei'fan'ying"},{"word":"注射部位感染","pinyin":"zhu'she'bu'wei'gan'ran"},{"word":"注射部位坏死","pinyin":"zhu'she'bu'wei'huai'si"},{"word":"注射部位溃疡形成","pinyin":"zhu'she'bu'wei'kui'yang'xing'cheng"},{"word":"注射部位麻木","pinyin":"zhu'she'bu'wei'ma'mu"},{"word":"注射部位脓肿","pinyin":"zhu'she'bu'wei'nong'zhong"},{"word":"注射部位皮疹","pinyin":"zhu'she'bu'wei'pi'zhen"},{"word":"注射部位骚痒","pinyin":"zhu'she'bu'wei'sao'yang"},{"word":"注射部位疼痛","pinyin":"zhu'she'bu'wei'teng'tong"},{"word":"注射部位萎缩","pinyin":"zhu'she'bu'wei'wei'suo"},{"word":"注射部位纤维化","pinyin":"zhu'she'bu'wei'xian'wei'hua"},{"word":"注射部位炎症","pinyin":"zhu'she'bu'wei'yan'zheng"},{"word":"注射部位硬结","pinyin":"zhu'she'bu'wei'ying'jie"},{"word":"蛛网膜下出血","pinyin":"zhu'wang'mo'xia'chu'xie"},{"word":"蛛网膜炎","pinyin":"zhu'wang'mo'yan"},{"word":"注意力不集中","pinyin":"zhu'yi'li'bu'ji'zhong"},{"word":"注意力损伤","pinyin":"zhu'yi'li'sun'shang"},{"word":"状况恶化","pinyin":"zhuang'kuang'e'hua"},{"word":"椎间盘病","pinyin":"zhui'jian'pan'bing"},{"word":"锥体外系病","pinyin":"zhui'ti'wai'xi'bing"},{"word":"锥体外系反应","pinyin":"zhui'ti'wai'xi'fan'ying"},{"word":"紫癜","pinyin":"zi'dian"},{"word":"紫癜性疹","pinyin":"zi'dian'xing'zhen"},{"word":"自动症","pinyin":"zi'dong'zheng"},{"word":"自发性血小板减少性紫癜","pinyin":"zi'fa'xing'xue'xiao'ban'jian'shao'xing'zi'dian"},{"word":"紫绀","pinyin":"zi'gan"},{"word":"子宫癌","pinyin":"zi'gong'ai"},{"word":"子宫出血","pinyin":"zi'gong'chu'xie"},{"word":"子宫穿孔","pinyin":"zi'gong'chuan'kong"},{"word":"子宫肌层增厚","pinyin":"zi'gong'ji'ceng'zeng'hou"},{"word":"子宫肌瘤","pinyin":"zi'gong'ji'liu"},{"word":"子宫痉挛","pinyin":"zi'gong'jing'luan"},{"word":"子宫内膜癌","pinyin":"zi'gong'nei'mo'ai"},{"word":"子宫内膜病","pinyin":"zi'gong'nei'mo'bing"},{"word":"子宫内膜发育不全","pinyin":"zi'gong'nei'mo'fa'yu'bu'quan"},{"word":"子宫内膜炎","pinyin":"zi'gong'nei'mo'yan"},{"word":"子宫内膜异位症","pinyin":"zi'gong'nei'mo'yi'wei'zheng"},{"word":"子宫内膜增生","pinyin":"zi'gong'nei'mo'zeng'sheng"},{"word":"子宫内膜增长","pinyin":"zi'gong'nei'mo'zeng'zhang"},{"word":"子宫切除术","pinyin":"zi'gong'qie'chu'shu"},{"word":"子宫收缩","pinyin":"zi'gong'shou'suo"},{"word":"子宫张力缺乏","pinyin":"zi'gong'zhang'li'que'fa"},{"word":"子宫肿瘤","pinyin":"zi'gong'zhong'liu"},{"word":"自杀企图","pinyin":"zi'sha'qi'tu"},{"word":"自体抗体反应","pinyin":"zi'ti'kang'ti'fan'ying"},{"word":"子痫","pinyin":"zi'xian"},{"word":"纵膈纤维化","pinyin":"zong'ge'xian'wei'hua"},{"word":"纵隔肿瘤","pinyin":"zong'ge'zhong'liu"},{"word":"综合征","pinyin":"zong'he'zheng"},{"word":"组织细胞增多症","pinyin":"zu'zhi'xi'bao'zeng'duo'zheng"},{"word":"做梦异常","pinyin":"zuo'meng'yi'chang"},{"word":"左心衰竭","pinyin":"zuo'xin'shuai'jie"}]}