{"name":"常用人名131345646746413245631","type":"其它","description":"部门常用人名","example":"穆雪飞 牛魁明 魏苒  李金雨 王志强 ","words":[{"word":"白世伟","pinyin":"bai'shi'wei"},{"word":"常文达","pinyin":"chang'wen'da"},{"word":"关悦","pinyin":"guan'yue"},{"word":"郝少鹏","pinyin":"hao'shao'peng"},{"word":"贺树猛","pinyin":"he'shu'meng"},{"word":"贾国福","pinyin":"jia'guo'fu"},{"word":"解波","pinyin":"jie'bo"},{"word":"李达","pinyin":"li'da"},{"word":"李金雨","pinyin":"li'jin'yu"},{"word":"李鹏","pinyin":"li'peng"},{"word":"李强","pinyin":"li'qiang"},{"word":"梁鑫鹏","pinyin":"liang'xin'peng"},{"word":"林洋","pinyin":"lin'yang"},{"word":"刘毅","pinyin":"liu'yi"},{"word":"穆雪飞","pinyin":"mu'xue'fei"},{"word":"牛魁明","pinyin":"niu'kui'ming"},{"word":"庞成飞","pinyin":"pang'cheng'fei"},{"word":"孙世龙","pinyin":"sun'shi'long"},{"word":"王志强","pinyin":"wang'zhi'qiang"},{"word":"魏苒","pinyin":"wei'ran"},{"word":"徐舒","pinyin":"xu'shu"},{"word":"易英杰","pinyin":"yi'ying'jie"},{"word":"尹航","pinyin":"yin'hang"},{"word":"詹迪克","pinyin":"zhan'di'ke"},{"word":"张宝","pinyin":"zhang'bao"},{"word":"张港","pinyin":"zhang'gang"},{"word":"张浩宇","pinyin":"zhang'hao'yu"},{"word":"张琦","pinyin":"zhang'qi"},{"word":"周建业","pinyin":"zhou'jian'ye"},{"word":"祝文飞","pinyin":"zhu'wen'fei"}]}