{"name":"常用徽州话正字","type":"语言学","description":"徽州，今安徽黄山市、绩溪县及江西婺源县。\n\n徽語又叫徽州話，是一種分佈在新安江流域及周邊以古徽州府為核心區域的漢語方言。在相當長的時期內，被認為是吳語的一個方言，在《中國語言地圖集》出版前後它被承認是漢語中一種獨立方言，但關於其歸屬至今仍有爭議。有觀點指出，徽語與吳語、閩語共同起源于古代江東方言，現代徽語分化于吳語，吳語與徽語可被視為同屬一個方言大區。","example":"细风 冰冻 落雪 温暾水 夜间 先头 ","words":[{"word":"挨夜边","pinyin":"ai'ye'bian"},{"word":"苞萝","pinyin":"bao'luo"},{"word":"畚出","pinyin":"ben'chu"},{"word":"鼻孔","pinyin":"bi'kong"},{"word":"鼻孔水","pinyin":"bi'kong'shui"},{"word":"鼻孔眼","pinyin":"bi'kong'yan"},{"word":"扁荚","pinyin":"bian'jia"},{"word":"冰冻","pinyin":"bing'dong"},{"word":"伯娘","pinyin":"bo'niang"},{"word":"伯爷","pinyin":"bo'ye"},{"word":"布翼儿","pinyin":"bu'yi'er"},{"word":"插米舅","pinyin":"cha'mi'jiu"},{"word":"晨光早","pinyin":"chen'guang'zao"},{"word":"吃当昼","pinyin":"chi'dang'zhou"},{"word":"吃酒","pinyin":"chi'jiu"},{"word":"吃零碎","pinyin":"chi'ling'sui"},{"word":"吃天光","pinyin":"chi'tian'guang"},{"word":"吃烟","pinyin":"chi'yan"},{"word":"吃夜饭","pinyin":"chi'ye'fan"},{"word":"大后日","pinyin":"da'hou'ri"},{"word":"大郎","pinyin":"da'lang"},{"word":"打露水","pinyin":"da'lu'shui"},{"word":"大髈","pinyin":"da'pang"},{"word":"大前日","pinyin":"da'qian'ri"},{"word":"打铁个","pinyin":"da'tie'ge"},{"word":"当昼","pinyin":"dang'zhou"},{"word":"弟妇","pinyin":"di'fu"},{"word":"弟郎","pinyin":"di'lang"},{"word":"点灯星","pinyin":"dian'deng'xing"},{"word":"跌头发","pinyin":"die'tou'fa"},{"word":"肚里痛","pinyin":"du'li'tong"},{"word":"反手","pinyin":"fan'shou"},{"word":"阁板","pinyin":"ge'ban"},{"word":"阁楼梯","pinyin":"ge'lou'ti"},{"word":"胳落荚","pinyin":"ge'luo'jia"},{"word":"阁上","pinyin":"ge'shang"},{"word":"阁下","pinyin":"ge'xia"},{"word":"滚水","pinyin":"gun'shui"},{"word":"蛤蟆","pinyin":"ha'ma"},{"word":"河恨","pinyin":"he'hen"},{"word":"河螺扁","pinyin":"he'luo'bian"},{"word":"红苕","pinyin":"hong'shao"},{"word":"后日","pinyin":"hou'ri"},{"word":"猴狲","pinyin":"hou'sun"},{"word":"鸡公","pinyin":"ji'gong"},{"word":"鸡母","pinyin":"ji'mu"},{"word":"鸡子","pinyin":"ji'zi"},{"word":"鸡子糕","pinyin":"ji'zi'gao"},{"word":"嫁妮","pinyin":"jia'ni"},{"word":"肩膊","pinyin":"jian'bo"},{"word":"今日","pinyin":"jin'ri"},{"word":"井索","pinyin":"jing'suo"},{"word":"旧年","pinyin":"jiu'nian"},{"word":"酒酿","pinyin":"jiu'niang"},{"word":"舅爷","pinyin":"jiu'ye"},{"word":"槛窗","pinyin":"kan'chuang"},{"word":"拉叭布翼","pinyin":"la'ba'bu'yi"},{"word":"癞宝个","pinyin":"lai'bao'ge"},{"word":"老朝","pinyin":"lao'chao"},{"word":"老太","pinyin":"lao'tai"},{"word":"礼拜日","pinyin":"li'bai'ri"},{"word":"令妹","pinyin":"ling'mei"},{"word":"令妹夫","pinyin":"ling'mei'fu"},{"word":"萝卜鸡子","pinyin":"luo'bo'ji'zi"},{"word":"落苏","pinyin":"luo'su"},{"word":"落雪","pinyin":"luo'xue"},{"word":"落雨","pinyin":"luo'yu"},{"word":"马铃芋","pinyin":"ma'ling'yu"},{"word":"毛兔儿","pinyin":"mao'tu'er"},{"word":"每日","pinyin":"mei'ri"},{"word":"门后腋","pinyin":"men'hou'ye"},{"word":"门舌儿","pinyin":"men'she'er"},{"word":"米羹水","pinyin":"mi'geng'shui"},{"word":"面糊","pinyin":"mian'hu"},{"word":"面盆","pinyin":"mian'pen"},{"word":"面盆架","pinyin":"mian'pen'jia"},{"word":"面嘴","pinyin":"mian'zui"},{"word":"明年","pinyin":"ming'nian"},{"word":"明日","pinyin":"ming'ri"},{"word":"姆妈","pinyin":"mu'ma"},{"word":"囡儿","pinyin":"nan'er"},{"word":"囡家","pinyin":"nan'jia"},{"word":"妮儿","pinyin":"ni'er"},{"word":"伲家","pinyin":"ni'jia"},{"word":"妮家","pinyin":"ni'jia"},{"word":"妮婿","pinyin":"ni'xu"},{"word":"牛栏","pinyin":"niu'lan"},{"word":"前几年","pinyin":"qian'ji'nian"},{"word":"前几日","pinyin":"qian'ji'ri"},{"word":"前日","pinyin":"qian'ri"},{"word":"日间","pinyin":"ri'jian"},{"word":"日日夜家","pinyin":"ri'ri'ye'jia"},{"word":"日头","pinyin":"ri'tou"},{"word":"三十夜","pinyin":"san'shi'ye"},{"word":"烧酒","pinyin":"shao'jiu"},{"word":"蛇鱼","pinyin":"she'yu"},{"word":"生瓜","pinyin":"sheng'gua"},{"word":"生囡","pinyin":"sheng'nan"},{"word":"屎缸","pinyin":"shi'gang"},{"word":"十几日","pinyin":"shi'ji'ri"},{"word":"屎窟","pinyin":"shi'ku"},{"word":"屎窟眼","pinyin":"shi'ku'yan"},{"word":"顺手","pinyin":"shun'shou"},{"word":"丝瓜莲","pinyin":"si'gua'lian"},{"word":"丝瓜菩","pinyin":"si'gua'pu"},{"word":"四月荚","pinyin":"si'yue'jia"},{"word":"酸蝎","pinyin":"suan'xie"},{"word":"锁匙","pinyin":"suo'shi"},{"word":"堂前","pinyin":"tang'qian"},{"word":"天光","pinyin":"tian'guang"},{"word":"头脑壳","pinyin":"tou'nao'ke"},{"word":"头下颈","pinyin":"tou'xia'jing"},{"word":"驼子","pinyin":"tuo'zi"},{"word":"蚊虫","pinyin":"wen'chong"},{"word":"温暾水","pinyin":"wen'tun'shui"},{"word":"乌麦","pinyin":"wu'mai"},{"word":"物事","pinyin":"wu'shi"},{"word":"细白菜","pinyin":"xi'bai'cai"},{"word":"细病","pinyin":"xi'bing"},{"word":"细风","pinyin":"xi'feng"},{"word":"细路","pinyin":"xi'lu"},{"word":"细米","pinyin":"xi'mi"},{"word":"洗面","pinyin":"xi'mian"},{"word":"洗面水","pinyin":"xi'mian'shui"},{"word":"细牛","pinyin":"xi'niu"},{"word":"细雪","pinyin":"xi'xue"},{"word":"细羊","pinyin":"xi'yang"},{"word":"细雨","pinyin":"xi'yu"},{"word":"先头","pinyin":"xian'tou"},{"word":"小毛鬼","pinyin":"xiao'mao'gui"},{"word":"小指指儿","pinyin":"xiao'zhi'zhi'er"},{"word":"新妇","pinyin":"xin'fu"},{"word":"新郎倌","pinyin":"xin'lang'guan"},{"word":"新人","pinyin":"xin'ren"},{"word":"鸭子","pinyin":"ya'zi"},{"word":"晏饭","pinyin":"yan'fan"},{"word":"眼泪水","pinyin":"yan'lei'shui"},{"word":"芫荽菜","pinyin":"yan'sui'cai"},{"word":"洋幅儿","pinyin":"yang'fu'er"},{"word":"舀饭","pinyin":"yao'fan"},{"word":"夜饭","pinyin":"ye'fan"},{"word":"夜间","pinyin":"ye'jian"},{"word":"映山红","pinyin":"ying'shan'hong"},{"word":"鱼子","pinyin":"yu'zi"},{"word":"月光","pinyin":"yue'guang"},{"word":"灶下","pinyin":"zao'xia"},{"word":"折脚","pinyin":"zhe'jiao"},{"word":"指甲花","pinyin":"zhi'jia'hua"},{"word":"指指头儿","pinyin":"zhi'zhi'tou'er"},{"word":"猪栏","pinyin":"zhu'lan"},{"word":"竹翼","pinyin":"zhu'yi"},{"word":"蛛蛛","pinyin":"zhu'zhu"},{"word":"嘴涎水","pinyin":"zui'xian'shui"},{"word":"昨日","pinyin":"zuo'ri"}]}